Workbook

Sheet Indice
A1: Nombre de la Hoja | B1: Categoría | C1: Ubicación | E1: Categoría | F1: (Todas) | T1: Estadisticas
A2: Estadisticas | B2: Otros | C2: Ir a la hoja → | H2: https://compralo.revital.cloud/ | T2: Funcionales generales
A3: Funcionales generales | B3: Funcionales | C3: Ir a la hoja → | E3: Etiquetas de fila | T3: No-funcionales generales
A4: No-funcionales generales | B4: No-funcionales | C4: Ir a la hoja → | E4: Estadisticas | T4: Funcionales DB
A5: Funcionales DB | B5: Funcionales | C5: Ir a la hoja → | E5: Ir a la hoja → | H5: Credenciales Server | T5: No-funcionales DB
A6: No-funcionales DB | B6: No-funcionales | C6: Ir a la hoja → | E6: Funcionales Acerca de | H6: IP: | I6: 46.225.94.64 | T6: Funcionales Homepage
A7: Funcionales Homepage | B7: Funcionales | C7: Ir a la hoja → | E7: Ir a la hoja → | H7: user | I7: tester | T7: No-funcionales Homepage
A8: No-funcionales Homepage | B8: No-funcionales | C8: Ir a la hoja → | E8: Funcionales Atributos | H8: psw | I8: tS!@D26fBQfw*N8 | T8: Funcionales Productos
A9: Funcionales Productos | B9: Funcionales | C9: Ir a la hoja → | E9: Ir a la hoja → | H9: ssh | I9: tester@46.225.94.64 | T9: No-funcionales Productos
A10: No-funcionales Productos | B10: No-funcionales | C10: Ir a la hoja → | E10: Funcionales Ayuda | T10: Funcionales Categoria
A11: Funcionales Categoria | B11: Funcionales | C11: Ir a la hoja → | E11: Ir a la hoja → | H11: Credenciales PGADMIN | T11: No-funcionales Categoria
A12: No-funcionales Categoria | B12: No-funcionales | C12: Ir a la hoja → | E12: Funcionales barra informativa | H12: DB | I12: revital_ecommerce | T12: Funcionales Descuentos
A13: Funcionales Descuentos | B13: Funcionales | C13: Ir a la hoja → | E13: Ir a la hoja → | H13: user | I13: synkro_admin | T13: No-funcionales Descuentos
A14: No-funcionales Descuentos | B14: No-funcionales | C14: Ir a la hoja → | E14: Funcionales Bot-Admin | H14: password | I14: synkro_admin_pwd | T14: Funcionales Cookies
A15: Funcionales Cookies | B15: Funcionales | C15: Ir a la hoja → | E15: Ir a la hoja → | T15: No-funcionales Cookies
A16: No-funcionales Cookies | B16: No-funcionales | C16: Ir a la hoja → | E16: Funcionales Boton Ayuda | H16: Credenciales Software | T16: Funcionales Politicas
A17: Funcionales Politicas | B17: Funcionales | C17: Ir a la hoja → | E17: Ir a la hoja → | G17: Admin | H17: usuario | I17: ahernandezlara03@gmail.com | T17: No-funcionales Politicas
A18: No-funcionales Politicas | B18: No-funcionales | C18: Ir a la hoja → | E18: Funcionales Carrito | H18: contraseña | I18: Alejandro03* | T18: Funcionales Terminos condicione
A19: Funcionales Terminos condicione | B19: Funcionales | C19: Ir a la hoja → | E19: Ir a la hoja → | G19: Usuario | H19: usuario | I19: Debe ser creado | T19: No-funcionales Terminos Condici
A20: No-funcionales Terminos Condici | B20: No-funcionales | C20: Ir a la hoja → | E20: Funcionales Categoria | H20: contraseña | T20: Funcionales Perfil
A21: Funcionales Perfil | B21: Funcionales | C21: Ir a la hoja → | E21: Ir a la hoja → | T21: No-funcionales Perfil
A22: No-funcionales Perfil | B22: No-funcionales | C22: Ir a la hoja → | E22: Funcionales Categorías Admin | H22: Datos de Prueba Pagos Wompi | T22: Funcionales Contacto
A23: Funcionales Contacto | B23: Funcionales | C23: Ir a la hoja → | E23: Ir a la hoja → | H23: Nequi | I23: 3991111111 | T23: No-funcionales Contacto
A24: No-funcionales Contacto | B24: No-funcionales | C24: Ir a la hoja → | E24: Funcionales chatbotInformativo | H24: Tarjetas Bancolombia - Aprobado | I24: 4242 4242 4242 4242 | T24: Funcionales Seguimiento
A25: Funcionales Seguimiento | B25: Funcionales | C25: Ir a la hoja → | E25: Ir a la hoja → | H25: Tarjetas Bancolombia - Declinado | I25: 4111 1111 1111 1111 | T25: No-Funcionales Seguimiento
A26: No-Funcionales Seguimiento | B26: No-funcionales | C26: Ir a la hoja → | E26: Funcionales Checkout | T26: Funcionales Inversionistas
A27: Funcionales Inversionistas | B27: Funcionales | C27: Ir a la hoja → | E27: Ir a la hoja → | T27: No-funcionales Inversionistas
A28: No-funcionales Inversionistas | B28: No-funcionales | C28: Ir a la hoja → | E28: Funcionales Contacto | T28: Funcionales Devoluciones
A29: Funcionales Devoluciones | B29: Funcionales | C29: Ir a la hoja → | E29: Ir a la hoja → | T29: No-funcionales Devoluciones
A30: No-funcionales Devoluciones | B30: No-funcionales | C30: Ir a la hoja → | E30: Funcionales Cookies | T30: Funcionales Ayuda
A31: Funcionales Ayuda | B31: Funcionales | C31: Ir a la hoja → | E31: Ir a la hoja → | T31: No-funcionales Ayuda
A32: No-funcionales Ayuda | B32: No-funcionales | C32: Ir a la hoja → | E32: Funcionales Dashboard Admin | T32: Funcionales Prensa
A33: Funcionales Prensa | B33: Funcionales | C33: Ir a la hoja → | E33: Ir a la hoja → | T33: No-funcionales Prensa
A34: No-funcionales Prensa | B34: No-funcionales | C34: Ir a la hoja → | E34: Funcionales DB | T34: Funcionales Acerca de
A35: Funcionales Acerca de | B35: Funcionales | C35: Ir a la hoja → | E35: Ir a la hoja → | T35: No-funcionales Acerca de
A36: No-funcionales Acerca de | B36: No-funcionales | C36: Ir a la hoja → | E36: Funcionales Descuentos | T36: Funcionales chatbotInformativo
A37: Funcionales chatbotInformativo | B37: Funcionales | C37: Ir a la hoja → | E37: Ir a la hoja → | T37: No-funcionales chatbotInformati
... A56: Funcionales Categorías Admin | B56: Funcionales | C56: Ir a la hoja → | E56: Funcionales Perfil | T56: No-funcionales Categorias Admin
A57: No-funcionales Categorias Admin | B57: No-funcionales | C57: Ir a la hoja → | E57: Ir a la hoja → | S57: camilo | T57: Funcionales Usuario Admin
A58: Funcionales Usuario Admin | B58: Funcionales | C58: Ir a la hoja → | E58: Funcionales Politicas | T58: No-funcionales Usuarios Admin
A59: No-funcionales Usuarios Admin | B59: No-funcionales | C59: Ir a la hoja → | E59: Ir a la hoja → | T59: Funcionales Atributos
A60: Funcionales Atributos | B60: Funcionales | C60: Ir a la hoja → | E60: Funcionales Prensa | T60: No-funcionales Atributos
A61: No-funcionales Atributos | B61: No-funcionales | C61: Ir a la hoja → | E61: Ir a la hoja → | T61: Funcionales Marcas
A62: Funcionales Marcas | B62: Funcionales | C62: Ir a la hoja → | E62: Funcionales Producto | T62: No-funcionales Marcas
A63: No-funcionales Marcas | B63: No-funcionales | C63: Ir a la hoja → | E63: Ir a la hoja → | T63: Funcionales Proveedores Admin
A64: Funcionales Proveedores Admin | B64: Funcionales | C64: Ir a la hoja → | E64: Funcionales Productos | T64: No-funcionales Proveedores Admi
A65: No-funcionales Proveedores Admi | B65: No-funcionales | C65: Ir a la hoja → | E65: Ir a la hoja → | T65: Funcionales Descuentos Admin
A66: Funcionales Descuentos Admin | B66: Funcionales | C66: Ir a la hoja → | E66: Funcionales Productos Admin | T66: No-funcionales Descuentos Admin
A67: No-funcionales Descuentos Admin | B67: No-funcionales | C67: Ir a la hoja → | E67: Ir a la hoja → | T67: Funcionales Puntos Admin
A68: Funcionales Puntos Admin | B68: Funcionales | C68: Ir a la hoja → | E68: Funcionales Proveedores Admin | T68: No-funcionales Puntos Admin
A69: No-funcionales Puntos Admin | B69: No-funcionales | C69: Ir a la hoja → | E69: Ir a la hoja → | T69: Funcionales barra informativa
... A74: Funcionales Boton Ayuda | B74: Funcionales | C74: Ir a la hoja → | E74: Funcionales Terminos condicione | T74: No-funcionales Boton Ayuda
A75: No-funcionales Boton Ayuda | B75: No-funcionales | C75: Ir a la hoja → | E75: Ir a la hoja →
E76: Funcionales Usuario Admin
E77: Ir a la hoja →
E78: input_req
E79: Ir a la hoja →
E80: No funcionales barra informativ
E81: Ir a la hoja →
E82: No-funcionales Acerca de
E83: Ir a la hoja →
E84: No-funcionales Atributos
E85: Ir a la hoja →
E86: No-funcionales Ayuda
E87: Ir a la hoja →
... E152: Total general

Sheet Estadisticas
A1: Métrica | B1: Valor
A2: Cant. Requerimientos Funcionales | B2: ='Funcionales generales'!L3+'Funcionales DB'!L3+'Funcionales Homepage'!L3+'Funcionales Productos'!L3+'Funcionales Categoria'!L3+'Funcionales Descuentos'!L3+'Funcionales Cookies'!L3+'Funcionales Politicas'!L3+'Funcionales Terminos condicione'!L3+'Funcionales Perfil'!L3+'Funcionales Contacto'!L3+'Funcionales Seguimiento'!L3+'Funcionales Inversionistas'!L3+'Funcionales Devoluciones'!L3+'Funcionales Ayuda'!L3+'Funcionales Prensa'!L3+'Funcionales Acerca de'!L3+'Funcionales chatbotInformativo'!L3+'Funcionales LoginRegister'!L3+'Funcionales Producto'!L3+'Funcionales Carrito'!L3+'Funcionales Checkout'!L3+'Funcionales Favoritos'!L3+'Funcionales Dashboard Admin'!L3+'Funcionales Ordenes admin'!L3+'Funcionales Productos Admin'!L3+'Funcionales Categorías Admin'!L3+'Funcionales Usuario Admin'!L3+'Funcionales Atributos'!L3+'Funcionales Marcas'!L3+'Funcionales Proveedores Admin'!L3+'Funcionales Descuentos Admin'!L3+'Funcionales Puntos Admin'!L3+'Funcionales barra informativa '!L3+'No-funcionales barra informativ'!L3+'Funcionales Bot-Admin'!L3+'Funcionales Boton Ayuda'!L3 -> 490
A3: Cant. Requerimientos No-funcionales | B3: ='No-funcionales generales'!L3+'No-funcionales DB'!L3+'No-funcionales Homepage'!L3+'No-funcionales Productos'!L3+'No-funcionales Categoria'!L3+'No-funcionales Descuentos'!L3+'No-funcionales Cookies'!L3+'No-funcionales Politicas'!L3+'No-funcionales Terminos Condici'!L3+'No-funcionales Perfil'!L3+'No-funcionales Contacto'!L3+'No-Funcionales Seguimiento'!L3+'No-funcionales Inversionistas'!L3+'No-funcionales Devoluciones'!L3+'No-funcionales Ayuda'!L3+'No-funcionales Prensa'!L3+'No-funcionales Acerca de'!L3+'No-funcionales chatbotInformati'!L3+'No-funcionales LoginRegister'!L3+'No-funcionales Producto'!L3+'No-funcionales Carrito'!L3+'No-funcionales Checkout '!L3+'No-funcionales Favoritos'!L3+'No-funcionales Dashboard Admin'!L3+'No-funcionales Ordenes admin'!L3+'No-funcionales Productos Admin '!L3+'No-funcionales Categorias Admin'!L3+'No-funcionales Usuarios Admin'!L3+'No-funcionales Atributos'!L3+'No-funcionales Marcas '!L3+'No-funcionales Proveedores Admi'!L3+'No-funcionales Descuentos Admin'!L3+'No-funcionales Puntos Admin'!L3+'No-funcionales Bot-Admin'!L3+'No-funcionales Boton Ayuda'!L3 -> 815
A4: Total Requerimientos | B4: =B2+B3 -> 1305
A5: Cant. Funcionales Cumplidos | B5: ='Funcionales generales'!L4+'Funcionales DB'!L4+'Funcionales Homepage'!L4+'Funcionales Productos'!L4+'Funcionales Categoria'!L4+'Funcionales Descuentos'!L4+'Funcionales Cookies'!L4+'Funcionales Politicas'!L4+'Funcionales Terminos condicione'!L4+'Funcionales Perfil'!L4+'Funcionales Contacto'!L4+'Funcionales Seguimiento'!L4+'Funcionales Inversionistas'!L4+'Funcionales Devoluciones'!L4+'Funcionales Ayuda'!L4+'Funcionales Prensa'!L4+'Funcionales Acerca de'!L4+'Funcionales chatbotInformativo'!L4+'Funcionales LoginRegister'!L4+'Funcionales Producto'!L4+'Funcionales Carrito'!L4+'Funcionales Checkout'!L4+'Funcionales Favoritos'!L4+'Funcionales Dashboard Admin'!L4+'Funcionales Ordenes admin'!L4+'Funcionales Productos Admin'!L4+'Funcionales Categorías Admin'!L4+'Funcionales Usuario Admin'!L4+'Funcionales Atributos'!L4+'Funcionales Marcas'!L4+'Funcionales Proveedores Admin'!L4+'Funcionales Descuentos Admin'!L4+'Funcionales Puntos Admin'!L4+'Funcionales barra informativa '!L4+'No-funcionales barra informativ'!L4+'Funcionales Bot-Admin'!L4+'Funcionales Boton Ayuda'!L4 -> 485
A6: Cant. No-funcionales Cumplidos | B6: ='No-funcionales generales'!L4+'No-funcionales DB'!L4+'No-funcionales Homepage'!L4+'No-funcionales Productos'!L4+'No-funcionales Categoria'!L4+'No-funcionales Descuentos'!L4+'No-funcionales Cookies'!L4+'No-funcionales Politicas'!L4+'No-funcionales Terminos Condici'!L4+'No-funcionales Perfil'!L4+'No-funcionales Contacto'!L4+'No-Funcionales Seguimiento'!L4+'No-funcionales Inversionistas'!L4+'No-funcionales Devoluciones'!L4+'No-funcionales Ayuda'!L4+'No-funcionales Prensa'!L4+'No-funcionales Acerca de'!L4+'No-funcionales chatbotInformati'!L4+'No-funcionales LoginRegister'!L4+'No-funcionales Producto'!L4+'No-funcionales Carrito'!L4+'No-funcionales Checkout '!L4+'No-funcionales Favoritos'!L4+'No-funcionales Dashboard Admin'!L4+'No-funcionales Ordenes admin'!L4+'No-funcionales Productos Admin '!L4+'No-funcionales Categorias Admin'!L4+'No-funcionales Usuarios Admin'!L4+'No-funcionales Atributos'!L4+'No-funcionales Marcas '!L4+'No-funcionales Proveedores Admi'!L4+'No-funcionales Descuentos Admin'!L4+'No-funcionales Puntos Admin'!L4+'No-funcionales Bot-Admin'!L4+'No-funcionales Boton Ayuda'!L4 -> 815
A7: Total Cumplidos | B7: =B5+B6 -> 1300
A8: Porcentaje de Cumplimiento | B8: =IF(B4=0, 0, B7/B4) -> 0.99616858

Sheet Funcionales generales
B2: LISTADO DE REQUERIMIENTOS DE COMPRALO | K2: ESTADISTICAS
K3: Requirimientos | L3: =COUNT(B12:D86) -> 26
B4: SI | C4: Marque con una equis (X) si el sistema cumple con la función descrita | K4: Cumplidos | L4: =COUNTIF(F12:F86,"X") -> 26
B5: NO | C5: Marque con una equis (X) si el sistema no cumple con la función descrita
B6: ADI | C6: Marque con una equis (X) si el sistema debe adicionar la función descrita | K6: Porcentaje | L6: =PERCENTOF(L4,L3) -> #NAME?
B7: Observaciones: | D7: Espacio para complementar respuestas
F9: Nivel de cumplimiento | I9: OBSERVACIONES
B10: REQUISITOS FUNCIONALES GENERALES | F10: SI | G10: NO | H10: ADI
B12: 1 | C12: El sistema debe garantizar la seguridad de los datos almacenados mediante contraseñas, autenticación basada en JWT y control de acceso por roles (admin, usuario) | F12: x
B13: 2 | C13: El sistema debe permitir el manejo de datos personales por medio de cookies | F13: x
B14: 3 | C14: El sistema debe estar disponible 24/7 con un tiempo de actividad mínimo del 99% | F14: x
B15: 4 | C15: El sistema es multiusuario con roles diferenciados (administradores y clientes, clientes anonimos) | F15: x
B16: 5 | C16: El sistema debe ser compatible con navegadores modernos Chrome, Firefox, Safari, Edge | F16: x
B17: 6 | C17: El sistema debe permitir la encripción de contraseñas | F17: x
B18: 7 | C18: El sistema debe cumplir con normativas de protección de datos GDPR/LGPD | F18: x
B19: 8 | C19: El sistema debe soportar dispositivos móviles y tablets responsivamente | F19: x
B20: 9 | C20: El sistema debe permitir gestionar un catálogo de productos con jerarquía categoría → línea → sublínea, marcas, proveedores y variantes (color/talla/atributos). | F20: x
B21: 10 | C21: El sistema debe permitir gestionar inventario (entradas, salidas, ajustes y movimientos por producto/variante). | F21: x
B22: 11 | C22: El sistema debe incluir herramientas de accesibilidad | F22: x
B23: 12 | C23: El sistema debe permitir que el cliente final navegue el catálogo, filtre por múltiples criterios (categoría, precio, marca, proveedor, texto libre) y ordene los resultados. | F23: x
... B37: 26 | C37: El sistema debe permitir programar descuentos y campañas con fecha/hora de inicio y fin, aplicadas automáticamente. | F37: x

Sheet No-funcionales generales
B2: LISTADO DE REQUERIMIENTOS DE COMPRALO | K2: ESTADISTICAS
K3: Requirimientos | L3: =COUNT(B12:D92) -> 33
B4: SI | C4: Marque con una equis (X) si el sistema cumple con la función descrita | K4: Cumplidos | L4: =COUNTIF(F12:F92,"X") -> 33
B5: NO | C5: Marque con una equis (X) si el sistema no cumple con la función descrita
B6: ADI | C6: Marque con una equis (X) si el sistema debe adicionar la función descrita | K6: Porcentaje | L6: =PERCENTOF(L4,L3) -> #NAME?
B7: Observaciones: | D7: Espacio para complementar respuestas
F9: Nivel de cumplimiento | I9: OBSERVACIONES
B10: REQUISITOS NO FUNCIONALES GENERALES | F10: SI | G10: NO | H10: ADI
B12: 1 | C12: El sistema debe garantizar la seguridad de los datos almacenados mediante encriptación de contraseñas, autenticación basada en JWT y control de acceso por roles (admin, usuario) | F12: X
B13: 2 | C13: El sistema debe validar que todos los datos de entrada (productos, usuarios, proveedores,etc) estén completos mediante esquemas Pydantic y mostrar mensajes de error específicos para campos faltantes o inválidos | F13: X
B14: 3 | C14: El sistema debe ser capaz de escalar horizontalmente para adaptarse al crecimiento de usuarios y productos sin afectar el rendimiento mediante pooling de conexiones y cache | F14: x
B15: 4 | C15: La base de datos PostgreSQL debe permitir respaldos automáticos, gestión de transacciones ACID y optimización de consultas | F15: X
B16: 5 | C16: El sistema debe integrar con servicios externos de pagos (futuro) y notificaciones mediante APIs REST | F16: x
B17: 6 | C17: El sistema debe tener un tiempo máximo de respuesta de 2 segundos para operaciones CRUD de productos, usuarios y proveedores | F17: X
B18: 7 | C18: Los permisos de acceso al sistema podrán ser gestionados solo por usuarios con rol de administrador | F18: X
B19: 8 | C19: Ningún log debe contener contraseñas, tokens, números completos de tarjeta u otra información altamente sensible. | F19: X
B20: 9 | C20: El sistema debe utilizar PostgreSQL como motor de base de datos con funciones almacenadas para operaciones complejas | F20: X
B21: 10 | C21: El sistema debe contar con documentación API automática generada por FastAPI (Swagger/OpenAPI) y manuales de usuario | F21: X
B22: 11 | C22: El sistema debe procesar al menos 100 transacciones por segundo bajo carga normal | F22: X
B23: 12 | C23: El sistema debe manejar errores de forma centralizada con logging estructurado y códigos de estado HTTP apropiados | F23: X
... B44: 33 | C44: Soporte para caracteres Unicode (UTF-8) | F44: X

Sheet Funcionales DB
B2: LISTADO DE REQUERIMIENTOS DE COMPRALO | K2: ESTADISTICAS
K3: Requirimientos | L3: =COUNT(B12:D99) -> 24
B4: SI | C4: Marque con una equis (X) si el sistema cumple con la función descrita | K4: Cumplidos | L4: =COUNTIF(F12:F99,"X") -> 24
B5: NO | C5: Marque con una equis (X) si el sistema no cumple con la función descrita
B6: ADI | C6: Marque con una equis (X) si el sistema debe adicionar la función descrita | K6: Porcentaje | L6: =PERCENTOF(L4,L3) -> #NAME?
B7: Observaciones: | D7: Espacio para complementar respuestas
F9: Nivel de cumplimiento | I9: OBSERVACIONES
B10: REQUISITOS FUNCIONALES DB | F10: SI | G10: NO | H10: ADI
B12: 1 | C12: La tabla tab_products no debe almacenar precio ni stock; estos datos deben residir únicamente en tab_product_variant_combinations. | F12: X | I12: Requerimientos no funcionales
B13: 2 | C13: La base de datos debe permitir gestionar variantes mediante el modelo tab_product_variant_groups (agrupación lógica, p. ej. color) y tab_product_variant_combinations (combinación concreta de atributos). | F13: x | I13: Requerimientos no funcionales
B14: 3 | C14: Cada registro de tab_product_variant_combinations debe estar asociado a un grupo válido en tab_product_variant_groups mediante group_id. | F14: x | I14: Requerimientos no funcionales
B15: 4 | C15: Cada grupo de variantes (tab_product_variant_groups) puede tener múltiples imágenes (tab_product_variant_images) con orden y marca de principal (is_main). | F15: x | I15: Requerimientos no funcionales
B16: 5 | C16: La función fun_insert_producto debe crear productos en tab_products garantizando slug único y consistencia con categorías, marcas y proveedores. | F16: x | I16: Requerimientos no funcionales
B17: 6 | C17: La función fun_insert_product_variant debe insertar combinaciones en tab_product_variant_combinations generando un SKU único con fun_generate_sku y respetando | F17: x | I17: Requerimientos no funcionales
B18: 7 | C18: La función fun_insert_product_image debe registrar imágenes en tab_product_variant_images y asegurar que exista siempre una imagen principal por producto/grupo (o un valor por defecto). | F18: x | I18: Requerimientos no funcionales
B19: 8 | C19: Las funciones de filtro (fun_filter_products, fun_filter_admin_products, funciones de favoritos, etc.) deben obtener precios, stock total e imagen principal a partir de tab_product_variant_combinations + tab_product_variant_groups + tab_product_variant_images. | F19: x | I19: Requerimientos no funcionales
B20: 9 | C20: tab_carrito_productos y tab_orden_productos deben referenciar siempre una combinación válida mediante variant_id (tab_product_variant_combinations.id). | F20: x | I20: Requerimientos no funcionales
B21: 10 | C21: Las columnas opciones_elegidas en tab_carrito_productos y tab_orden_productos deben almacenar en JSONB los atributos elegidos (color, talla, etc.) coherentes con tab_product_variant_combinations.attributes. | F21: x | I21: Requerimientos no funcionales
B22: 11 | C22: La función fun_obtener_carrito_usuario debe crear o recuperar un carrito único por usuario o session_id, garantizando que no existan carritos duplicados activos por la misma clave. | F22: x | I22: Requerimientos no funcionales
B23: 12 | C23: La función fun_agregar_producto_carrito debe validar existencia y estado (is_active) de la combinación, verificar stock disponible y actualizar/incrementar la línea en tab_carrito_productos con sus opciones_elegidas. | F23: x | I23: Requerimientos no funcionales
... B35: 24 | C35: Toda actualización de tab_ordenes.ind_estado a un estado final (completada, cancelada, etc.) debe ir acompañada de movimientos consistentes en tab_movimientos_inventario y tab_movimientos_puntos según la lógica de negocio. | F35: x | I35: Requerimientos no funcionales

Sheet No-funcionales DB
B2: LISTADO DE REQUERIMIENTOS DE COMPRALO | K2: ESTADISTICAS
K3: Requirimientos | L3: =COUNT(B12:D33) -> 20
B4: SI | C4: Marque con una equis (X) si el sistema cumple con la función descrita | K4: Cumplidos | L4: =COUNTIF(F12:F33,"X") -> 20
B5: NO | C5: Marque con una equis (X) si el sistema no cumple con la función descrita
B6: ADI | C6: Marque con una equis (X) si el sistema debe adicionar la función descrita | K6: Porcentaje | L6: =PERCENTOF(L4,L3) -> #NAME?
B7: Observaciones: | D7: Espacio para complementar respuestas
F9: Nivel de cumplimiento | I9: OBSERVACIONES
B10: REQUISITOS NO FUNCIONALES DB | F10: SI | G10: NO | H10: ADI
B12: 1 | C12: La base de datos debe mantener integridad referencial entre todas las tablas mediante claves foráneas, incluyendo la nueva relación producto → grupo → combinación → carrito/orden. | F12: x
B13: 2 | C13: Las transacciones que involucren carrito, órdenes, pagos, inventario, descuentos y puntos deben ser ACID: o se confirman todos los cambios o se revierte todo. | F13: x
B14: 3 | C14: Los cambios de estado de una orden deben ser atómicos respecto a las actualizaciones de stock y puntos. | F14: x
B15: 4 | C15: Las consultas de catálogo que usan fun_filter_products y fun_filter_admin_products sobre tab_products + tab_product_variant_groups + tab_product_variant_combinations deben devolver resultados paginados en tiempos aceptables (por ejemplo, < 300 ms para catálogos de hasta ~10.000 productos). | F15: x
B16: 5 | C16: Las consultas que calculan precios mínimos/máximos y stock total por producto a partir de tab_product_variant_combinations deben aprovechar índices y evitar escaneos completos innecesarios. | F16: x
B17: 6 | C17: La recuperación del carrito (fun_obtener_carrito_detalle) y el cálculo de totales (fun_calcular_total_carrito) deben ejecutarse típicamente en menos de ~200 ms para carritos de tamaño razonable. | F17: x
B18: 7 | C18: La creación de una orden desde carrito (fun_crear_orden_desde_carrito) debe completarse en un tiempo acotado (p.ej. < 1 segundo en condiciones normales), incluyendo inserciones en órdenes, líneas y movimientos de inventario. | F18: x
B19: 8 | C19: Las consultas de historial de órdenes (fun_obtener_ordenes_usuario) y de puntos (fun_obtener_resumen_puntos_usuario) deben soportar miles de registros por usuario manteniendo tiempos de respuesta aceptables (p.ej. < 500 ms). | F19: x
B20: 9 | C20: Los reportes de ventas por producto/categoría (tab_estadisticas_productos, tab_estadisticas_categorias y vistas/funciones asociadas) deben apoyarse en índices o tablas resumen para no degradar el rendimiento de las tablas transaccionales. | F20: x
B21: 10 | C21: Deben existir índices sobre columnas de filtrado frecuente: tab_product_variant_groups.product_id, tab_product_variant_combinations.group_id, tab_product_variant_combinations.is_active, slugs de categorías/productos y campos de búsqueda por texto. | F21: x
B22: 11 | C22: El índice GIN sobre tab_product_variant_combinations.attributes debe ser utilizado por las consultas que filtren por atributos dinámicos, equilibrando coste de escritura y rendimiento de lectura. | F22: x
B23: 12 | C23: Las tablas de alta escritura (tab_carrito_productos, tab_orden_productos, tab_movimientos_inventario, tab_movimientos_puntos) deben tener índices alineados con sus consultas principales sin penalizar de forma excesiva las inserciones. | F23: x
... B31: 20 | C31: Los logs de auditoría no deben almacenar información excesivamente sensible; cuando sea necesario, se deben anonimizar o truncar valores. | F31: x

Sheet Funcionales Homepage
B2: LISTADO DE REQUERIMIENTOS DE COMPRALO | K2: ESTADISTICAS
K3: Requirimientos | L3: =COUNT(B12:D99) -> 83
B4: SI | C4: Marque con una equis (X) si el sistema cumple con la función descrita | K4: Cumplidos | L4: =COUNTIF(F12:F99,"X") -> 81
B5: NO | C5: Marque con una equis (X) si el sistema no cumple con la función descrita
B6: ADI | C6: Marque con una equis (X) si el sistema debe adicionar la función descrita | K6: Porcentaje | L6: =PERCENTOF(L4,L3) -> #NAME?
B7: Observaciones: | D7: Espacio para complementar respuestas
B8: https://compralo.revital.cloud/
F9: Nivel de cumplimiento | I9: Observaciones
B10: REQUERIMIENTOS FUNCIONALES DEL HOME | F10: SI | G10: NO | H10: ADI
B12: 1 | C12: La home debe mostrar una barra superior informativa con mensajes clave (por ejemplo “Envíos gratis desde $X”) configurable por administrador, es posible cerrar la barra informativa con un boton de la parte derecha. | F12: X | I12: Cumple, NOTA: No se menciona la opcion de cerrar el mensaje en los requerimiento
B13: 2 | C13: La home debe mostrar un **header fijo** con: logo de la tienda, menú principal (`Inicio`, `Productos`, `Descuentos`, `Contacto`), buscador, icono de carrito, acceso a cuenta y selector de tema/color (si está habilitado). | F13: X | I13: Cumple
B14: 3 | C14: El **logo** en el header debe redirigir siempre a la home al hacer clic. | F14: X | I14: Cumple
B15: 4 | C15: El **menú principal de navegación** debe verse destacado en rojo según la sección actual (por ejemplo, `Inicio` resaltado en la homepage). Feature solo para desktop | F15: X | I15: Cumple
B16: 5 | C16: La **barra de búsqueda** de la home debe permitir buscar productos por texto y redirigir a la vista de catálogo (`/products`) mostrando los resultados filtrados. | F16: X | I16: Cumple
B17: 6 | C17: La home debe mostrar una **sección hero** con imagen/ilustración principal, título, subtítulo y al menos dos botones de llamada a la acción (“Ver productos” y “Ver categorías”). | F17: X | I17: Cumple, NOTA: No se especifica todo el contenido de la seccion hero como las metricas debajo del logo, el color de los botones, etc.
B18: 7 | C18: Al hacer clic en “Ver productos” desde el hero, el usuario debe ser redirigido a la página de catálogo de productos. | F18: X | I18: Cumple
B19: 8 | C19: Al hacer clic en “Ver categorías” desde el hero, el usuario debe ser redirigido a la página de categorías | F19: X | I19: Cumple
B20: 9 | C20: La home debe mostrar una **sección de categorías destacadas** con tarjetas para las categorías principales (por ejemplo: Electrónica, Moda, Hogar, Videojuegos, Mascotas, Ferretería). | F20: X | I20: Cumple, NOTA: No se menciona el numero de tarjetas por cada linea ni el color. Existe un boton "Ver Todas las Categorias" que no se menciona en los requerimientos
B21: 10 | C21: Cada tarjeta de categoría debe incluir nombre, breve descripción/etiqueta y fondo/ícono representativo. | F21: X | I21: Cumple
B22: 11 | C22: Al hacer clic en una categoría de la home, el usuario debe ser redirigido a una vista filtrada de catálogo que muestre las lineas de esa categoría. | F22: X | I22: Cumple,
B23: 12 | C23: La home debe mostrar una **sección de productos destacados** con un carrusel o grilla de tarjetas de producto (imagen, nombre, precio, rating/resumen y botón "ver detalles"). | F23: X | I23: Cumple, NOTA: Existe un boton "Ver Todos los Productos" que no se menciona en los requerimientos
... B25: 14 | C25: Al hacer clic en “Ver Detalles” en un producto destacado, el usuario debe ser redirigido a la página de detalle del producto correspondiente. | F25: X | I25: Cumple
B26: 15 | C26: Si un producto destacado tiene descuento, la tarjeta debe mostrar de forma clara el precio anterior, el porcentaje o monto de descuento y el precio final. | F26: x
B27: 16 | C27: La home debe mostrar una **sección de testimonios de clientes** con tarjetas que incluyan nombre, rol/segmento del cliente, foto/avatar y texto del testimonio. | F27: X | I27: Cumple, NOTA: Existe un boton "Empezar a comprar" que no se menciona en los requerimientos
B28: 17 | C28: Solo se mostraran las 3 ultimas reseñas. | F28: x
B29: 18 | C29: La home debe mostrar una **banda de beneficios** (por ejemplo: Envío Gratis, Compra Segura, Devoluciones, Pago Seguro) con iconos y texto corto. | F29: X | I29: No Cumple, la banda de beneficios se encuentra en el footer
B30: 19 | C30: El **footer** de la home debe incluir información corta "Acerca de nosotros" | F30: X | I30: Cumple
B31: 20 | C31: El **footer** de la home debe incluir listas de enlaces a categorías, líneas y sublíneas | F31: X | I31: Cumple
B32: 21 | C32: El **footer** de la home debe incluir enlaces de empresa (Acerca de, Contacto, Blog, Prensa, Inversionistas), | F32: X | I32: Cumple
B33: 22 | C33: El **footer** de la home debe incluir enlaces a secciones de ayuda del cliente (Mi cuenta, Seguir pedido, Centro de ayuda, Devoluciones), | F33: X | I33: Cumple
B34: 23 | C34: El **footer** de la home debe incluir enlaces legales (Términos y condiciones, Política de privacidad, Política de cookies, Accesibilidad, Configurar cookies) | F34: X | I34: Cumple
B35: 24 | C35: El **footer** de la home debe incluir Iconos de redes sociales que redireccione a las homepage de cada red social | F35: X | I35: Cumple
B36: 25 | C36: El **footer** de la home debe incluir logos de metodo de pago soportados | F36: X | I36: Cumple, NOTA: No hay requerimiento sobre el mensaje de copyright al final del footer
B37: 26 | C37: Todos los enlaces del footer deben redirigir a las páginas correspondientes dentro del sitio o a URLs externas configuradas. | F37: X | I37: No cumple, el link "Mi Cuenta" redirige al home
B38: 27 | C38: En la esquina inferior derecha de la home debe aparecer un **botón flotante de carrito** que abra el widget del chatbot | F38: X | I38: Cumple
B39: 28 | C39: La home debe mostrar el **widget de chatbot informativo** que al abrirse ofrezca un menú de opciones (términos, datos, descuentos, puntos, garantías) y responda usando datos de descuentos y puntos activos. | F39: X | I39: Cumple
B40: 29 | C40: la homepage debe mostrar el **banner de cookies** en la primera visita hasta que el usuario tome una decisión (aceptar todas, solo necesarias o configurar). | F40: X | I40: Cumple
... B43: 32 | C43: La home debe mostrar indicadores de sesión en el header: si el usuario está autenticado, mostrar acceso a su cuenta/perfil; si no, mostrar enlaces “Iniciar sesión” y “Registrarse” o equivalente. | F43: X | I43: Cumple
B44: 33 | C44: La home debe poder ocultar/mostrar secciones (por ejemplo testimonios, productos destacados, CTA secundaria) mediante parámetros de configuración por instancia sin requerir cambios de código. | H44: x
B45: 34 | C45: La home debe permitir que el administrador configure los textos principales (hero, beneficios, mensajes de barra superior, títulos de secciones) de acuerdo con el branding de cada instancia. | E45: Información corta “Acerca de nosotros”, | H45: x
B46: 35 | C46: En el hero se muestra el logo de la tienda (Ejm: Carrito rojo con una flecha amarilla adentro) | E46: Información corta “Acerca de nosotros”, | F46: x
B47: 36 | C47: El fondo del hero debe ser un degradado oscuro (azul/negro). | E47: Enlaces de empresa (Acerca de, Contacto, Blog, Prensa, Inversionistas), | F47: x
B48: 37 | C48: El fondo del hero debe incluir partículas/puntos de colores distribuidos aleatoriamente. | E48: Enlaces a secciones de ayuda del cliente (Mi cuenta, Seguir pedido, Centro de ayuda, Devoluciones), | F48: x
B49: 38 | C49: El hero debe contener una etiqueta superior tipo badge con fondo naranja que diga “Ofertas en Tendencia”. | E49: Enlaces legales (Términos y condiciones, Política de privacidad, Política de cookies, Accesibilidad, Configurar cookies), | F49: x
B50: 39 | C50: El texto principal debe estar dividido en dos líneas: "Descubre las" en color blanco, y “ofertas increíbles” en color naranja. | E50: Iconos de redes sociales, | F50: x
B51: 40 | C51: El texto descriptivo debe ser de menor tamaño, en color gris claro/blanco tenue. | E51: Logos de métodos de pago soportados. | F51: x
B52: 41 | C52: Deben existir dos botones: Botón primario: “Ver productos” (color naranja), Botón secundario: “Ver Categorías” (color oscuro con borde). | F52: x
B53: 42 | C53: Los botones deben tener bordes redondeados. | F53: x
B54: 43 | C54: El hero debe incluir un ícono/gráfico grande de carrito de compras en el lado derecho. | F54: x
B55: 44 | C55: El carrito debe ser rojo con un elemento amarillo (bolsa o forma). | F55: x
B56: 45 | C56: Deben mostrarse indicadores de confianza debajo del texto:Compra segura. Entrega rápida, Calificación (estrellas) | F56: x
B57: 46 | C57: Deben mostrarse métricas destacadas: “50K+ Clientes”, “10K+ Productos”, “24/7 Soporte” | F57: x
B58: 47 | C58: Las métricas deben estar en tarjetas pequeñas con fondo oscuro y bordes suaves. | F58: x
B59: 48 | C59: Debe existir un título centrado: “Explora Nuestras Categorías”. | F59: x
B60: 49 | C60: La palabra “Categorías” debe estar en color naranja. | F60: x
B61: 50 | C61: Debe haber un subtítulo descriptivo en texto pequeño. | F61: x
B62: 51 | C62: Las categorías deben mostrarse en formato grid (mínimo 6). | F62: x
B63: 52 | C63: Cada categoría debe ser una tarjeta con: Fondo con gradiente de color único, Icono centrado,Nombre de la categoría,Descripción corta. | F63: x
... B94: 83 | C94: El banner debe tener fondo oscuro y botones contrastantes. | F94: x

Sheet No-funcionales Homepage
B2: LISTADO DE REQUERIMIENTOS DE COMPRALO | K2: ESTADISTICAS
K3: Requirimientos | L3: =COUNT(B12:D100) -> 35
B4: SI | C4: Marque con una equis (X) si el sistema cumple con la función descrita | K4: Cumplidos | L4: =COUNTIF(F12:F100,"X") -> 35
B5: NO | C5: Marque con una equis (X) si el sistema no cumple con la función descrita | K5: Porcentaje | L5: =PERCENTOF(L4,L3) -> #NAME?
B6: ADI | C6: Marque con una equis (X) si el sistema debe adicionar la función descrita
B7: Observaciones: | D7: Espacio para complementar respuestas
B8: https://compralo.revital.cloud/
F9: Nivel de cumplimiento | I9: Observaciones
B10: REQUERIMIENTOS NO FUNCIONALES DEL HOME | F10: SI | G10: NO | H10: ADI
B12: 1 | C12: El slider debe ser responsive en móviles | F12: X
B13: 2 | C13: Las imágenes deben optimizarse automáticamente | F13: X
B14: 3 | C14: La página debe ser accesible con navegación por teclado | F14: X
B15: 4 | C15: La home debe aplicar técnicas de **lazy loading** para imágenes y secciones que no son visibles inicialmente, reduciendo el tiempo de carga inicial. | F15: X
B16: 5 | C16: El slider/banner debe ser responsive y adaptarse a móviles, tablets y desktop | F16: X
B17: 6 | C17: Las imágenes de productos deben optimizarse automáticamente (WebP, compresión) | F17: X
B18: 7 | C18: La interfaz debe mantener contraste mínimo 4.5:1 para accesibilidad WCAG 2.1 | F18: X
B19: 8 | C19: La galería de imágenes debe soportar zoom fluido sin lag perceptible | F19: X
B20: 9 | C20: El formulario de checkout debe validarse en tiempo real con feedback visual | F20: X
B21: 10 | C21: La página debe ser compatible con Chrome, Firefox, Safari, Edge (últimas 2 versiones) | F21: X
B22: 11 | C22: El cambio entre modo claro/oscuro debe ser instantáneo sin parpadeos | F22: X
B23: 12 | C23: Los botones deben tener estados hover, active y disabled claramente diferenciados | F23: X
... B46: 35 | C46: La home debe respetar las preferencias de cookies del usuario: si ha rechazado cookies no esenciales, no se deben disparar scripts analíticos/marketing desde la home hasta que cambie su configuración. | F46: X

Sheet Funcionales Productos
B2: LISTADO DE REQUERIMIENTOS DE COMPRALO | K2: ESTADISTICAS
K3: Requirimientos | L3: =COUNT(B12:D75) -> 9
B4: SI | C4: Marque con una equis (X) si el sistema cumple con la función descrita | K4: Cumplidos | L4: =COUNTIF(F12:F75,"X") -> 8
B5: NO | C5: Marque con una equis (X) si el sistema no cumple con la función descrita | K5: Porcentaje | L5: =PERCENTOF(L4,L3) -> #NAME?
B6: ADI | C6: Marque con una equis (X) si el sistema debe adicionar la función descrita
B7: Observaciones: | D7: Espacio para complementar respuestas
B8: https://compralo.revital.cloud/products
F10: Nivel de cumplimiento | I10: Observaciones
B11: REQUERIMIENTOS FUNCIONALES PRODUCTOS | F11: SI | G11: NO | H11: ADI
B13: 1 | C13: La página de productos debe mostrar un listado paginado de productos basado en los filtros y criterios de ordenamiento seleccionados por el usuario. | F13: x | I13: Cumple
B14: 2 | C14: Cada tarjeta de producto debe mostrar al menos imagen principal, nombre, rango de precios cuando existan variantes. | F14: x | I14: Cumple
B15: 3 | C15: La página debe permitir filtrar productos por rango de precio mínimo y máximo mediante controles específicos en el panel de filtros. | F15: x
B16: 4 | C16: La página debe permitir filtrar productos por categoría, línea y sublínea utilizando una navegación jerárquica en el panel de filtros. | F16: x
B17: 5 | C17: La página debe permitir filtrar productos por marca y, pudiendo seleccionar una o varias opciones simultáneamente. | F17: x
B18: 6 | C18: La página debe ofrecer filtros de disponibilidad (por ejemplo “Solo en stock”, “Solo con descuento”) que limiten el listado a productos que cumplan dichas condiciones. | H18: x
B19: 7 | C19: La página debe mostrar una sección de filtros activos (chips o etiquetas) que resuma todos los filtros aplicados y permita quitarlos individualmente o limpiar todos a la vez. | F19: x
B20: 8 | C20: La página debe ofrecer un selector de ordenamiento con al menos las opciones por nombre, por precio (ascendente y descendente) y por relevancia o más vendidos. | F20: x
B21: 9 | C21: La página debe permitir cambiar entre al menos dos modos de visualización del listado (por ejemplo, vista de cuadrícula y vista de lista), recordando la preferencia del usuario cuando sea posible. | F21: x

Sheet No-funcionales Productos
B2: LISTADO DE REQUERIMIENTOS DE COMPRALO | K2: ESTADISTICAS
K3: Requirimientos | L3: =COUNT(B12:D100) -> 30
B4: SI | C4: Marque con una equis (X) si el sistema cumple con la función descrita | K4: Cumplidos | L4: =COUNTIF(F12:F100,"X") -> 30
B5: NO | C5: Marque con una equis (X) si el sistema no cumple con la función descrita | K5: Porcentaje | L5: =PERCENTOF(L4,L3) -> #NAME?
B6: ADI | C6: Marque con una equis (X) si el sistema debe adicionar la función descrita
B7: Observaciones: | D7: Espacio para complementar respuestas
F10: Nivel de cumplimiento | I10: Observaciones
B11: REQUERIMIENTOS NO FUNCIONALES PRODUCTOS | F11: SI | G11: NO | H11: ADI
B13: 1 | C13: El contenido inicial de la página (primer bloque de productos visible y filtros básicos) debe cargarse en menos de ~3 segundos en conexiones de banda ancha típicas. | F13: x
B14: 2 | C14: Las consultas al backend que alimentan el listado de productos deben estar paginadas y usar índices adecuados sobre categoría, precio, estado y marca para evitar escaneos completos de tablas. | F14: x
B15: 3 | C15: La API que lista productos debe mantener un tiempo de respuesta objetivo P95 menor a 500 ms bajo carga normal, incluyendo la aplicación de filtros estándar. | F15: x
B16: 4 | C16: Las imágenes de productos deben cargarse utilizando técnicas de lazy loading para elementos fuera del viewport, reduciendo el peso inicial de la página. | F16: x
B17: 5 | C17: Los formatos y tamaños de imagen utilizados en la página de productos deben estar optimizados (compresión, tamaños adaptativos) para equilibrar calidad visual y rendimiento. | F17: x
B18: 6 | C18: La reserva de espacio para imágenes y tarjetas debe evitar saltos de layout significativos (CLS), manteniendo la estructura estable durante la carga. | F18: x
B19: 7 | C19: El control de rango de precio (inputs o slider) debe responder sin bloqueos perceptibles al usuario, aplicando el filtro mediante solicitudes asincrónicas o recarga controlada. | F19: x
B20: 8 | C20: La aplicación de filtros de precio no debe degradar de forma notable el tiempo de respuesta de la página, manteniendo un comportamiento similar al de otros filtros. | F20: x
B21: 9 | C21: El formato de precios mostrado en la página debe ser consistente con la configuración regional de la instancia (separadores de miles, símbolo de moneda, número de decimales). | F21: x
B22: 10 | C22: La navegación jerárquica de categorías, líneas y sublíneas debe ser completamente responsiva, adaptándose a una columna expandible en móvil y a un panel lateral en escritorio sin solapamientos. | F22: x
B23: 11 | C23: Las consultas para filtrar por categoría, línea y sublínea deben aprovechar índices compuestos o vistas preparadas para que el rendimiento se mantenga estable incluso con catálogos grandes. | F23: x
B24: 12 | C24: Los textos de nombres y descripciones de categorías, líneas y sublíneas deben truncarse de forma elegante en el panel de filtros para evitar desbordes en pantallas pequeñas. | F24: x
... B42: 30 | C42: En el flujo de añadir al carrito, los errores (por ejemplo, falta de stock o selección de variante incompleta) deben manejarse con mensajes claros y no bloquear el resto de interacciones en la página | F42: x

Sheet Funcionales Categoria
B2: LISTADO DE REQUERIMIENTOS DE COMPRALO | K2: ESTADISTICAS
K3: Requirimientos | L3: =COUNT(B12:D96) -> 10
B4: SI | C4: Marque con una equis (X) si el sistema cumple con la función descrita | K4: Cumplidos | L4: =COUNTIF(F12:F96,"X") -> 10
B5: NO | C5: Marque con una equis (X) si el sistema no cumple con la función descrita | K5: Porcentaje | L5: =PERCENTOF(L4,L3) -> #NAME?
B6: ADI | C6: Marque con una equis (X) si el sistema debe adicionar la función descrita
B7: Observaciones: | D7: Espacio para complementar respuestas
F10: Nivel de cumplimiento | I10: Observaciones
B11: REQUERIMIENTOS FUNCIONALES CATEGORIA | F11: SI | G11: NO | H11: ADI
B13: 1 | C13: La sección de categorías debe mostrar una cuadrícula de tarjetas de todas las categorías activas del catálogo, cada una con nombre, breve descripción y un ícono o imagen representativa. | F13: X | I13: cumple Pregunta: ¿Las categorías activas sin productos deben mostrarse en el catálogo o deben ocultarse?
B14: 2 | C14: Cada tarjeta de categoría debe mostrar el número de productos asociados a esa categoría (por ejemplo “4 productos”) calculado a partir del catálogo actual. | F14: X | I14: cumple
B15: 3 | C15: Al hacer clic en una tarjeta de categoría, el sistema debe navegar a una vista de detalle de categoría donde se muestren las líneas asociadas (por ejemplo /categories/[id_category]) | F15: X | I15: cumple Nota: Esto debe ir en requerimientos No Funcionales (por ejemplo /categories/[id_category])
B16: 4 | C16: La vista de detalle de categoría debe listar todas las líneas pertenecientes a esa categoría como tarjetas, cada una con nombre, descripción corta y contador de productos asociados. | F16: X | I16: cumple Nota: la descripción debe ser un poco más específica acerca de las características del producto
B17: 5 | C17: Al hacer clic en una tarjeta de línea, el sistema debe navegar a una vista de detalle de línea donde se muestren las sublíneas correspondientes (por ejemplo /categories/[id_line]) | F17: X | I17: cumple
B18: 6 | C18: La vista de detalle de línea debe listar todas las sublíneas como tarjetas con nombre y contador de productos, y permitir navegar a la vista de productos filtrados por esa sublínea. | F18: X | I18: cumple
B19: 7 | C19: En cualquier nivel (categoría, línea, sublínea) la sección debe ofrecer un enlace o botón claro para volver al nivel inmediatamente anterior. | F19: X | I19: cumple Nota: Cuando se le da clic al producto para ver las específicaciones no se puede volver atrás.
B20: 8 | C20: La vista de nivel más profundo (por ejemplo, sublínea) debe mostrar, además de la tarjeta de sublínea, un listado de productos filtrados exclusivamente por esa sublínea. | F20: X | I20: cumple
B21: 9 | C21: Cuando el número de categorías sea mayor que la capacidad de la cuadrícula, la sección debe ofrecer paginación para navegar entre páginas de categorías. | F21: X | I21: cumple
B22: 10 | C22: La sección de categorías, en todos sus niveles, debe reutilizar el mismo header, barra superior y footer que el resto del sitio, manteniendo activo el ítem de menú “Productos” según la navegación definida. | F22: X | I22: cumple

Sheet No-funcionales Categoria
B2: LISTADO DE REQUERIMIENTOS DE COMPRALO | K2: ESTADISTICAS
K3: Requirimientos | L3: =COUNT(B12:D100) -> 40
B4: SI | C4: Marque con una equis (X) si el sistema cumple con la función descrita | K4: Cumplidos | L4: =COUNTIF(F12:F100,"X") -> 40
B5: NO | C5: Marque con una equis (X) si el sistema no cumple con la función descrita | K5: Porcentaje | L5: =PERCENTOF(L4,L3) -> #NAME?
B6: ADI | C6: Marque con una equis (X) si el sistema debe adicionar la función descrita
B7: Observaciones: | D7: Espacio para complementar respuestas
F10: Nivel de cumplimiento | I10: Observaciones
B11: REQUERIMIENTOS NO FUNCIONALES CATEGORIA | F11: SI | G11: NO | H11: ADI
B13: 1 | C13: El tiempo de carga inicial de la cuadrícula de categorías (primer “fold”) no debe exceder ~3 segundos en conexiones de banda ancha típicas. | F13: x
B14: 2 | C14: Las consultas a la base de datos para obtener el listado de categorías deben estar paginadas y usan índices sobre las columnas de estado y orden de visualización para evitar escaneos completos innecesarios. | F14: x
B15: 3 | C15: El cálculo de contadores de productos por categoría debe realizarse mediante vistas/materializaciones o consultas agregadas optimizadas para no degradar el rendimiento al crecer el catálogo. | F15: x
B16: 4 | C16: El layout de la cuadrícula de categorías debe ser completamente responsivo, mostrando 1–2 columnas en móvil, 2–3 en tablet y ≥4 en escritorio sin solapamiento de contenido. | F16: x
B17: 5 | C17: Las tarjetas de categoría deben mantener un tamaño mínimo táctil de acuerdo con las recomendaciones de accesibilidad (al menos 44x44 px en dispositivos táctiles). | F17: x
B18: 6 | C18: Los textos de nombre y descripción de cada categoría deben truncarse de forma elegante (con ellipsis) para evitar desbordes o saltos de layout inesperados. | F18: x
B19: 7 | C19: Las imágenes o íconos de las tarjetas de categoría deben cargarse con técnicas de lazy loading para minimizar el peso inicial de la página. | F19: x
B20: 8 | C20: Los colores y contrastes usados en títulos y tarjetas de categorías deben cumplir como mínimo el nivel AA de WCAG 2.1 para asegurar legibilidad en todos los dispositivos. | F20: x
B21: 9 | C21: La cuadrícula y los controles de paginación deben ser completamente navegables por teclado, con un orden de tabulación lógico y focos visibles en todos los elementos interactivos. | F21: x
B22: 10 | C22: Las consultas que devuelven líneas asociadas a una categoría deben filtrar solo líneas activas y aprovechar índices sobre category_id y is_active para reducir la latencia. | F22: x
B23: 11 | C23: La vista de detalle de categoría debe renderizar las tarjetas de líneas sin provocar reflujo visual significativo; se deben reservar alturas aproximadas para las tarjetas antes de cargar su contenido. | F23: x
B24: 12 | C24: Los textos de encabezados y descripciones en la vista de detalle de categoría deben ser internacionalizables, permitiendo cambiar de idioma sin modificar el código de la página. | F24: x
... B52: 30 | C52: Cualquier animación usada en las tarjetas de categorías (hover, focus, transiciones) debe ejecutarse de forma fluida (60 fps objetivo) y no debe bloquear la interacción ni provocar mareo o distracción excesiva. | F52: x

Sheet Funcionales Descuentos
B2: LISTADO DE REQUERIMIENTOS DE COMPRALO | K2: ESTADISTICAS
K3: Requirimientos | L3: =COUNT(B12:D99) -> 9
B4: SI | C4: Marque con una equis (X) si el sistema cumple con la función descrita | K4: Cumplidos | L4: =COUNTIF(F12:F99,"X") -> 9
B5: NO | C5: Marque con una equis (X) si el sistema no cumple con la función descrita | K5: Porcentaje | L5: =PERCENTOF(L4,L3) -> #NAME?
B6: ADI | C6: Marque con una equis (X) si el sistema debe adicionar la función descrita
B7: Observaciones: | D7: Espacio para complementar respuestas
B8: https://compralo.revital.cloud/discounts
F10: Nivel de cumplimiento | I10: Observaciones
B11: REQUERIMIENTOS FUNCIONALES DESCUENTOS | F11: SI | G11: NO | H11: ADI
B13: 1 | C13: La sección de descuentos debe mostrar un listado de todos los descuentos activos, cada uno en una tarjeta con nombre, porcentaje o monto de descuento y descripción corta. | F13: x | I13: Cumple
B14: 2 | C14: Cada tarjeta de descuento debe mostrar claramente el tipo de descuento (porcentaje o monto fijo) y el valor correspondiente (por ejemplo “50.00%” o “$50.000”). | F14: x | I14: Cumple
B15: 3 | C15: Cada descuento debe indicar a qué ámbito aplica: categoría específica, subconjunto de productos, carrito completo u otros criterios definidos en la configuración. | F15: x | I15: Cumple
B16: 4 | C16: La tarjeta de descuento debe mostrar el período de vigencia (fecha de inicio y fecha de fin) y, si corresponde, un indicador de estado (por ejemplo “Próximo”, “Activo”, “Pronto a expirar”). | F16: x | I16: Cumple. NOTA: No se pudo verificar el indicador de estado
B17: 5 | C17: La sección de descuentos debe permitir mostrar ejemplos concretos de precios antes y después de aplicar el descuento (por ejemplo “$100.000 → $50.000”) para ilustrar el beneficio. | F17: x | I17: Cumple
B18: 6 | C18: La sección de descuentos debe indicar, cuando aplique, si el descuento requiere condiciones especiales, como un cupón, un mínimo de compra o pertenecer a un segmento de clientes. | F18: x | I18: Cumple
B19: 7 | C19: La sección de descuentos debe mostrar solo los descuentos que estén realmente disponibles para el usuario actual, excluyendo aquellos reservados a otros segmentos o ya expirados. | F19: x
B20: 8 | C20: La sección de descuentos debe manejar el caso “sin descuentos disponibles” mostrando un estado vacío con mensaje amigable y sugerencias (por ejemplo ver productos o suscribirse a un boletín). | F20: x | I20: Cumple
B21: 9 | C21: La sección de descuentos debe convivir con la estructura global de la app (header, barra superior, footer, chatbot, botón flotante de carrito) sin interferir en su funcionamiento ni en la navegación principal. | F21: x | I21: cumple NOTA: el requerimiento es funcional, pero la forma en que está redactado usa términos técnicos (“estructura global”, “chatbot”, “botón flotante de carrito”)

Sheet No-funcionales Descuentos
B2: LISTADO DE REQUERIMIENTOS DE COMPRALO | K2: ESTADISTICAS
K3: Requirimientos | L3: =COUNT(B12:D100) -> 30
B4: SI | C4: Marque con una equis (X) si el sistema cumple con la función descrita | K4: Cumplidos | L4: =COUNTIF(F12:F100,"X") -> 30
B5: NO | C5: Marque con una equis (X) si el sistema no cumple con la función descrita | K5: Porcentaje | L5: =PERCENTOF(L4,L3) -> #NAME?
B6: ADI | C6: Marque con una equis (X) si el sistema debe adicionar la función descrita
B7: Observaciones: | D7: Espacio para complementar respuestas
B8: https://compralo.revital.cloud/discounts
F10: Nivel de cumplimiento | I10: Observaciones
B11: REQUERIMIENTOS NO FUNCIONALES DESCUENTOS | F11: SI | G11: NO | H11: ADI
B13: 1 | C13: El listado inicial de descuentos debe cargarse en menos de aproximadamente 2 segundos en conexiones de banda ancha típicas. | F13: x
B14: 2 | C14: La consulta que obtiene los descuentos activos debe filtrar por fecha de vigencia y estado para evitar recorrer descuentos expirados o desactivados. | F14: x
B15: 3 | C15: El endpoint que lista descuentos debe mantener un tiempo de respuesta objetivo P95 menor a 500 ms bajo carga normal. | F15: x
B16: 4 | C16: El formato de porcentajes y montos debe seguir la configuración regional de la instancia (símbolo de moneda, separadores de miles y decimales). | F16: x
B17: 5 | C17: Los valores de descuento deben formatearse de forma consistente en toda la interfaz para reducir ambigüedades y errores de interpretación. | F17: x
B18: 6 | C18: La lógica que calcula y muestra los valores de descuento debe estar cubierta por pruebas automatizadas que validen diversos casos (porcentajes altos, montos pequeños, redondeos). | F18: x
B19: 7 | C19: La obtención de la información de ámbito (categorías, productos, reglas) debe realizarse con consultas optimizadas (joins mínimos, uso de índices sobre columnas de relación). | F19: x
B20: 8 | C20: La descripción del ámbito de aplicación debe generarse a partir de datos estructurados y ser fácilmente traducible a otros idiomas sin cambios de código. | F20: x
B21: 9 | C21: Los textos que explican el ámbito deben ser claros, concisos y evitar tecnicismos innecesarios para disminuir el riesgo de reclamaciones por malentendidos. | F21: x
B22: 10 | C22: El cálculo de estados de vigencia (próximo, activo, pronto a expirar, expirado) debe basarse en la zona horaria configurada para la instancia y no en la hora local del navegador. | F22: x
B23: 11 | C23: El formato de fechas mostrado para vigencia debe ser consistente en toda la aplicación y configurable por región (por ejemplo, DD/MM/AAAA o MM/DD/YYYY). | F23: x
B24: 12 | C24: El refresco del estado visual de vigencia no debe requerir recargar toda la página; idealmente debe recalcularse en cliente o con llamadas ligeras al backend. | F24: x
... B42: 30 | C42: La sección de descuentos debe respetar las preferencias de cookies y privacidad del usuario, evitando la ejecución de scripts analíticos o de marketing si no se ha otorgado el consentimiento correspondiente. | F42: x

Sheet Funcionales Cookies
A1: mino
B2: LISTADO DE REQUERIMIENTOS DE COMPRALO | K2: ESTADISTICAS
K3: Requirimientos | L3: =COUNT(B12:D73) -> 8
B4: SI | C4: Marque con una equis (X) si el sistema cumple con la función descrita | K4: Cumplidos | L4: =COUNTIF(F12:F73,"X") -> 8
B5: NO | C5: Marque con una equis (X) si el sistema no cumple con la función descrita | K5: Porcentaje | L5: =PERCENTOF(L4,L3) -> #NAME?
B6: ADI | C6: Marque con una equis (X) si el sistema debe adicionar la función descrita
B7: Observaciones: | D7: Espacio para complementar respuestas
F10: Nivel de cumplimiento | I10: Observaciones
B11: REQUERIMIENTOS FUNCIONALES COOKIES | F11: SI | G11: NO | H11: ADI
B13: 1 | C13: La sección de Política de Cookies debe explicar de forma clara qué son las cookies y para qué se utilizan en la tienda Compralo. | F13: x | I13: Cumple
B14: 2 | C14: La sección debe describir los distintos tipos de cookies que utiliza el sitio (necesarias, funcionales, analíticas, de marketing u otras que se definan) y su propósito. | F14: x | I14: Cumple
B15: 3 | C15: La sección debe indicar explícitamente qué cookies son estrictamente necesarias para el funcionamiento del sitio y que no pueden desactivarse desde el banner. | F15: x | I15: Cumple
B16: 4 | C16: La sección debe informar qué cookies opcionales pueden ser aceptadas o rechazadas por el usuario (funcionales, analíticas, marketing, etc.). | F16: x | I16: Cumple
B17: 5 | C17: La sección debe explicar cómo puede el usuario gestionar sus preferencias de cookies a través del banner inicial y del enlace “Configurar cookies” disponible en el footer. | F17: x | I17: Cumple
B18: 6 | C18: La sección debe indicar el procedimiento para retirar el consentimiento en cualquier momento, incluyendo el acceso directo a la página o componente donde se revocan las cookies opcionales. | F18: x | I18: Cumple
B19: 7 | C19: La sección debe informar si se utilizan cookies de terceros (por ejemplo, herramientas de analítica o publicidad) e identificar a esos terceros o sus categorías. | F19: x | I19: Cumple
B20: 8 | C20: La sección debe indicar la fecha de última actualización de la Política de Cookies para que el usuario sepa desde cuándo son aplicables las condiciones actuales. | F20: x | I20: Cumple

Sheet No-funcionales Cookies
B2: LISTADO DE REQUERIMIENTOS DE COMPRALO | K2: ESTADISTICAS
K3: Requirimientos | L3: =COUNT(B12:D100) -> 30
B4: SI | C4: Marque con una equis (X) si el sistema cumple con la función descrita | K4: Cumplidos | L4: =COUNTIF(F12:F100,"X") -> 30
B5: NO | C5: Marque con una equis (X) si el sistema no cumple con la función descrita | K5: Porcentaje | L5: =PERCENTOF(L4,L3) -> #NAME?
B6: ADI | C6: Marque con una equis (X) si el sistema debe adicionar la función descrita
B7: Observaciones: | D7: Espacio para complementar respuestas
F10: Nivel de cumplimiento | I10: Observaciones
B11: REQUERIMIENTOS NO FUNCIONALES COOKIES | F11: SI | G11: NO | H11: ADI
B13: 1 | C13: La redacción de la Política de Cookies debe utilizar un lenguaje sencillo y comprensible para usuarios no técnicos, evitando jerga legal innecesaria. | F13: x
B14: 2 | C14: La estructura del contenido (títulos, subtítulos, listas) debe facilitar la lectura rápida, permitiendo identificar secciones como “Qué son las cookies”, “Tipos de cookies”, “Cómo gestionar tus preferencias” y “Derechos y más información”. | F14: x
B15: 3 | C15: El texto de la política debe estar disponible al menos en el mismo idioma principal de la tienda y ser fácilmente traducible a otros idiomas (contenido no hardcodeado en el código). | F15: x
B16: 4 | C16: La página de Política de Cookies debe compartir el mismo layout base que el resto del sitio (header, footer, tipografías, colores) para mantener consistencia visual y de navegación. | F16: x
B17: 5 | C17: La sección debe ser totalmente responsiva, presentando el contenido de forma legible tanto en móviles como en pantallas de escritorio sin necesidad de zoom horizontal. | F17: x
B18: 6 | C18: El tamaño de fuente, interlineado y contraste de colores en la Política de Cookies debe cumplir al menos el nivel AA de WCAG 2.1 para asegurar su legibilidad. | F18: x
B19: 7 | C19: Los enlaces dentro de la Política de Cookies (por ejemplo, a la Política de Privacidad o Configurar cookies) deben ser fácilmente reconocibles como tales y accesibles vía teclado. | F19: x
B20: 8 | C20: La sección debe estar optimizada para lectores de pantalla, utilizando encabezados (h1, h2, h3) y listas correctamente anidadas para que la navegación estructurada sea posible. | F20: x
B21: 9 | C21: El tiempo de carga de la página de Política de Cookies no debe diferir de forma significativa del de otras páginas de contenido estático del sitio (sin scripts pesados adicionales). | F21: x
B22: 10 | C22: El contenido de la Política de Cookies debe almacenarse y versionarse de forma que se pueda auditar qué texto estaba vigente en una fecha determinada (por motivos legales/compliance). | F22: x
B23: 11 | C23: Cualquier actualización de la política debe seguir un flujo controlado (revisión y aprobación) antes de ser publicada en producción. | F23: x
B24: 12 | C24: El sistema debe permitir actualizar la fecha de última revisión sin requerir despliegues complejos, idealmente mediante configuración o CMS. | F24: x
... B42: 30 | C42: La sección de descuentos debe respetar las preferencias de cookies y privacidad del usuario, evitando la ejecución de scripts analíticos o de marketing si no se ha otorgado el consentimiento correspondiente. | F42: x

Sheet Funcionales Politicas
A1: mino
B2: LISTADO DE REQUERIMIENTOS DE COMPRALO | K2: ESTADISTICAS
K3: Requirimientos | L3: =COUNT(B12:D75) -> 8
B4: SI | C4: Marque con una equis (X) si el sistema cumple con la función descrita | K4: Cumplidos | L4: =COUNTIF(F12:F75,"X") -> 8
B5: NO | C5: Marque con una equis (X) si el sistema no cumple con la función descrita | K5: Porcentaje | L5: =PERCENTOF(L4,L3) -> #NAME?
B6: ADI | C6: Marque con una equis (X) si el sistema debe adicionar la función descrita
B7: Observaciones: | D7: Espacio para complementar respuestas
F10: Nivel de cumplimiento | I10: Observaciones
B11: REQUERIMIENTOS FUNCIONALES POLITICAS | F11: SI | G11: NO | H11: ADI
B13: 1 | C13: La plataforma debe disponer de una página dedicada de Política de Privacidad accesible desde el footer y desde cualquier punto relevante del sitio. | F13: x | I13: Cumple
B14: 2 | C14: La sección debe indicar claramente el responsable del tratamiento de los datos personales (nombre comercial o razón social y medios de contacto). | F14: x | I14: Cumple
B15: 3 | C15: La sección debe describir de forma explícita los tipos de datos que se recogen (registro, perfil, direcciones, historial de pedidos, navegación, etc.). | F15: x | I15: Cumple
B16: 4 | C16: La sección debe explicar la finalidad y base legal del tratamiento de datos (ejecución del contrato, interés legítimo, consentimiento, obligaciones legales). | F16: x | I16: Cumple
B17: 5 | C17: La sección debe informar los derechos del titular (acceso, rectificación, supresión, oposición, portabilidad, limitación del tratamiento) y el procedimiento para ejercerlos. | F17: x | I17: Cumple
B18: 6 | C18: La sección debe especificar el marco legal aplicable (por ejemplo, Ley 1581 de 2012 y demás normas locales de protección de datos). | F18: x | I18: Cumple
B19: 7 | C19: La sección debe indicar cómo se tratan los datos de pago y financieros (por ejemplo, procesados solo por la pasarela Wompi sin almacenar tarjetas en la plataforma). | F19: x | I19: Cumple
B20: 8 | C20: La sección debe explicar las comunicaciones por email que se envían (transaccionales, de seguridad, marketing opcional) y cómo el usuario puede gestionar sus preferencias. | F20: x | G20: x | I20: No cumple

Sheet No-funcionales Politicas
B2: LISTADO DE REQUERIMIENTOS DE COMPRALO | K2: ESTADISTICAS
K3: Requirimientos | L3: =COUNT(B12:D94) -> 24
B4: SI | C4: Marque con una equis (X) si el sistema cumple con la función descrita | K4: Cumplidos | L4: =COUNTIF(F12:F94,"X") -> 24
B5: NO | C5: Marque con una equis (X) si el sistema no cumple con la función descrita | K5: Porcentaje | L5: =PERCENTOF(L4,L3) -> #NAME?
B6: ADI | C6: Marque con una equis (X) si el sistema debe adicionar la función descrita
B7: Observaciones: | D7: Espacio para complementar respuestas
F10: Nivel de cumplimiento | I10: Observaciones
B11: REQUERIMIENTOS NO FUNCIONALES POLITICAS | F11: SI | G11: NO | H11: ADI
B13: 1 | C13: La página de Política de Privacidad debe ser legible en todo tipo de dispositivo, con tipografía y espaciado que faciliten la lectura de textos largos. | F13: x
B14: 2 | C14: La Política de Privacidad debe estar disponible sin necesidad de iniciar sesión y sin requerir la ejecución de scripts no esenciales. | F14: x
B15: 3 | C15: El contenido de la Política debe ser versionable, conservando fecha de última actualización visible para el usuario. | F15: x
B16: 4 | C16: El texto debe estar redactado en un lenguaje claro y comprensible para personas no expertas en derecho, evitando tecnicismos innecesarios. | F16: x
B17: 5 | C17: La Política de Privacidad debe estar alineada con las prácticas reales de tratamiento de datos implementadas en backend y bases de datos; no debe prometer cosas que el sistema no cumple. | F17: x
B18: 6 | C18: Cualquier cambio relevante en la Política debe poder ser comunicado a los usuarios (por ejemplo, mediante banner o correo) de forma comprobable. | F18: x
B19: 7 | C19: La página debe ser accesible mediante tecnologías de asistencia (lectores de pantalla), con estructura semántica correcta de encabezados y listas. | F19: x
B20: 8 | C20: Los enlaces internos (a contacto, términos, cookies, accesibilidad) deben funcionar de forma consistente y no provocar errores 404. | F20: x
B21: 9 | C21: El rendimiento de la página debe ser óptimo: al ser predominantemente texto, su tiempo de carga debe ser muy bajo incluso en conexiones móviles lentas. | F21: x
B22: 10 | C22: La Política de Privacidad debe estar disponible en todos los idiomas soportados por la instancia, manteniendo equivalencia de contenido entre versiones. | F22: x
B23: 11 | C23: La sección que describe los datos recogidos debe estar sincronizada con los formularios reales (registro, perfil, checkout) para no omitir nuevos campos introducidos. | F23: x
B24: 12 | C24: La descripción de derechos del titular debe incluir instrucciones accionables (correo, formulario, dirección física) que sean válidas y estén monitorizadas. | F24: x
... B36: 24 | C36: Cuando se utilicen servicios de terceros (pasarela de pagos, proveedores de email, herramientas analíticas), la Política debe indicar de forma transparente su rol (encargado o responsable) sin revelar secretos técnicos. | F36: x

Sheet Funcionales Terminos condicione
A1: mino
B2: LISTADO DE REQUERIMIENTOS DE COMPRALO | K2: ESTADISTICAS
K3: Requirimientos | L3: =COUNT(B12:D75) -> 8
B4: SI | C4: Marque con una equis (X) si el sistema cumple con la función descrita | K4: Cumplidos | L4: =COUNTIF(F12:F75,"X") -> 8
B5: NO | C5: Marque con una equis (X) si el sistema no cumple con la función descrita | K5: Porcentaje | L5: =PERCENTOF(L4,L3) -> #NAME?
B6: ADI | C6: Marque con una equis (X) si el sistema debe adicionar la función descrita
B7: Observaciones: | D7: Espacio para complementar respuestas
F10: Nivel de cumplimiento | I10: Observaciones
B11: REQUERIMIENTOS FUNCIONALES TERMINOS & CONDICIONES | F11: SI | G11: NO | H11: ADI
B13: 1 | C13: La sección de Términos y Condiciones debe mostrar el contrato de uso de la plataforma, incluyendo al menos: registro, roles de usuario, carrito, condiciones de compra, comunicaciones y aceptación. | F13: x | I13: Cumple
B14: 2 | C14: La sección debe describir explícitamente los roles soportados por la plataforma (Cliente, Empleado, Administrador) y sus responsabilidades básicas. | F14: x | I14: Cumple
B15: 3 | C15: La sección debe explicar cómo funciona el carrito de compras, incluyendo navegación anónima, asociación a la cuenta al iniciar sesión y comportamiento de los productos agregados. | F15: x | I15: Cumple
B16: 4 | C16: La sección debe detallar las condiciones de compra: precios, impuestos, costos de envío, medio de pago (Wompi) y momento de confirmación de la orden. | F16: x | I16: Cumple
B17: 5 | C17: La sección debe indicar claramente qué tipos de comunicaciones por correo envía la plataforma (registro, órdenes, recuperación de contraseña, etc.) y mediante qué proveedor (Resend). | F17: x | I17: Cumple
B18: 6 | C18: La sección debe incluir una cláusula de aceptación, indicando que el uso de la plataforma implica la aceptación de los Términos de Servicio y de la Política de Privacidad. | F18: x | I18: Cumple
B19: 7 | C19: La sección debe referenciar y enlazar, cuando existan, a otros documentos legales relacionados: Política de Privacidad, Política de Cookies, Accesibilidad y otros avisos legales relevantes. | F19: x | I19: Cumple
B20: 8 | C20: La sección debe indicar el marco legal aplicable (por ejemplo, leyes colombianas específicas como Ley 1480 de 2011, Ley 527 de 1999, Decreto 1074 de 2015) y el país de jurisdicción. | F20: x | I20: Cumple

Sheet No-funcionales Terminos Condici
B2: LISTADO DE REQUERIMIENTOS DE COMPRALO | K2: ESTADISTICAS
K3: Requirimientos | L3: =COUNT(B12:D97) -> 27
B4: SI | C4: Marque con una equis (X) si el sistema cumple con la función descrita | K4: Cumplidos | L4: =COUNTIF(F12:F97,"X") -> 27
B5: NO | C5: Marque con una equis (X) si el sistema no cumple con la función descrita | K5: Porcentaje | L5: =PERCENTOF(L4,L3) -> #NAME?
B6: ADI | C6: Marque con una equis (X) si el sistema debe adicionar la función descrita
B7: Observaciones: | D7: Espacio para complementar respuestas
F10: Nivel de cumplimiento | I10: Observaciones
B11: REQUERIMIENTOS NO FUNCIONALES TERMINOS & CONDICIONES | F11: SI | G11: NO | H11: ADI
B13: 1 | C13: El contenido de Términos y Condiciones debe ser legible en cualquier dispositivo (desktop, tablet, móvil), usando tipografía y espaciado adecuados para textos largos. | F13: x
B14: 2 | C14: La sección debe ser fácilmente navegable, permitiendo al usuario hacer scroll sin interrupciones ni elementos que tapen el texto legal. | F14: x
B15: 3 | C15: El tiempo de carga de la página de Términos y Condiciones debe ser comparable al de otras páginas informativas (por ejemplo, < 2 segundos en banda ancha típicamente), al no depender de llamadas pesadas a la API. | F15: x
B16: 4 | C16: El lenguaje utilizado en Términos y Condiciones debe ser claro, evitando tecnicismos innecesarios, y estar alineado con buenas prácticas de redacción legal para consumidores. | F16: x
B17: 5 | C17: El contenido debe estar disponible al menos en el idioma principal de la instancia (por ejemplo, español de Colombia) y preparado para internacionalización si se soportan otros mercados. | F17: x
B18: 6 | C18: La sección debe estructurarse con encabezados, listas y párrafos que faciliten la lectura y la segmentación de temas (registro, roles, compras, comunicaciones, marco legal, etc.). | F18: x
B19: 7 | C19: La descripción de roles (Cliente, Empleado, Administrador) debe reflejar exactamente las capacidades reales que el sistema otorga, evitando inconsistencias que puedan generar reclamos. | F19: x
B20: 8 | C20: Cualquier cambio en la gestión de roles en la aplicación debe venir acompañado de una revisión del texto de Términos y Condiciones para mantener la alineación. | F20: x
B21: 9 | C21: La sección debe dejar claro que la asignación de roles internos (Empleado, Administrador) es responsabilidad del titular de la tienda, reduciendo ambigüedad de responsabilidad. | F21: x
B22: 10 | C22: La explicación del funcionamiento del carrito debe evitar contradicciones con el comportamiento real (por ejemplo, migración de carrito anónimo a cuenta) y revisarse cuando cambien dichas reglas. | F22: x
B23: 11 | C23: El texto debe aclarar que los productos en el carrito no constituyen una reserva hasta completar el proceso de pago, reduciendo riesgos de malentendidos legales. | F23: x
B24: 12 | C24: La descripción del carrito debe estar libre de supuestos implícitos no soportados por el sistema (por ejemplo, no prometer funcionalidades de wishlist si se gestionan en otra sección). | F24: x
... B39: 27 | C39: La sección debe ser fácilmente imprimible o exportable (por ejemplo, que al imprimir desde el navegador se vea el texto completo con buena maquetación), apoyando requerimientos legales de conservación de contrato. | F39: x

Sheet Funcionales Perfil
B2: LISTADO DE REQUERIMIENTOS DE COMPRALO | K2: ESTADISTICAS
K3: Requirimientos | L3: =COUNT(B12:D77) -> 10
B4: SI | C4: Marque con una equis (X) si el sistema cumple con la función descrita | K4: Cumplidos | L4: =COUNTIF(F12:F77,"X") -> 10
B5: NO | C5: Marque con una equis (X) si el sistema no cumple con la función descrita | K5: Porcentaje | L5: =PERCENTOF(L4,L3) -> #NAME?
B6: ADI | C6: Marque con una equis (X) si el sistema debe adicionar la función descrita
B7: Observaciones: | D7: Espacio para complementar respuestas
F10: Nivel de cumplimiento | I10: Observaciones
B11: REQUERIMIENTOS FUNCIONALES PERFIL | F11: SI | G11: NO | H11: ADI
B13: 1 | C13: La sección de perfil debe mostrar los datos personales básicos del usuario autenticado, incluyendo nombre, apellidos, email, teléfono, fecha de nacimiento, avatar y estado de la cuenta (por ejemplo “Usuario Activo”). | F13: x | I13: Cumple
B14: 2 | C14: El usuario debe poder editar y actualizar sus datos personales (nombre, apellidos, teléfono, fecha de nacimiento, etc.) desde la sección de perfil, guardando los cambios en el backend. | F14: x | G14: x | I14: No cumple. La fecha de nacimiento no se puede editar. NOTA: Elimine terminos que el usuario no entienda en los requerimientos
B15: 3 | C15: La sección de perfil debe permitir cambiar el avatar del usuario seleccionando entre diferentes combinaciones de colores, mostrando una vista previa antes de guardar. | F15: x | I15: Cumple
B16: 4 | C16: El perfil debe mostrar un panel de estadísticas de cuenta con información agregada como total gastado, número de órdenes completadas, cantidad de productos favoritos y puntos de fidelidad acumulados. | F16: x | I16: Cumple
B17: 5 | C17: La pestaña de “Órdenes” debe listar el historial de pedidos del usuario, mostrando para cada orden su identificador, fecha, estado y total pagado. | F17: x | G17: x | I17: No cumple. El numero de la orden no coincide con el numero de compras del cliente
B18: 6 | C18: Desde el historial de órdenes, el usuario debe poder ver el detalle completo de una orden seleccionada, incluyendo productos comprados, cantidades, variantes, subtotales, descuentos y total. | F18: x | I18: Cumple. NOTA: falta metodo de pago en el requerimiento
B19: 7 | C19: En el detalle de una orden, el usuario debe poder crear, editar o cancelar una reseña para cada producto comprado, proporcionando una calificación y un comentario. | F19: x | G19: x | I19: No cumple. No permite editar o eliminar una reseña
B20: 8 | C20: La pestaña de “Direcciones” debe permitir gestionar las direcciones de envío del usuario: listar direcciones existentes, crear nuevas, editarlas, marcarlas como principal y desactivarlas o eliminarlas. | F20: x | G20: x | I20: No cumple. La funcion de activar o desactivar una direccion no funciona, al momento de realizar un pedido o una compra se muestran todas las direcciones.
B21: 9 | C21: La pestaña de “Canje” debe mostrar los puntos de fidelidad disponibles, los canjes de puntos vigentes y los descuentos que el usuario puede canjear con sus puntos. | F21: x | I21: No cumple. No fue posible probarlo, arroja un error al crear descuentos
B22: 10 | C22: La pestaña de “Configuración” debe permitir al usuario gestionar la seguridad de su cuenta, incluyendo cambiar contraseña y solicitar la eliminación definitiva de la cuenta. | F22: x | G22: x | I22: No cumple. No se puede eliminar la cuenta

Sheet No-funcionales Perfil
B2: LISTADO DE REQUERIMIENTOS DE COMPRALO | K2: ESTADISTICAS
K3: Requirimientos | L3: =COUNT(B12:D100) -> 30
B4: SI | C4: Marque con una equis (X) si el sistema cumple con la función descrita | K4: Cumplidos | L4: =COUNTIF(F12:F100,"X") -> 30
B5: NO | C5: Marque con una equis (X) si el sistema no cumple con la función descrita | K5: Porcentaje | L5: =PERCENTOF(L4,L3) -> #NAME?
B6: ADI | C6: Marque con una equis (X) si el sistema debe adicionar la función descrita
B7: Observaciones: | D7: Espacio para complementar respuestas
B8: https://compralo.revital.cloud/discounts
F10: Nivel de cumplimiento | I10: Observaciones
B11: REQUERIMIENTOS NO FUNCIONALES PERFIL | F11: SI | G11: NO | H11: ADI
B13: 1 | C13: La carga inicial de la sección de perfil (datos personales y estadísticas básicas) debe completarse en menos de ~2 segundos en conexiones de banda ancha típicas. | F13: x
B14: 2 | C14: Los datos personales mostrados deben recuperarse únicamente para el usuario autenticado actual, respetando estrictamente las reglas de acceso por token/rol. | F14: x
B15: 3 | C15: Los campos de datos personales deben estar validados en frontend y backend (formatos de email y teléfono, fechas válidas, longitud máxima), devolviendo mensajes de error claros. | F15: x
B16: 4 | C16: El formulario de edición de datos personales debe ofrecer retroalimentación inmediata al usuario (estados de carga, éxito, error) cuando se envían cambios. | F16: x
B17: 5 | C17: La actualización de los datos personales debe ser transaccional: o bien se guardan correctamente todos los campos válidos, o bien se rechaza la operación sin dejar el perfil en un estado inconsistente. | F17: x
B18: 6 | C18: El sistema debe registrar auditoría mínima de cambios críticos (por ejemplo, cambios de email o teléfono) para facilitar trazabilidad y seguridad. | F18: x
B19: 7 | C19: El selector de avatar debe ser completamente responsivo y usable tanto con mouse como con dispositivos táctiles, con un tamaño mínimo de los avatares que facilite su selección. | F19: x
B20: 8 | C20: La acción de guardar avatar debe ejecutarse sin recargar toda la página, mostrando un estado de “guardando” y confirmación visual una vez aplicado. | F20: x
B21: 9 | C21: La paleta de avatares y combinaciones de colores debe cumplir criterios de contraste mínimos para que el avatar sea reconocible en temas claros y oscuros. | F21: x
B22: 10 | C22: El panel de estadísticas de cuenta debe obtener sus datos mediante consultas agregadas optimizadas para no afectar el rendimiento, incluso cuando el usuario tenga muchas órdenes. | F22: x
B23: 11 | C23: Los valores de estadísticas (total gastado, órdenes, puntos) deben actualizarse de forma coherente después de nuevas compras u operaciones, evitando mostrar información desfasada. | F23: x
B24: 12 | C24: El formato de moneda y números en el panel de estadísticas debe seguir la configuración regional de la instancia (símbolo, separadores, decimales). | F24: x
... B42: 30 | C42: Cualquier cambio en la configuración de seguridad debe desencadenar invalidación de sesiones activas según la política definida (por ejemplo, cerrar sesión en otros dispositivos) para reducir el riesgo de accesos no autorizados. | F42: x

Sheet Funcionales Contacto
B2: LISTADO DE REQUERIMIENTOS DE COMPRALO | K2: ESTADISTICAS
K3: Requirimientos | L3: =COUNT(B12:D75) -> 8
B4: SI | C4: Marque con una equis (X) si el sistema cumple con la función descrita | K4: Cumplidos | L4: =COUNTIF(F12:F75,"X") -> 8
B5: NO | C5: Marque con una equis (X) si el sistema no cumple con la función descrita | K5: Porcentaje | L5: =PERCENTOF(L4,L3) -> #NAME?
B6: ADI | C6: Marque con una equis (X) si el sistema debe adicionar la función descrita
B7: Observaciones: | D7: Espacio para complementar respuestas
B8: https://compralo.revital.cloud/contacto
F10: Nivel de cumplimiento | I10: Observaciones
B11: REQUERIMIENTOS CONTACTO | F11: SI | G11: NO | H11: ADI
B13: 1 | C13: La sección de contacto debe mostrar claramente los datos de contacto principales de la tienda: correo electrónico, teléfono y dirección física. | F13: x | I13: Cumple
B14: 2 | C14: La sección de contacto debe mostrar el horario de atención al cliente (días y franjas horarias) de forma legible. | F14: x | I14: Cumple
B15: 3 | C15: La sección de contacto debe incluir un enlace o botón “Volver al inicio” que lleve al usuario a la página principal. | F15: x | I15: Cumple
B16: 4 | C16: La sección de contacto debe reutilizar el mismo header, barra superior, menú de navegación y footer que el resto del sitio, manteniendo el ítem “Contacto” como activo. | F16: x | I16: Cumple Recomendación: Evitar usar tanto lenguaje técnico en los requerimientos funcionales :).
B17: 5 | C17: La sección de contacto debe permitir que, al hacer clic en el correo electrónico mostrado, se abra el cliente de correo del usuario con la dirección prellenada (enlace mailto). | F17: x | I17: Cumple
B18: 6 | C18: La sección de contacto debe permitir que, al hacer clic en el teléfono mostrado en dispositivos móviles, se inicie una llamada telefónica (enlace tel). | F18: x | I18: Cumple
B19: 7 | C19: La sección de contacto debe mostrar un bloque de texto que indique que el formulario de contacto está en desarrollo y ofrezca canales alternativos (teléfono/correo) mientras tanto. | F19: x | I19: Cumple
B20: 8 | C20: La sección de contacto debe permitir, en el futuro, incluir un formulario de contacto con campos para nombre, correo, asunto y mensaje, enviando la información al backend para su gestión. | F20: x | H20: x | I20: No se ha implementado por lo tanto en el nivel de cumplimiento debe ir ADI.

Sheet No-funcionales Contacto
B2: LISTADO DE REQUERIMIENTOS DE COMPRALO | K2: ESTADISTICAS
K3: Requirimientos | L3: =COUNT(B12:D97) -> 30
B4: SI | C4: Marque con una equis (X) si el sistema cumple con la función descrita | K4: Cumplidos | L4: =COUNTIF(F12:F97,"X") -> 30
B5: NO | C5: Marque con una equis (X) si el sistema no cumple con la función descrita | K5: Porcentaje | L5: =PERCENTOF(L4,L3) -> #NAME?
B6: ADI | C6: Marque con una equis (X) si el sistema debe adicionar la función descrita
B7: Observaciones: | D7: Espacio para complementar respuestas
B8: https://compralo.revital.cloud/contacto
F10: Nivel de cumplimiento | I10: Observaciones
B11: REQUERIMIENTOS CONTACTO | F11: SI | G11: NO | H11: ADI
B13: 1 | C13: El listado inicial de descuentos debe cargarse en menos de aproximadamente 2 segundos en conexiones de banda ancha típicas. | F13: x
B14: 2 | C14: La consulta que obtiene los descuentos activos debe filtrar por fecha de vigencia y estado para evitar recorrer descuentos expirados o desactivados. | F14: x
B15: 3 | C15: El endpoint que lista descuentos debe mantener un tiempo de respuesta objetivo P95 menor a 500 ms bajo carga normal. | F15: x
B16: 4 | C16: El formato de porcentajes y montos debe seguir la configuración regional de la instancia (símbolo de moneda, separadores de miles y decimales). | F16: x
B17: 5 | C17: Los valores de descuento deben formatearse de forma consistente en toda la interfaz para reducir ambigüedades y errores de interpretación. | F17: x
B18: 6 | C18: La lógica que calcula y muestra los valores de descuento debe estar cubierta por pruebas automatizadas que validen diversos casos (porcentajes altos, montos pequeños, redondeos). | F18: x
B19: 7 | C19: La obtención de la información de ámbito (categorías, productos, reglas) debe realizarse con consultas optimizadas (joins mínimos, uso de índices sobre columnas de relación). | F19: x
B20: 8 | C20: La descripción del ámbito de aplicación debe generarse a partir de datos estructurados y ser fácilmente traducible a otros idiomas sin cambios de código. | F20: x
B21: 9 | C21: Los textos que explican el ámbito deben ser claros, concisos y evitar tecnicismos innecesarios para disminuir el riesgo de reclamaciones por malentendidos. | F21: x
B22: 10 | C22: El cálculo de estados de vigencia (próximo, activo, pronto a expirar, expirado) debe basarse en la zona horaria configurada para la instancia y no en la hora local del navegador. | F22: x
B23: 11 | C23: El formato de fechas mostrado para vigencia debe ser consistente en toda la aplicación y configurable por región (por ejemplo, DD/MM/AAAA o MM/DD/YYYY). | F23: x
B24: 12 | C24: El refresco del estado visual de vigencia no debe requerir recargar toda la página; idealmente debe recalcularse en cliente o con llamadas ligeras al backend. | F24: x
... B42: 30 | C42: La sección de descuentos debe respetar las preferencias de cookies y privacidad del usuario, evitando la ejecución de scripts analíticos o de marketing si no se ha otorgado el consentimiento correspondiente. | F42: x

Sheet Funcionales Seguimiento
B2: LISTADO DE REQUERIMIENTOS DE COMPRALO | K2: ESTADISTICAS
K3: Requirimientos | L3: =COUNT(B12:D58) -> 2
B4: SI | C4: Marque con una equis (X) si el sistema cumple con la función descrita | K4: Cumplidos | L4: =COUNTIF(F12:F58,"X") -> 1
B5: NO | C5: Marque con una equis (X) si el sistema no cumple con la función descrita | K5: Porcentaje | L5: =PERCENTOF(L4,L3) -> #NAME?
B6: ADI | C6: Marque con una equis (X) si el sistema debe adicionar la función descrita
B7: Observaciones: | D7: Espacio para complementar respuestas
B9: https://compralo.revital.cloud/seguimiento
F10: Nivel de cumplimiento | I10: Observaciones
B11: REQUERIMIENTOS FUNCIONALES SEGUIMIENTO | F11: SI | G11: NO | H11: ADI
B13: 1 | C13: La sección “Seguir pedido” debe mostrar un título y una descripción indicando que permite consultar el estado del envío con número de pedido y email. | H13: x | I13: NO CUMPLE, No se ha implementado
B14: 2 | C14: La sección debe incluir un enlace “Volver al inicio” que redirija a /. | F14: x | I14: Cumple

Sheet No-Funcionales Seguimiento
B2: LISTADO DE REQUERIMIENTOS DE COMPRALO | K2: ESTADISTICAS
K3: Requirimientos | L3: =COUNT(B12:D58) -> 5
B4: SI | C4: Marque con una equis (X) si el sistema cumple con la función descrita | K4: Cumplidos | L4: =COUNTIF(F12:F58,"X") -> 5
B5: NO | C5: Marque con una equis (X) si el sistema no cumple con la función descrita | K5: Porcentaje | L5: =PERCENTOF(L4,L3) -> #NAME?
B6: ADI | C6: Marque con una equis (X) si el sistema debe adicionar la función descrita
B7: Observaciones: | D7: Espacio para complementar respuestas
F10: Nivel de cumplimiento | I10: Observaciones
B11: REQUERIMIENTOS FUNCIONALES NO SEGUIMIENTO | F11: SI | G11: NO | H11: ADI
B13: 1 | C13: La página debe ser responsiva (contenedor centrado y legible en móvil/desktop) sin desbordes horizontales. | F13: x
B14: 2 | C14: La página debe ser accesible: jerarquía de encabezados clara (h1/h2), texto con buen contraste en modo claro/oscuro y navegación por teclado para el enlace “Volver al inicio”. | F14: x
B15: 3 | C15: La página debe cargar rápido al ser contenido mayormente estático (sin esperas perceptibles para mostrar el contenido). | F15: x
B16: 4 | C16: El contenido debe mostrarse de forma consistente (sin saltos de layout importantes) al cargar. | F16: x
B17: 5 | C17: Los textos deben ser claros y sin ambigüedad sobre el estado actual: el formulario real no está disponible todavía. | F17: x

Sheet Funcionales Inversionistas
B2: LISTADO DE REQUERIMIENTOS DE COMPRALO | K2: ESTADISTICAS
K3: Requirimientos | L3: =COUNT(B12:D65) -> 5
B4: SI | C4: Marque con una equis (X) si el sistema cumple con la función descrita | K4: Cumplidos | L4: =COUNTIF(F12:F65,"X") -> 5
B5: NO | C5: Marque con una equis (X) si el sistema no cumple con la función descrita | K5: Porcentaje | L5: =PERCENTOF(L4,L3) -> #NAME?
B6: ADI | C6: Marque con una equis (X) si el sistema debe adicionar la función descrita
B7: Observaciones: | D7: Espacio para complementar respuestas
F10: Nivel de cumplimiento | I10: Observaciones
B11: REQUERIMIENTOS FUNCIONALES INVERSIONISTAS | F11: SI | G11: NO | H11: ADI
B13: 1 | C13: La página de Inversionistas debe mostrar un título y una descripción breve del contenido (resumen corporativo). (en el pie de página) | F13: x | I13: Cumple.
B14: 2 | C14: La página debe mostrar una sección de cifras destacadas con tarjetas (ej.: ventas anuales, pedidos entregados, usuarios activos) y sus valores. | F14: x | I14: Cumple.
B15: 3 | C15: La página debe indicar explícitamente cuando las cifras mostradas son de ejemplo/ilustrativas (disclaimer visible). | F15: x | I15: Cumple.
B16: 4 | C16: La página debe mostrar un correo de contacto para inversionistas (ej.: inversionistas@compralo.com) para solicitudes de información. | F16: x | I16: Cumple.
B17: 5 | C17: La página debe incluir un enlace o acción de “Volver al inicio”. | F17: x | I17: Cumple.

Sheet No-funcionales Inversionistas
B2: LISTADO DE REQUERIMIENTOS DE COMPRALO | K2: ESTADISTICAS
K3: Requirimientos | L3: =COUNT(B12:D100) -> 36
B4: SI | C4: Marque con una equis (X) si el sistema cumple con la función descrita | K4: Cumplidos | L4: =COUNTIF(F12:F100,"X") -> 36
B5: NO | C5: Marque con una equis (X) si el sistema no cumple con la función descrita | K5: Porcentaje | L5: =PERCENTOF(L4,L3) -> #NAME?
B6: ADI | C6: Marque con una equis (X) si el sistema debe adicionar la función descrita
B7: Observaciones: | D7: Espacio para complementar respuestas
F10: Nivel de cumplimiento | I10: Observaciones
B11: REQUERIMIENTOS NO FUNCIONALES INVERSIONISTAS | F11: SI | G11: NO | H11: ADI
B13: 1 | C13: La página debe cargar el contenido principal (título + cifras) en un tiempo razonable (objetivo ~3s en condiciones normales). | F13: x
B14: 2 | C14: El diseño debe ser responsive (móvil/tablet/escritorio) sin que las tarjetas se solapen ni se corten textos. | F14: x
B15: 3 | C15: Las tarjetas de cifras deben mantener legibilidad: contraste suficiente y tamaños de fuente adecuados. | F15: x
B16: 4 | C16: El disclaimer de “datos de ejemplo” debe ser claramente visible (no depender solo de color). | F16: x
B17: 5 | C17: El correo de contacto debe ser copiable y/o clicable (mailto) sin errores. | F17: x
B18: 6 | C18: El enlace “Volver al inicio” debe funcionar sin recargas innecesarias y mantener una navegación consistente con el resto del sitio. | F18: x
B19: 7 | C19: La página debe ser accesible por teclado: foco visible en enlaces/botones y orden de tabulación lógico. | F19: x
B20: 8 | C20: El contenido debe ser estático o cacheable para minimizar latencia (no debe bloquearse por llamadas pesadas si solo son datos informativos). | F20: x
B21: 9 | C21: Los textos deben ser consistentes con el idioma del sitio (español) y fáciles de mantener (sin hardcode disperso si luego se migra a CMS). | F21: x
B22: 10 | C22: No debe mostrarse información sensible real por error (si las cifras son “ejemplo”, debe mantenerse así hasta que exista un origen de datos validado). | F22: x
B23: 11 | C23: Debe manejarse correctamente el estado “sin datos” si en el futuro las cifras vienen de API (mostrar placeholder/mensaje en vez de romper el layout). | F23: x
B24: 12 | C24: La estructura debe permitir agregar más tarjetas de cifras sin degradar el layout (grilla adaptable). | F24: x
... B48: 36 | C48: Los metadatos (por ejemplo etiquetas Open Graph, esquema de producto) deben poder configurarse para mejorar la compartición en redes sociales y motores de búsqueda. | F48: x

Sheet Funcionales Devoluciones
B2: LISTADO DE REQUERIMIENTOS DE COMPRALO | K2: ESTADISTICAS
K3: Requirimientos | L3: =COUNT(B12:D63) -> 11
B4: SI | C4: Marque con una equis (X) si el sistema cumple con la función descrita | K4: Cumplidos | L4: =COUNTIF(F12:F63,"X") -> 11
B5: NO | C5: Marque con una equis (X) si el sistema no cumple con la función descrita | K5: Porcentaje | L5: =PERCENTOF(L4,L3) -> #NAME?
B6: ADI | C6: Marque con una equis (X) si el sistema debe adicionar la función descrita
B7: Observaciones: | D7: Espacio para complementar respuestas
F10: Nivel de cumplimiento | I10: Observaciones
B11: REQUERIMIENTOS FUNCIONALES DEVOLUCIONES | F11: SI | G11: NO | H11: ADI
B13: 1 | C13: La sección de devoluciones debe mostrar el título “Devoluciones” y una descripción breve de que es una política/proceso de devoluciones. | F13: x | I13: Cumple.
B14: 2 | C14: La sección debe mostrar claramente el plazo para devoluciones (en el ejemplo: 30 días desde la recepción del producto). | F14: x | I14: Cumple.
B15: 3 | C15: La sección debe mostrar un bloque de condiciones para aceptar una devolución (en el ejemplo: producto sin usar, empaque original con etiquetas, incluir factura/comprobante, y restricciones para ciertos productos como higiene o electrónica abierta). | F15: x | I15: Cumple.
B16: 4 | C16: La sección debe mostrar el proceso de devolución como una lista de pasos numerados (en el ejemplo: proceso en 4 pasos). | F16: x | I16: Cumple.
B17: 5 | C17: El paso 1 del proceso debe indicar que el cliente debe contactar a atención al cliente e incluir al menos “número de pedido” y “motivo”. | F17: x | I17: Cumple.
B18: 6 | C18: El proceso debe indicar que la tienda enviará etiqueta/instrucciones para el envío de vuelta (paso 2). | F18: x | I18: Cumple.
B19: 7 | C19: El proceso debe indicar que el cliente debe empacar y entregar el producto al mensajero o en un punto indicado (paso 3). | F19: x | I19: Cumple.
B20: 8 | C20: El proceso debe indicar que el reembolso se procesa tras revisión y un tiempo estimado (en el ejemplo: 5–10 días hábiles) (paso 4). | F20: x | I20: Cumple.
B21: 9 | C21: La sección debe mostrar la regla de que el reembolso se realiza por el mismo método de pago usado en la compra. | F21: x | I21: Cumple.
B22: 10 | C22: La sección debe incluir un enlace/acción de “Volver al inicio”. | F22: x | I22: Cumple.
B23: 11 | C23: La sección debe mantener el header y footer globales del sitio para navegación consistente. | F23: x | I23: Cumple. NOTA: Elimine terminos que el usuario no entienda en los requerimientos

Sheet No-funcionales Devoluciones
B2: LISTADO DE REQUERIMIENTOS DE COMPRALO | K2: ESTADISTICAS
K3: Requirimientos | L3: =COUNT(B12:D69) -> 9
B4: SI | C4: Marque con una equis (X) si el sistema cumple con la función descrita | K4: Cumplidos | L4: =COUNTIF(F12:F69,"X") -> 9
B5: NO | C5: Marque con una equis (X) si el sistema no cumple con la función descrita | K5: Porcentaje | L5: =PERCENTOF(L4,L3) -> #NAME?
B6: ADI | C6: Marque con una equis (X) si el sistema debe adicionar la función descrita
B7: Observaciones: | D7: Espacio para complementar respuestas
F10: Nivel de cumplimiento | I10: Observaciones
B11: REQUERIMIENTOS NO FUNCIONALES DEVOLUCIONES | F11: SI | G11: NO | H11: ADI
B13: 1 | C13: La página de devoluciones debe ser responsive (usable en móvil y escritorio sin desbordes). | F13: x
B14: 2 | C14: El contenido (plazo, condiciones y pasos) debe ser legible: tipografía clara, espaciado suficiente y jerarquía visual (títulos/subtítulos). | F14: x
B15: 3 | C15: El contenido debe ser accesible: estructura con encabezados, listas reales (no solo texto), y elementos interactivos (como “Volver al inicio”) accesibles por teclado con foco visible. | F15: x
B16: 4 | C16: Los pasos numerados deben ser claros y consistentes (numeración visible, orden correcto, sin ambigüedades). | F16: x
B17: 5 | C17: La página debe cargar sin depender de datos dinámicos (al ser contenido informativo) y debe mostrar el contenido completo aun si falla cualquier llamada externa. | F17: x
B18: 6 | C18: Los textos deben poder actualizarse sin romper el layout (si cambian plazos, condiciones o número de pasos). | F18: x
B19: 7 | C19: El enlace “Volver al inicio” debe ser visible y funcionar correctamente (sin errores de navegación). | F19: x
B20: 8 | C20: El contenido debe ser coherente con el resto del sitio (mismos estilos generales, header/footer). | F20: x
B21: 9 | C21: Debe evitarse cualquier contradicción interna: plazo, condiciones, pasos y método de reembolso deben presentarse de forma consistente en la misma página. | F21: x

Sheet Funcionales Ayuda
B2: LISTADO DE REQUERIMIENTOS DE COMPRALO | K2: ESTADISTICAS
K3: Requirimientos | L3: =COUNT(B12:D63) -> 5
B4: SI | C4: Marque con una equis (X) si el sistema cumple con la función descrita | K4: Cumplidos | L4: =COUNTIF(F12:F63,"X") -> 5
B5: NO | C5: Marque con una equis (X) si el sistema no cumple con la función descrita | K5: Porcentaje | L5: =PERCENTOF(L4,L3) -> #NAME?
B6: ADI | C6: Marque con una equis (X) si el sistema debe adicionar la función descrita
B7: Observaciones: | D7: Espacio para complementar respuestas
F10: Nivel de cumplimiento | I10: Observaciones
B11: REQUERIMIENTOS FUNCIONALES AYUDA | F11: SI | G11: NO | H11: ADI
B13: 1 | C13: La sección “Centro de Ayuda” debe mostrar un título y una descripción indicando que contiene preguntas frecuentes y recursos. | F13: x | I13: Cumple.
B14: 2 | C14: La sección debe mostrar una lista de preguntas frecuentes (FAQ), donde cada ítem tenga una pregunta y una respuesta. | F14: x | I14: Cumple.
B15: 3 | C15: Cada pregunta del FAQ no debe poder expandirse/colapsarse para ver u ocultar su respuesta. | F15: x | I15: Cumple.
B16: 4 | C16: El FAQ debe incluir, como mínimo, estas preguntas (según lo mostrado): “¿Cómo realizo un pedido?” , “¿Cuáles son los plazos de entrega?”, “¿Puedo cambiar o devolver un producto?”, “¿Cómo contacto a soporte?” | F16: x | I16: Cumple.
B17: 5 | C17: La sección debe mostrar una franja o mensaje final del tipo “¿No encuentras lo que buscas?” con un correo de contacto (ej. contacto@compralo.com) para soporte. | F17: x | I17: Cumple.

Sheet No-funcionales Ayuda
B2: LISTADO DE REQUERIMIENTOS DE COMPRALO | K2: ESTADISTICAS
K3: Requirimientos | L3: =COUNT(B12:D69) -> 15
B4: SI | C4: Marque con una equis (X) si el sistema cumple con la función descrita | K4: Cumplidos | L4: =COUNTIF(F12:F69,"X") -> 15
B5: NO | C5: Marque con una equis (X) si el sistema no cumple con la función descrita | K5: Porcentaje | L5: =PERCENTOF(L4,L3) -> #NAME?
B6: ADI | C6: Marque con una equis (X) si el sistema debe adicionar la función descrita
B7: Observaciones: | D7: Espacio para complementar respuestas
F10: Nivel de cumplimiento | I10: Observaciones
B11: REQUERIMIENTOS NO FUNCIONALES AYUDA | F11: SI | G11: NO | H11: ADI
B13: 1 | C13: La página del Centro de Ayuda debe cargar y ser usable en navegadores modernos (Chrome/Firefox/Safari/Edge). | F13: x
B14: 2 | C14: El contenido (título + FAQ visible) debe renderizarse sin “saltos” visuales notorios (evitar CLS grande al expandir ítems). | F14: x
B15: 3 | C15: La interacción de expandir/colapsar una pregunta debe responder de forma inmediata (sin retrasos perceptibles). | F15: x
B16: 4 | C16: La sección debe ser responsive: el layout debe verse correctamente en móvil y escritorio sin desbordes de texto. | F16: x
B17: 5 | C17: Los ítems del FAQ deben ser accesibles por teclado (tab, enter/space) y con foco visible. | F17: x
B18: 6 | C18: Cada pregunta debe tener etiquetas/atributos de accesibilidad adecuados (por ejemplo, aria-expanded) para lectores de pantalla. | F18: x
B19: 7 | C19: El contraste de texto (preguntas, respuestas, enlaces) debe ser suficiente para lectura en modo oscuro (WCAG AA como referencia). | F19: x
B20: 8 | C20: El correo de contacto debe ser claramente identificable y usable (clicable o copiable) sin ambigüedad. | F20: x
B21: 9 | C21: Si el contenido del FAQ es estático, debe entregarse de forma eficiente (sin llamadas innecesarias a la API). | F21: x
B22: 10 | C22: El texto del FAQ debe ser consistente y legible, con tamaños de fuente y espaciado que no cansen la lectura. | F22: x
B23: 11 | C23: Expandir un ítem no debe romper el scroll: el usuario no debe perder su posición ni “saltar” a otra parte de la página. | F23: x
B24: 12 | C24: La sección debe mantener consistencia visual con el resto del sitio (header/footer/estilos). | F24: x
... B27: 15 | C27: La sección debe evitar errores silenciosos: si algo falla al renderizar un ítem, debe degradar mostrando al menos el texto básico. | F27: x

Sheet Funcionales Prensa
B2: LISTADO DE REQUERIMIENTOS DE COMPRALO | K2: ESTADISTICAS
K3: Requirimientos | L3: =COUNT(B12:D96) -> 8
B4: SI | C4: Marque con una equis (X) si el sistema cumple con la función descrita | K4: Cumplidos | L4: =COUNTIF(F12:F96,"X") -> 8
B5: NO | C5: Marque con una equis (X) si el sistema no cumple con la función descrita | K5: Porcentaje | L5: =PERCENTOF(L4,L3) -> #NAME?
B6: ADI | C6: Marque con una equis (X) si el sistema debe adicionar la función descrita
B7: Observaciones: | D7: Espacio para complementar respuestas
F10: Nivel de cumplimiento | I10: Observaciones
B11: REQUERIMIENTOS FUNCIONALES PRENSA | F11: SI | G11: NO | H11: ADI
B13: 1 | C13: La tienda debe exponer una ruta pública /prensa accesible desde el footer mediante el enlace de empresa Prensa. | F13: x | I13: Cumple. NOTA: Elimine terminos que el usuario no entienda en los requerimientos
B14: 2 | C14: La página /prensa debe mostrar el título principal “Sala de Prensa” y un subtítulo descriptivo indicando que son comunicados y notas de prensa de ejemplo. | F14: x | I14: Cumple.
B15: 3 | C15: La sección debe renderizar un listado de comunicados de prensa a partir de una colección de objetos (id, título, fecha, resumen) definida en el frontend. | F15: x | I15: Cumple. NOTA: Elimine terminos que el usuario no entienda en los requerimientos
B16: 4 | C16: Cada comunicado de prensa debe mostrar al menos: fecha de publicación, título y un resumen breve del contenido. | F16: x | I16: Cumple.
B17: 5 | C17: La fecha de cada comunicado debe mostrarse formateada en español de Colombia usando toLocaleDateString("es-CO", { dateStyle: "long" }). | F17: x | I17: Requerimiento no funcional
B18: 6 | C18: Los comunicados deben presentarse como tarjetas apiladas verticalmente, con borde y fondo diferenciado para cada elemento. | F18: x | I18: Cumple.
B19: 7 | C19: La sección debe incluir un texto de contacto para prensa con el correo contacto@compralo.com y la instrucción de usar el asunto “Prensa”. | F19: x | I19: Cumple.
B20: 8 | C20: La página debe ofrecer un enlace de navegación “← Volver al inicio” que lleve a la ruta /. | F20: x | I20: Cumple. NOTA: Elimine terminos que el usuario no entienda en los requerimientos

Sheet No-funcionales Prensa
B2: LISTADO DE REQUERIMIENTOS DE COMPRALO | K2: ESTADISTICAS
K3: Requirimientos | L3: =COUNT(B12:D69) -> 5
B4: SI | C4: Marque con una equis (X) si el sistema cumple con la función descrita | K4: Cumplidos | L4: =COUNTIF(F12:F69,"X") -> 5
B5: NO | C5: Marque con una equis (X) si el sistema no cumple con la función descrita | K5: Porcentaje | L5: =PERCENTOF(L4,L3) -> #NAME?
B6: ADI | C6: Marque con una equis (X) si el sistema debe adicionar la función descrita
B7: Observaciones: | D7: Espacio para complementar respuestas
F10: Nivel de cumplimiento | I10: Observaciones
B11: REQUERIMIENTOS NO FUNCIONALES PRENSA | F11: SI | G11: NO | H11: ADI
B13: 1 | C13: La página de prensa debe utilizar un layout centrado y legible, con contenedor max-w-4xl, márgenes horizontales (mx-auto, px-4) y espacio vertical (py-10). | F13: x
B14: 2 | C14: El diseño de las tarjetas de prensa debe ser coherente con el tema visual de la tienda, usando colores claros/oscuros compatibles (bg-gray-50/50 / dark:bg-gray-800/50, bordes border-gray-200 / dark:border-gray-700). | F14: x
B15: 3 | C15: La sección debe ser compatible con modo oscuro, aplicando variantes dark: a textos, bordes y fondos para mantener el contraste. | F15: x
B16: 4 | C16: La estructura del listado debe ser semántica y accesible, usando elementos HTML apropiados (<ul>, <li>, <time>, <h2>, <p>) para que lectores de pantalla puedan interpretar correctamente la información. | F16: x
B17: 5 | C17: El enlace de vuelta al inicio debe ser claramente identificable como acción navegable (estilo de texto rojo de marca y hover:underline) sin romper el diseño general. | F17: x

Sheet Funcionales Acerca de
B2: LISTADO DE REQUERIMIENTOS DE COMPRALO | K2: ESTADISTICAS
K3: Requirimientos | L3: =COUNT(B12:D99) -> 11
B4: SI | C4: Marque con una equis (X) si el sistema cumple con la función descrita | K4: Cumplidos | L4: =COUNTIF(F12:F99,"X") -> 11
B5: NO | C5: Marque con una equis (X) si el sistema no cumple con la función descrita | K5: Porcentaje | L5: =PERCENTOF(L4,L3) -> #NAME?
B6: ADI | C6: Marque con una equis (X) si el sistema debe adicionar la función descrita
B7: Observaciones: | D7: Espacio para complementar respuestas
F10: Nivel de cumplimiento | I10: Observaciones
B11: REQUERIMIENTOS FUNCIONALES ACERCA DE | F11: SI | G11: NO | H11: ADI
B13: 1 | C13: La sección “Acerca de” debe mostrar un título principal (por ejemplo “Acerca de Compralo”) y un subtítulo descriptivo. | F13: x | I13: Cumple
B14: 2 | C14: La sección debe mostrar el bloque “Nuestra misión” con un texto explicativo configurable. | F14: x | G14: x | I14: No cumple. No es posible modificar el texto
B15: 3 | C15: La sección debe mostrar el bloque “Nuestra visión” con un texto explicativo configurable. | F15: x | G15: x | I15: No cumple. No es posible modificar el texto
B16: 4 | C16: La sección debe mostrar el bloque “Valores” con una lista de valores (por ejemplo Confianza, Innovación, Compromiso), cada uno con nombre y descripción. | F16: x | I16: Cumple.
B17: 5 | C17: La sección debe mostrar el bloque “Equipo directivo” con una lista de integrantes y su rol (por ejemplo CEO, CTO, Directora de Operaciones). | F17: x | I17: Cumple.
A18: 6 | B18: 6 | C18: La sección debe incluir un enlace o botón “Volver al inicio” que redirija a la home. | F18: x | I18: Cumple.
B19: 7 | C19: La sección debe mantener visible y funcional el header global (logo, menú, buscador, carrito, acceso a cuenta) para permitir navegación sin salir de la página. | F19: x | I19: Cumple. NOTA: Elimine terminos que el usuario no entienda en los requerimientos
B20: 8 | C20: La sección debe incluir el footer global con enlaces a páginas legales, categorías, empresa y atención al cliente. | F20: x | I20: Cumple. NOTA: Elimine terminos que el usuario no entienda en los requerimientos
B21: 9 | C21: La sección debe resaltar en el menú el ítem correspondiente (por ejemplo “Empresa” o “Acerca de”) cuando el usuario se encuentre en esta página. | F21: x | I21: No cumple. Solo se resalta al colocar el clic encima pero no se mantiene al ingresar a la seccion
B22: 10 | C22: La sección debe poder mostrar información adicional opcional (historia de la empresa, hitos, métricas, certificaciones) si la instancia lo habilita. | F22: x | G22: x | I22: No cumple.
B23: 11 | C23: La sección debe poder incluir enlaces de contacto (email, teléfono, redes). | F23: x | G23: x | I23: No cumple.

Sheet No-funcionales Acerca de
B2: LISTADO DE REQUERIMIENTOS DE COMPRALO | K2: ESTADISTICAS
K3: Requirimientos | L3: =COUNT(B12:D100) -> 36
B4: SI | C4: Marque con una equis (X) si el sistema cumple con la función descrita | K4: Cumplidos | L4: =COUNTIF(F12:F100,"X") -> 36
B5: NO | C5: Marque con una equis (X) si el sistema no cumple con la función descrita | K5: Porcentaje | L5: =PERCENTOF(L4,L3) -> #NAME?
B6: ADI | C6: Marque con una equis (X) si el sistema debe adicionar la función descrita
B7: Observaciones: | D7: Espacio para complementar respuestas
F10: Nivel de cumplimiento | I10: Observaciones
B11: REQUERIMIENTOS NO FUNCIONALES ACERCA DE | F11: SI | G11: NO | H11: ADI
B13: 1 | C13: La página debe cargar el contenido principal en menos de ~3 segundos en conexiones de banda ancha típicas. | F13: x
B14: 2 | C14: El layout debe ser totalmente responsivo, adaptándose a móviles, tablets y escritorio sin desbordes ni cortes de texto. | F14: x
B15: 3 | C15: Los textos deben mantener legibilidad (tamaños, interlineado, ancho de línea) en distintos tamaños de pantalla. | F15: x
B16: 4 | C16: Los encabezados deben seguir una jerarquía semántica correcta (H1, H2, H3) para accesibilidad y SEO. | F16: x
B17: 5 | C17: La página debe ser navegable por teclado con foco visible en enlaces y botones. | F17: x
B18: 6 | C18: El contraste de texto y elementos debe cumplir al menos con WCAG 2.1 AA. | F18: x
B19: 7 | C19: El contenido debe ser localizable (preparado para traducción) sin reestructurar la página. | F19: x
B20: 8 | C20: El “Volver al inicio” debe ser accesible (texto claro y/o aria-label descriptivo) y visible sin esfuerzo. | F20: x
B21: 9 | C21: La página no debe producir saltos de layout (CLS) notables; el espacio para bloques debe reservarse adecuadamente. | F21: x
B22: 10 | C22: Si se usa CMS/configuración para contenidos, debe existir validación para evitar contenido roto (por ejemplo, valores sin título, roles vacíos). | F22: x
B23: 11 | C23: El contenido mostrado no debe exponer información sensible (correos internos, datos personales no autorizados). | F23: x
B24: 12 | C24: La página debe mantener consistencia visual con el resto del sitio (tipografía, espaciado, componentes, tema claro/oscuro). | F24: x
... B48: 36 | C48: Los metadatos (por ejemplo etiquetas Open Graph, esquema de producto) deben poder configurarse para mejorar la compartición en redes sociales y motores de búsqueda. | F48: x

Sheet Funcionales chatbotInformativo
B2: LISTADO DE REQUERIMIENTOS DE COMPRALO | K2: ESTADISTICAS
K3: Requirimientos | L3: =COUNT(B12:D93) -> 5
B4: SI | C4: Marque con una equis (X) si el sistema cumple con la función descrita | K4: Cumplidos | L4: =COUNTIF(F12:F93,"X") -> 5
B5: NO | C5: Marque con una equis (X) si el sistema no cumple con la función descrita | K5: Porcentaje | L5: =PERCENTOF(L4,L3) -> #NAME?
B6: ADI | C6: Marque con una equis (X) si el sistema debe adicionar la función descrita
B7: Observaciones: | D7: Espacio para complementar respuestas
F10: Nivel de cumplimiento | I10: Observaciones
B11: REQUERIMIENTOS FUNCIONALES CHAT BOT INFORMATIVO | F11: SI | G11: NO | H11: ADI
B13: 1 | C13: El chatbot informativo debe poder abrirse y cerrarse desde un botón flotante visible en la interfaz sin interferir con otros elementos importantes de la página. | F13: x | I13: Cumple.
B14: 2 | C14: Al abrirse, el chatbot debe mostrar un mensaje de bienvenida e imprimir un menú numerado con las opciones: (1) Términos y condiciones, (2) Protección de datos y transacciones, (3) Descuentos activos, (4) Sistema de puntos, (5) Garantías y devoluciones y (6) Salir. | F14: x | I14: Cumple.
B15: 3 | C15: El chatbot debe aceptar como entrada un número de opción y responder con un texto explicativo correspondiente a la opción elegida, sin requerir comandos adicionales. | F15: x | I15: Cumple.
B16: 4 | C16: Cuando el usuario seleccione la opción “Descuentos activos”, el chatbot debe mostrar un resumen legible de los descuentos actualmente disponibles en la tienda, coherente con la sección de Descuentos. | F16: x | I16: Cumple.
B17: 5 | C17: Cuando el usuario seleccione la opción “Sistema de puntos”, el chatbot debe mostrar una explicación clara de cómo se acumulan, consultan y canjean los puntos de fidelidad, coherente con la lógica real del sistema de puntos. | F17: x | I17: Cumple.

Sheet No-funcionales chatbotInformati
B2: LISTADO DE REQUERIMIENTOS DE COMPRALO | K2: ESTADISTICAS
K3: Requirimientos | L3: =COUNT(B12:D69) -> 15
B4: SI | C4: Marque con una equis (X) si el sistema cumple con la función descrita | K4: Cumplidos | L4: =COUNTIF(F12:F69,"X") -> 15
B5: NO | C5: Marque con una equis (X) si el sistema no cumple con la función descrita | K5: Porcentaje | L5: =PERCENTOF(L4,L3) -> #NAME?
B6: ADI | C6: Marque con una equis (X) si el sistema debe adicionar la función descrita
B7: Observaciones: | D7: Espacio para complementar respuestas
F10: Nivel de cumplimiento | I10: Observaciones
B11: REQUERIMIENTOS NO FUNCIONALES PRENSA | F11: SI | G11: NO | H11: ADI
B13: 1 | C13: El tiempo de apertura del chatbot (desde el clic en el botón hasta que se vea el panel y el menú inicial) no debe exceder aproximadamente 1 segundo en condiciones normales. | F13: x
B14: 2 | C14: El chatbot debe cargar de forma perezosa (lazy) sus recursos de UI y texto para no afectar significativamente el tiempo de carga inicial de la página principal. | F14: x
B15: 3 | C15: El diseño del panel del chatbot debe ser totalmente responsivo, adaptándose a pantallas móviles, tablets y escritorio sin solaparse con el header, el carrito o otros elementos críticos. | F15: x
B16: 4 | C16: Los textos de bienvenida, menú y respuestas deben poder gestionarse desde un fichero de traducciones o configuración para permitir su actualización sin cambios de código. | F16: x
B17: 5 | C17: El contenido que el chatbot muestra para cada opción (términos, protección de datos, descuentos, puntos, garantías) debe estar alineado con las secciones legales y de ayuda existentes, evitando contradicciones. | F17: x
B18: 6 | C18: El chatbot debe manejar entradas inválidas (por ejemplo, números fuera de rango o texto no reconocido) mostrando un mensaje de error claro y manteniéndose usable sin recargar la página. | F18: x
B19: 7 | C19: El componente debe ser accesible mediante teclado (foco en el botón de abrir/cerrar, navegación dentro del panel, envío del mensaje) y compatible con lectores de pantalla. | F19: x
B20: 8 | C20: Los colores, tamaños de fuente y contraste del panel y los textos del chatbot deben cumplir al menos el nivel AA de WCAG 2.1. | F20: x
B21: 9 | C21: El chatbot no debe registrar ni exponer datos personales sensibles en sus mensajes; solo debe mostrar información estática o agregada sobre políticas y sistemas (descuentos, puntos, garantías). | F21: x
B22: 10 | C22: El uso del chatbot debe respetar las preferencias de cookies y privacidad del usuario: no debe activar servicios analíticos o de marketing adicionales si el usuario no ha dado su consentimiento. | F22: x
B23: 11 | C23: El widget debe recordar su estado de abierto/cerrado durante la sesión actual sin generar errores si el usuario navega entre páginas compatibles. | F23: x
B24: 12 | C24: Los errores internos del chatbot (por ejemplo, fallos al cargar textos configurados) deben registrarse en logs técnicos, pero mostrarse al usuario con un mensaje genérico que no revele detalles internos del sistema. | F24: x
... B27: 15 | C27: El chatbot debe poder desactivarse completamente por configuración de instancia sin dejar elementos rotos en la interfaz (botones huérfanos o errores de JavaScript). | F27: x

Sheet Funcionales LoginRegister
B2: LISTADO DE REQUERIMIENTOS DE COMPRALO | K2: ESTADISTICAS
K3: Requirimientos | L3: =COUNT(B12:D99) -> 18
B4: SI | C4: Marque con una equis (X) si el sistema cumple con la función descrita | K4: Cumplidos | L4: =COUNTIF(F12:F99,"X") -> 18
B5: NO | C5: Marque con una equis (X) si el sistema no cumple con la función descrita | K5: Porcentaje | L5: =PERCENTOF(L4,L3) -> #NAME?
B6: ADI | C6: Marque con una equis (X) si el sistema debe adicionar la función descrita
B7: Observaciones: | D7: Espacio para complementar respuestas
F10: Nivel de cumplimiento | I10: Observaciones
B11: REQUERIMIENTOS FUNCIONALES LOGIN/REGISTER | F11: SI | G11: NO | H11: ADI
B13: 1 | C13: La página de login debe permitir al usuario autenticarse introduciendo su correo electrónico y contraseña en un formulario centrado en la pantalla. | F13: x | I13: Cumple.
B14: 2 | C14: La página de login debe incluir un enlace “¿Olvidaste tu contraseña?” que lleve al flujo de recuperación de contraseña. | F14: x | I14: Cumple.
B15: 3 | C15: La página de login debe incluir un icono o botón para mostrar/ocultar la contraseña introducida. | F15: x | I15: Cumple.
B16: 4 | C16: La página de login debe mostrar un enlace “¿No tienes una cuenta? Regístrate” que navegue a la página de registro. | F16: x | I16: Cumple.
B17: 5 | C17: Al enviar el formulario de login con credenciales válidas, el sistema debe iniciar sesión al usuario y redirigirlo a la experiencia de tienda configurada (por ejemplo, home o página anterior protegida). | F17: x | I17: Cumple.
B18: 6 | C18: La página de registro debe permitir crear una cuenta introduciendo como mínimo: identificación (cédula), nombre, apellido, email, contraseña y teléfono. | F18: x | I18: Cumple.
B19: 7 | C19: La página de registro debe permitir capturar un campo opcional de fecha de nacimiento mediante un selector de fecha. | F19: x | I19: Cumple.
B20: 8 | C20: La página de registro debe permitir seleccionar el género del usuario mediante un control de tipo lista desplegable. | F20: x | I20: Cumple.
B21: 9 | C21: La página de registro debe mostrar un enlace “¿Ya tienes una cuenta? Inicia sesión” que navegue a la página de login. | F21: x | I21: Cumple.
B22: 10 | C22: Tanto en login como en registro, se debe mostrar un texto que indique que al continuar el usuario acepta los Términos de Servicio y la Política de Privacidad, con enlaces que permitan abrir dichas secciones. | F22: x | I22: Cumple.
B23: 11 | C23: La página debe mostrar un carrusel o listado de productos recomendados o relacionados (“También te puede gustar”) basados en la misma categoría o reglas de negocio. | F23: x | I23: No cumple.
B24: 12 | C24: La página debe integrarse con la navegación global (breadcrumbs, header, footer), indicando la ruta de navegación (por ejemplo “Inicio > Productos > Smartphones > Galaxy A55 5G”). | F24: x | I24: Requerimiento no funcional.
... B30: 18 | C30: Si el código es incorrecto, está incompleto o ha expirado, la página de verificación debe mostrar un mensaje de error claro e indicar al usuario que revise el correo o se registre de nuevo. | F30: x | I30: Cumple.

Sheet No-funcionales LoginRegister
B2: LISTADO DE REQUERIMIENTOS DE COMPRALO | K2: ESTADISTICAS
K3: Requirimientos | L3: =COUNT(B12:D91) -> 33
B4: SI | C4: Marque con una equis (X) si el sistema cumple con la función descrita | K4: Cumplidos | L4: =COUNTIF(F12:F91,"X") -> 33
B5: NO | C5: Marque con una equis (X) si el sistema no cumple con la función descrita | K5: Porcentaje | L5: =PERCENTOF(L4,L3) -> #NAME?
B6: ADI | C6: Marque con una equis (X) si el sistema debe adicionar la función descrita
B7: Observaciones: | D7: Espacio para complementar respuestas
F10: Nivel de cumplimiento | I10: Observaciones
B11: REQUERIMIENTOS NO FUNCIONALES LOGIN/REGISTER | F11: SI | G11: NO | H11: ADI
B13: 1 | C13: El formulario de login debe cargarse visualmente en menos de ~2 segundos en conexiones de banda ancha típicas. | F13: x
B14: 2 | C14: El formulario de registro debe cargarse en un tiempo similar al de login, evitando retrasos perceptibles al navegar entre ambas pantallas. | F14: x
B15: 3 | C15: Las llamadas al backend para autenticar o registrar usuarios deben mantener un tiempo de respuesta aceptable (p.ej. P95 < 500 ms bajo carga normal). | F15: x
B16: 4 | C16: Los campos de email en login y registro deben validar el formato básico de correo antes de enviar la solicitud al servidor, mostrando mensajes de error claros en caso de formato inválido. | F16: x
B17: 5 | C17: Los campos obligatorios en el formulario de registro (identificación, nombre, apellido, email, contraseña, teléfono) deben indicar visualmente su obligatoriedad y bloquear el envío si están vacíos. | F17: x
B18: 6 | C18: Los mensajes de error de validación deben aparecer cerca de los campos correspondientes y ser comprensibles para usuarios no técnicos. | F18: x
B19: 7 | C19: La contraseña no debe mostrarse en texto plano por defecto; el botón de mostrar/ocultar debe alternar el tipo de campo sin recargar la página. | F19: x
B20: 8 | C20: El contenido del campo de contraseña no debe copiarse automáticamente al portapapeles ni mostrarse en atributos inseguros del HTML. | F20: x
B21: 9 | C21: La longitud mínima y reglas básicas de complejidad de la contraseña deben validarse en el cliente y en el servidor, devolviendo errores específicos. | F21: x
B22: 10 | C22: La funcionalidad “¿Olvidaste tu contraseña?” debe manejarse mediante un flujo que no revele si un email existe o no en el sistema (por ejemplo, siempre mostrando un mensaje genérico de envío si el formato es válido). | F22: x
B23: 11 | C23: Las solicitudes de recuperación de contraseña deben estar protegidas frente a abuso mediante limitaciones razonables de frecuencia por dirección IP y por correo. | F23: x
B24: 12 | C24: Los enlaces enviados para restablecer contraseña deben tener una caducidad definida y no ser reutilizables una vez usados. | F24: x
... B45: 33 | C45: Ante errores de verificación, los mensajes devueltos al usuario deben ser seguros y genéricos (“código inválido o expirado”) sin revelar detalles internos de validación o del almacenamiento de OTP | F45: x

Sheet Funcionales Producto
B2: LISTADO DE REQUERIMIENTOS DE COMPRALO | K2: ESTADISTICAS
K3: Requirimientos | L3: =COUNT(B12:D100) -> 12
B4: SI | C4: Marque con una equis (X) si el sistema cumple con la función descrita | K4: Cumplidos | L4: =COUNTIF(F12:F100,"X") -> 12
B5: NO | C5: Marque con una equis (X) si el sistema no cumple con la función descrita | K5: Porcentaje | L5: =PERCENTOF(L4,L3) -> #NAME?
B6: ADI | C6: Marque con una equis (X) si el sistema debe adicionar la función descrita
B7: Observaciones: | D7: Espacio para complementar respuestas
F10: Nivel de cumplimiento | I10: Observaciones
B11: REQUERIMIENTOS FUNCIONALES PRODUCT | F11: SI | G11: NO | H11: ADI
B13: 1 | C13: La página de producto debe mostrar una galería principal de imágenes del producto, permitiendo cambiar entre miniaturas y ver cada imagen en mayor tamaño. | F13: x | I13: Cumple. NOTA: Las flechas para cambiar de imgen casi no se ven
B14: 2 | C14: La página debe mostrar claramente el nombre del producto, la marca, la categoría y el proveedor asociado. | F14: x | I14: Cumple.
B15: 3 | C15: La página debe mostrar el rango de precios del producto cuando existan múltiples variantes (por ejemplo “Desde $650.000 – $750.000”) y el precio exacto de la variante seleccionada. | F15: x | I15: Cumple.
B16: 4 | C16: La página debe indicar el estado de disponibilidad del producto (por ejemplo “En stock”, “Agotado”) y la cantidad de unidades disponibles cuando aplique. | F16: x | G16: x | I16: No cumple. El estado no cambia
B17: 5 | C17: La página debe permitir seleccionar atributos de variante (por ejemplo color, almacenamiento, RAM u otros) antes de añadir el producto al carrito. | F17: x | I17: Cumple.
B18: 6 | C18: El botón de “Añadir al carrito” debe estar deshabilitado mientras no se hayan seleccionado todas las opciones obligatorias de la variante. | F18: x | G18: x | I18: No cumple. Se pueden dejar atributos sin seleccionar y al momento de agregar al carrito se le añade uno predeterminado
B19: 7 | C19: La página debe mostrar, cuando exista, la información de descuento aplicada a la variante seleccionada (precio original tachado, porcentaje o monto de descuento y precio final). | F19: x | I19: Cumple.
B20: 8 | C20: La página debe permitir marcar o desmarcar el producto como favorito mediante un control visible (por ejemplo un ícono de corazón) para usuarios autenticados. | F20: x | I20: Cumple.
B21: 9 | C21: La página debe mostrar una sección de información adicional del producto (descripción, especificaciones técnicas, ficha de stock, estado, etc.). | F21: x | I21: Cumple.
B22: 10 | C22: La página debe mostrar una sección de comentarios o reseñas de clientes, con la posibilidad de que usuarios elegibles puedan añadir una reseña desde su historial de órdenes. | F22: x | I22: Cumple. NOTA: Revisar redaccion del requerimiento
B23: 11 | C23: La página debe mostrar un carrusel o listado de productos recomendados o relacionados (“También te puede gustar”) basados en la misma categoría o reglas de negocio. | F23: x | I23: Cumple.
B24: 12 | C24: La página debe integrarse con la navegación global (breadcrumbs, header, footer), indicando la ruta de navegación (por ejemplo “Inicio > Productos > Smartphones > Galaxy A55 5G”). | F24: x | G24: x | I24: No cumple. La ruta de navegacion no existe. NOTA: Elimine terminos que el usuario no entienda en los requerimientos

Sheet No-funcionales Producto
B2: LISTADO DE REQUERIMIENTOS DE COMPRALO | K2: ESTADISTICAS
K3: Requirimientos | L3: =COUNT(B12:D100) -> 36
B4: SI | C4: Marque con una equis (X) si el sistema cumple con la función descrita | K4: Cumplidos | L4: =COUNTIF(F12:F100,"X") -> 36
B5: NO | C5: Marque con una equis (X) si el sistema no cumple con la función descrita | K5: Porcentaje | L5: =PERCENTOF(L4,L3) -> #NAME?
B6: ADI | C6: Marque con una equis (X) si el sistema debe adicionar la función descrita
B7: Observaciones: | D7: Espacio para complementar respuestas
F10: Nivel de cumplimiento | I10: Observaciones
B11: REQUERIMIENTOS NO FUNCIONALES PRODUCT | F11: SI | G11: NO | H11: ADI
B13: 1 | C13: La página de producto debe cargar el contenido principal (imagen destacada, nombre y precio) en menos de ~3 segundos en conexiones de banda ancha típicas. | F13: x
B14: 2 | C14: Las imágenes de la galería deben estar optimizadas (compresión, tamaños adaptativos, uso de formatos modernos cuando sea posible) para minimizar el peso total de la página. | F14: x
B15: 3 | C15: La galería debe usar lazy loading para imágenes que no sean visibles inicialmente (por ejemplo, miniaturas lejanas o imágenes del carrusel de recomendados). | F15: x
B16: 4 | C16: El diseño de la sección superior (galería + información básica) debe ser completamente responsivo, apilando los elementos en una sola columna en móvil y presentándolos en dos columnas en pantallas grandes. | F16: x
B17: 5 | C17: Los controles de navegación de la galería (flechas, miniaturas) deben ser fácilmente accesibles por teclado y anunciables correctamente por lectores de pantalla. | F17: x
B18: 6 | C18: El cambio entre imágenes de la galería debe ser fluido y no provocar saltos de layout o reflujo excesivo del contenido. | F18: x
B19: 7 | C19: La consulta que obtiene la información detallada del producto (datos generales, variantes, stock) debe estar indexada por identificador de producto/slug para garantizar bajas latencias. | F19: x
B20: 8 | C20: La información de stock disponible debe recuperarse de forma consistente con la BD y/o caché, evitando mostrar valores obsoletos tras operaciones de carrito/orden. | F20: x
B21: 9 | C21: El cálculo del rango de precios (mínimo y máximo) para productos con múltiples variantes debe realizarse con consultas agregadas optimizadas y/o precalculadas. | F21: x
B22: 10 | C22: Los bloques de texto principales (nombre, descripción, especificaciones) deben ser legibles, con tamaños de fuente y contrastes que cumplan al menos nivel AA de WCAG 2.1. | F22: x
B23: 11 | C23: La jerarquía de encabezados (h1, h2, etc.) en la página de producto debe ser coherente para facilitar la navegación con tecnologías de asistencia. | F23: x
B24: 12 | C24: Todas las etiquetas de formularios y controles (selección de color, almacenamiento, RAM, etc.) deben contar con label o atributos aria apropiados. | F24: x
... B48: 36 | C48: Los metadatos (por ejemplo etiquetas Open Graph, esquema de producto) deben poder configurarse para mejorar la compartición en redes sociales y motores de búsqueda. | F48: x

Sheet input_req
A2: Requerimientos separados por saltos de linea: | B2: El sistema debe mostrar la sección “Analytics Avanzados” dentro del dashboard de admin. La sección debe incluir un botón “Actualizar” para refrescar los datos mostrados. La sección debe tener pestañas para cambiar de vista entre: Conversión, Tráfico, Clientes y Productos. En la vista Conversión, el sistema debe mostrar una tarjeta con la Tasa de conversión (porcentaje). En la vista Conversión, el sistema debe mostrar una tarjeta con el Valor promedio de orden. En la vista Conversión, el sistema debe mostrar una tarjeta con el Total de órdenes. En la vista Conversión, el sistema debe mostrar una tarjeta con Ingresos totales. En la vista Conversión, el sistema debe mostrar un bloque de Performance por categoría con: Gráfico de participación por categoría (tipo dona) Gráfico de ventas por categoría (barras) Un ranking/lista por categoría con su valor (ventas) En la vista Tráfico, el sistema debe mostrar un gráfico de Tráfico por horas (órdenes por hora del día, “últimos 30 días”). En la vista Tráfico, el sistema debe mostrar indicadores de Pico y Valle (hora y cantidad). En la vista Tráfico, el sistema debe mostrar el Promedio de órdenes/hora. En la vista Tráfico, el sistema debe mostrar un módulo de Ventas por región con listado de regiones y valores (órdenes y monto). En la vista Clientes, el sistema debe mostrar el bloque Demografía de clientes con distribución por rangos de edad. En la vista Clientes, el sistema debe mostrar un módulo de Ventas por región (mismo tipo de bloque visible). En la vista Productos, el sistema debe mostrar un módulo “Métricas de productos” que incluya: Productos activos Productos inactivos Sin stock Precio promedio Rating promedio En la vista Productos, el sistema debe mostrar el bloque de Performance por categoría (participación/ventas) y el ranking por categoría. Los valores monetarios mostrados en tarjetas y gráficos deben presentarse con símbolo de moneda y separadores de miles (como se ve en la UI).
A3: Nombre de la hoja: | B3: Funcionales analiticas
E61: Requerimientos funcionales (botón de ayuda del admin)
E62: El dashboard de admin debe mostrar un botón de ayuda (ícono tipo “?”) en la barra superior (AdminHeader).
E63: El botón de ayuda debe tener un nombre accesible (por ejemplo aria-label="Ayuda y recorridos").
E64: Al hacer clic en el botón de ayuda, el sistema debe iniciar un recorrido guiado (tour) del panel usando driver.js.
E65: Si el usuario está en una sección específica del admin, el botón de ayuda debe iniciar el tour de esa sección (tour contextual).
E66: Si el usuario está en el dashboard principal u otra ruta sin tour contextual, el botón de ayuda debe iniciar el tour general del admin.
E67: El tour general debe incluir pasos que apunten como mínimo a:
E68: La navegación lateral (data-tour-id="admin-sidebar"),
E69: La barra superior (data-tour-id="admin-header"),
E70: Elementos principales del dashboard (KPIs y gráficas) cuando existan (data-tour-id="admin-dashboard-kpis", data-tour-id="admin-dashboard-charts").
E71: El tour contextual debe existir (según ruta) al menos para estas secciones, porque están definidas en el código:
E72: Órdenes (/admin/orders)
... E94: El botón/tour debe funcionar únicamente dentro del área protegida de admin (está envuelto por AdminGuard), evitando exposición en rutas públicas.

Sheet Funcionales Carrito
B2: LISTADO DE REQUERIMIENTOS DE COMPRALO | K2: ESTADISTICAS
K3: Requirimientos | L3: =COUNT(B12:D96) -> 10
B4: SI | C4: =COUNTIF('No-funcionales generales'!F12:F46,"x")+COUNTIF('Funcionales generales'!F12,"x")+COUNTIF(#REF!,"x")+COUNTIF(#REF!,"x")+COUNTIF('Funcionales Homepage'!F12:F20,"x")+COUNTIF('No-funcionales Homepage'!F12:F16,"x")+COUNTIF('Funcionales Productos'!F13:F21,"x")+COUNTIF('No-funcionales Productos'!F13:F17,"x")+COUNTIF('Funcionales Producto'!F13:F22,"x")+COUNTIF('No-funcionales Producto'!F13:F17,"x")+COUNTIF('Funcionales Carrito'!F13:F21,"x")+_xleta.COUNTIF -> #REF! | K4: Cumplidos | L4: =COUNTIF(F12:F96,"X") -> 10
B5: NO | C5: Marque con una equis (X) si el sistema no cumple con la función descrita | K5: Porcentaje | L5: =PERCENTOF(L4,L3) -> #NAME?
B6: ADI | C6: Marque con una equis (X) si el sistema debe adicionar la función descrita
B7: Observaciones: | D7: Espacio para complementar respuestas
F10: Nivel de cumplimiento | I10: Observaciones
B11: REQUERIMIENTOS FUNCIONALES CARRITO | F11: SI | G11: NO | H11: ADI
B13: 1 | C13: El sistema debe crear u obtener automáticamente un carrito para el usuario (anónimo o autenticado) al acceder a la tienda. | F13: X | I13: Cumple.
B14: 2 | C14: El sistema debe mostrar el listado de productos del carrito con nombre, imagen, cantidad, precio, subtotal y, cuando aplique, información de descuentos (precio original tachado, precio con descuento, porcentaje). | F14: X | I14: Cumple.
B15: 3 | C15: El sistema debe permitir incrementar y disminuir la cantidad de cada producto tanto desde la página de carrito como desde el mini‑carrito (hover), respetando que la cantidad mínima es 1 y sin superar el stock disponible. | F15: X | I15: Cumple. NOTA: Elimine terminos que el usuario no entienda en los requerimientos
B16: 4 | C16: El sistema debe permitir eliminar productos del carrito desde la página de carrito y desde el mini‑carrito. | F16: X | I16: No cumple, no se pueden eliminar productos desde el mini-carrito
B17: 5 | C17: El sistema debe migrar/sincronizar el carrito anónimo con la cuenta del usuario cuando este inicia sesión, manteniendo los productos que tenía agregados (comportamiento descrito en el banner “Tu carrito se sincroniza automáticamente.”). | F17: X | I17: Cumple.
B18: 6 | C18: El sistema debe validar un límite máximo de valor total del carrito (CART_LIMITS.MAX_TOTAL) y bloquear operaciones de agregado o aumento de cantidad que excedan ese límite, mostrando un mensaje de error claro. (Por Ejm $20.000.000) | F18: X | I18: Cumple. NOTA: Elimine terminos que el usuario no entienda en los requerimientos
B19: 7 | C19: El sistema debe permitir aplicar un código promocional sobre el carrito actual, validándolo en el backend (validateDiscountForCart) y, si es válido, guardar el código en sessionStorage y compartirlo con otras vistas (mini‑carrito) mediante el evento discountCodeChanged. | F19: X | I19: Requerimiento no funcional
B20: 8 | C20: El sistema debe permitir remover un código promocional aplicado, limpiando el estado del descuento, eliminando el código de sessionStorage y notificando al usuario con un mensaje de éxito. | F20: X | I20: No cumple, no se pudo comprobar, el sistema no permite agregar cupones
B21: 9 | C21: El sistema debe calcular y mostrar el resumen del pedido en el carrito, incluyendo al menos: subtotal original, descuentos (automáticos, por código, por canje de puntos), envío, total a pagar y, cuando aplique, información de puntos canjeados o ganados. | F21: X | I21: Cumple
B22: 10 | C22: El sistema debe mostrar productos recomendados en la sección “También te puede gustar”, obteniéndolos desde el backend a partir de las categorías de los productos del carrito (incluyendo subcategorías) y excluyendo los productos ya presentes en el carrito. | F22: X | I22: No cumple, la seccion se encuentra vacia. NOTA: Elimine terminos que el usuario no entienda en los requerimientos

Sheet No-funcionales Carrito
B2: LISTADO DE REQUERIMIENTOS DE COMPRALO | K2: ESTADISTICAS
K3: Requirimientos | L3: =COUNT(B12:D100) -> 31
B4: SI | C4: Marque con una equis (X) si el sistema cumple con la función descrita | K4: Cumplidos | L4: =COUNTIF(F12:F100,"X") -> 31
B5: NO | C5: Marque con una equis (X) si el sistema no cumple con la función descrita | K5: Porcentaje | L5: =PERCENTOF(L4,L3) -> #NAME?
B6: ADI | C6: Marque con una equis (X) si el sistema debe adicionar la función descrita
B7: Observaciones: | D7: Espacio para complementar respuestas
F10: Nivel de cumplimiento | I10: Observaciones
B11: REQUERIMIENTOS NO FUNCIONALES CARRITO | F11: SI | G11: NO | H11: ADI
B13: 1 | C13: El carrito debe mantener una sesión estable para usuarios anónimos, reutilizando un session_id generado una sola vez por dispositivo/sesión de navegador para evitar recrear el carrito en cada render. | F13: X
B14: 2 | C14: Las consultas al backend para crear/obtener el carrito deben tener una política de caché adecuada (staleTime de varios minutos) y no re‑ejecutarse en cada foco de ventana (refetchOnWindowFocus: false) para mejorar el rendimiento. | F14: X
B15: 3 | C15: Las consultas para productos y totales del carrito deben tratar los errores 400 Bad Request como carrito vacío y no reintentar indefinidamente, evitando saturar el backend y bloqueos en la UI. | F15: X
B16: 4 | C16: Cuando el total del carrito exceda el límite configurado, el sistema debe mostrar un mensaje de error contextual y descriptivo (por ejemplo, indicando el total actual y el máximo permitido) mediante notificaciones (toast.error). | F16: X
B17: 5 | C17: La migración de carrito anónimo a usuario autenticado debe manejar errores de forma robusta, registrando errores en consola, mostrando mensajes de fallo al usuario y permitiendo reintentos sin dejar el carrito en un estado inconsistente. | F17: X
B18: 6 | C18: El mini‑carrito debe ser ligero y rápido, cargando solo hasta un número acotado de ítems (por ejemplo, los primeros 6) y usando un área scrollable para listas largas, evitando que el hover bloquee la vista. | F18: X
B19: 7 | C19: El mini‑carrito debe controlar las acciones de cantidad para no enviar actualizaciones mientras un ítem tiene un ID temporal (optimistic update) o hay una actualización en curso, previniendo estados corruptos y doble clic. | F19: X
B20: 8 | C20: El cálculo de precios con descuentos en el mini‑carrito debe reutilizar utilidades comunes (getApplicableDiscount, calculateDiscountedPrice, calculateDiscountPercentage) para garantizar consistencia con la página de carrito y otras vistas. | F20: X
B21: 9 | C21: Todas las cantidades y precios del carrito deben mostrarse con formateo localizado (por ejemplo, toLocaleString('es-CO') o formatPrice) para mejorar la legibilidad y reducir errores de interpretación. | F21: X
B22: 10 | C22: Al aplicar un código de descuento, el sistema debe distinguir claramente entre errores de código inexistente (404), código no aplicable (400) y fallos generales del servidor, mostrando mensajes específicos para cada caso. | F22: X
B23: 11 | C23: El mecanismo de sincronización del código de descuento (sessionStorage + eventos storage y discountCodeChanged) debe ser tolerante a fallos: si la validación remota falla, el descuento debe descartarse sin romper el mini‑carrito. | F23: X
B24: 12 | C24: Las consultas de canjes y descuentos disponibles para el usuario deben estar habilitadas solo cuando exista id_usuario, evitando errores 401 innecesarios en usuarios anónimos. | F24: X
... B43: 31 | C43: El sistema debe crear u obtener automáticamente un carrito para el usuario (anónimo o autenticado) al acceder a la tienda, usando un session_id para invitados y id_usuario cuando hay sesión iniciada. | F43: x

Sheet Funcionales Checkout
B2: LISTADO DE REQUERIMIENTOS DE COMPRALO | K2: ESTADISTICAS
K3: Requirimientos | L3: =COUNT(B12:D92) -> 20
B4: SI | C4: Marque con una equis (X) si el sistema cumple con la función descrita | K4: Cumplidos | L4: =COUNTIF(F12:F92,"X") -> 20
B5: NO | C5: Marque con una equis (X) si el sistema no cumple con la función descrita | K5: Porcentaje | L5: =PERCENTOF(L4,L3) -> #NAME?
B6: ADI | C6: Marque con una equis (X) si el sistema debe adicionar la función descrita
B7: Observaciones: | D7: Espacio para complementar respuestas
F10: Nivel de cumplimiento | I10: Observaciones
B11: REQUERIMIENTOS FUNCIONALES CHECKOUT | F11: SI | G11: NO | H11: ADI
B13: 1 | C13: El sistema debe permitir al usuario seleccionar o crear una dirección de envío en el paso de información del checkout (lista desplegable de direcciones guardadas + opción “Nueva”). | F13: x | I13: Cumple.
B14: 2 | C14: El formulario de nueva dirección debe permitir capturar al menos: nombre, apellidos, dirección principal, complemento, país, departamento, ciudad/localidad, código postal, barrio y teléfono/celular. | F14: x | I14: No cumple. El formulario no contiene nombre, apellidos, pais y telefono
B15: 3 | C15: El sistema debe validar que todos los campos obligatorios de dirección estén completos y mostrar mensajes de error claros cuando falte información o el formato sea inválido. | F15: x | I15: No cumple. El sistema no valida que los campos tengan el formato requerido
B16: 4 | C16: El sistema debe permitir elegir un método de entrega (por ejemplo “Enviar pedido” o “Recoger pedido”) o mostrar solo las opciones configuradas para la instancia. | F16: x | I16: No cumple. La seccion esta desabilitada y no se puede seleccionar ninguna de las opciones
B17: 5 | C17: El sistema debe construir y mostrar un resumen del pedido en el checkout, con: producto(s), cantidad, variantes/opciones, subtotal, costo de envío y total general. | F17: x | I17: No cumple. En el resumen del pedido del checkout no se muestra la cantidad comprada de cada producto
B18: 6 | C18: El sistema debe permitir al usuario avanzar desde el paso de información/dirección al paso de pago solo si la dirección y el método de entrega son válidos. | F18: x | I18: Cumple.
B19: 7 | C19: En el paso de pago, el sistema debe permitir seleccionar un método de pago principal (por ejemplo “Pago en línea con Wompi”) y mostrar los medios aceptados (PSE, VISA, AMEX, etc.). | F19: x | I19: Cumple.
B20: 8 | C20: El sistema debe permitir indicar si la dirección de facturación coincide con la de envío o, en caso contrario, capturar una nueva dirección de facturación. | F20: x | I20: No cumple. El sistema no permite agregar una nueva direccion de facturación
B21: 9 | C21: Al hacer clic en “Continuar con el pago”, el sistema debe crear o actualizar una orden en estado pendiente en la base de datos, asociada al usuario y al carrito, antes de redirigir al proveedor de pago. | F21: x | I21: Requerimiento no funcional
B22: 10 | C22: El sistema debe redirigir al usuario a la plataforma de pagos Wompi (u otra pasarela) con los datos necesarios: monto total, moneda, referencia única de la orden y URL de retorno / webhook configurados. | F22: x | I22: Requerimiento no funcional
B23: 11 | C23: Tras finalizar el flujo en Wompi (éxito, fallo o cancelación), el sistema debe procesar la respuesta de la pasarela (retorno por URL y/o webhook), validar la firma y actualizar el estado del pago y de la orden. | F23: x | I23: Requerimiento no funcional
B24: 12 | C24: Cuando el pago sea exitoso, el sistema debe mostrar una página de resultado de pago con mensaje de éxito, monto pagado, referencia de transacción, fecha/hora y un enlace para ver el detalle de la orden. | F24: x | I24: Cumple.
... B27: 15 | C27: El sistema debe permitir al usuario acceder desde la página de éxito al detalle de la orden en su perfil (historial de órdenes) para consultar en cualquier momento los datos completos. | F27: x | I27: No cumple. No se puede acceder directamente a las ordenes en el perfil
B28: 16 | C28: Al confirmarse el pago, el sistema debe calcular y registrar los puntos ganados según la configuración de fidelización, asociándolos al usuario y a la orden. | F28: x
B29: 17 | C29: Al confirmarse el pago, el sistema debe enviar un correo de confirmación de orden al cliente con el resumen completo: número de orden, fecha, estado, productos, totales, puntos ganados, dirección de envío y datos de contacto de la tienda. | F29: x
B30: 18 | C30: El sistema debe poder enviar, además del correo al cliente, un correo interno de notificación opcional al administrador o a una casilla de operaciones con la información clave de la nueva orden. | F30: x
B31: 19 | C31: El sistema debe permitir reintentar el pago de una orden pendiente desde el perfil del usuario (por ejemplo, botón “Pagar ahora” en la orden) reutilizando la referencia o generando una nueva, según la integración con la pasarela. | F31: x
B32: 20 | C32: El sistema debe registrar en la base de datos un historial de cambios de estado de la orden (pendiente, pagada, procesada, enviada, etc.) asociado a la transacción de pago y a cualquier acción posterior. | F32: x

Sheet No-funcionales Checkout 
B2: LISTADO DE REQUERIMIENTOS DE COMPRALO | K2: ESTADISTICAS
K3: Requirimientos | L3: =COUNT(B12:D100) -> 30
B4: SI | C4: Marque con una equis (X) si el sistema cumple con la función descrita | K4: Cumplidos | L4: =COUNTIF(F12:F100,"X") -> 30
B5: NO | C5: Marque con una equis (X) si el sistema no cumple con la función descrita | K5: Porcentaje | L5: =PERCENTOF(L4,L3) -> #NAME?
B6: ADI | C6: Marque con una equis (X) si el sistema debe adicionar la función descrita
B7: Observaciones: | D7: Espacio para complementar respuestas
F10: Nivel de cumplimiento | I10: Observaciones
B11: REQUERIMIENTOS NO FUNCIONALES CHECKOUT | F11: SI | G11: NO | H11: ADI
B13: 1 | C13: La carga del paso de información/dirección del checkout debe completarse en menos de ~3 segundos en condiciones normales de red. | F13: X
B14: 2 | C14: La validación del formulario de dirección debe ejecutarse en el cliente de manera inmediata (sin recargar la página), y posteriormente en el servidor para garantizar integridad de datos. | F14: x
B15: 3 | C15: El guardado de nuevas direcciones debe realizarse en una única transacción en la base de datos, garantizando que no se creen registros parciales o inconsistentes. | F15: x
B16: 4 | C16: El cálculo del resumen de pedido (subtotal, envío, total) debe utilizar funciones centralizadas de negocio para evitar diferencias entre frontend, backend y correos. | F16: x
B17: 5 | C17: El resumen del pedido debe actualizarse de forma reactiva si el usuario cambia dirección, método de envío o descuento aplicado, manteniendo tiempos de actualización percibidos inferiores a 1 segundo. | F17: x
B18: 6 | C18: Los montos mostrados en el resumen deben usar un formato consistente con la configuración regional de la instancia (moneda, separadores, decimales). | F18: x
B19: 7 | C19: Las llamadas al backend para avanzar de información a pago deben ser idempotentes en la medida de lo posible, evitando la creación de órdenes duplicadas por reenvío de formularios o errores de red. | F19: x
B20: 8 | C20: El cambio de paso (Información → Pago → Resultado) debe mostrar indicadores de carga y no dejar la interfaz en un estado ambiguo donde el usuario pueda repetir acciones críticas sin feedback. | F20: x
B21: 9 | C21: Cualquier error del servidor al crear/actualizar la orden debe manejarse mostrando mensajes claros y ofreciendo opciones de reintentar o volver al carrito sin perder datos relevantes. | F21: x
B22: 10 | C22: Los datos enviados a la pasarela de pago (monto, referencia, callback URLs) deben estar firmados o protegidos según los lineamientos de la pasarela para evitar manipulación maliciosa. | F22: x
B23: 11 | C23: El sistema debe verificar las firmas y la integridad de la respuesta de la pasarela (retorno y webhook) antes de actualizar el estado de la orden o marcar un pago como exitoso. | F23: x
B24: 12 | C24: Los secretos de integración con la pasarela (keys, tokens) deben almacenarse en variables de entorno seguras y nunca en código fuente plano ni en el frontend. | F24: x
... B42: 30 | C42: El flujo completo desde selección de dirección hasta visualización del resumen de orden y envío de correos debe soportar picos razonables de tráfico sin degradar la experiencia de usuario ni perder transacciones. | F42: x

Sheet Funcionales Favoritos
B2: LISTADO DE REQUERIMIENTOS DE COMPRALO | K2: ESTADISTICAS
K3: Requirimientos | L3: =COUNT(B12:D99) -> 8
B4: SI | C4: Marque con una equis (X) si el sistema cumple con la función descrita | K4: Cumplidos | L4: =COUNTIF(F12:F99,"X") -> 8
B5: NO | C5: Marque con una equis (X) si el sistema no cumple con la función descrita | K5: Porcentaje | L5: =PERCENTOF(L4,L3) -> #NAME?
B6: ADI | C6: Marque con una equis (X) si el sistema debe adicionar la función descrita
B7: Observaciones: | D7: Espacio para complementar respuestas
B9: REQUERIMIENTOS FUNCIONALES DE LA SECRETARIA GESTORA (FUNCIONARIO)
F10: Nivel de cumplimiento | I10: Observaciones
B11: REQUERIMIENTOS FUNCIONALES FAVORITOS | F11: SI | G11: NO | H11: ADI
B13: 1 | C13: La sección de favoritos debe mostrar un listado de todos los productos que el usuario autenticado ha marcado como favoritos. | F13: x | I13: Cumple.
B14: 2 | C14: Cada tarjeta de producto favorito debe mostrar al menos: imagen principal, nombre del producto y precio actual. | F14: x | I14: Cumple.
B15: 3 | C15: La sección de favoritos debe permitir al usuario quitar un producto de favoritos mediante un botón o icono claramente identificable (por ejemplo, un corazón relleno/vacío). | F15: x | I15: Cumple.
B16: 4 | C16: Al hacer clic en la tarjeta de un producto favorito (imagen, nombre o botón “Ver detalles”), el sistema debe navegar a la página de detalle de ese producto. | F16: x | I16: Cumple.
B17: 5 | C17: La sección de favoritos debe mostrar el número total de productos guardados en favoritos (por ejemplo, “1 producto guardado”, “5 productos guardados”). | F17: x | I17: Cumple.
B18: 6 | C18: Si el usuario elimina un producto de favoritos, la tarjeta correspondiente debe desaparecer de la lista sin necesidad de recargar manualmente la página. | F18: x | I18: Cumple.
B19: 7 | C19: En caso de que el usuario no tenga productos guardados, la sección de favoritos debe mostrar un estado vacío con un mensaje y al menos una acción recomendada (por ejemplo, ir a explorar productos). | F19: x | I19: Cumple.
B20: 8 | C20: Debe existir un enlace o botón claro de navegación para volver a la página anterior o al catálogo principal de productos. | F20: x | I20: Cumple.

Sheet No-funcionales Favoritos
B2: LISTADO DE REQUERIMIENTOS DE COMPRALO | K2: ESTADISTICAS
K3: Requirimientos | L3: =COUNT(B12:D100) -> 24
B4: SI | C4: Marque con una equis (X) si el sistema cumple con la función descrita | K4: Cumplidos | L4: =COUNTIF(F12:F100,"X") -> 24
B5: NO | C5: Marque con una equis (X) si el sistema no cumple con la función descrita | K5: Porcentaje | L5: =PERCENTOF(L4,L3) -> #NAME?
B6: ADI | C6: Marque con una equis (X) si el sistema debe adicionar la función descrita
B7: Observaciones: | D7: Espacio para complementar respuestas
B9: REQUERIMIENTOS FUNCIONALES DE LA SECRETARIA GESTORA (FUNCIONARIO)
F10: Nivel de cumplimiento | I10: Observaciones
B11: REQUERIMIENTOS NO FUNCIONALES FAVORITOS | F11: SI | G11: NO | H11: ADI
B13: 1 | C13: La carga inicial de la sección de favoritos (incluyendo el primer lote de productos) debe completarse en menos de ~2 segundos en conexiones de banda ancha típicas. | F13: x
B14: 2 | C14: La consulta al backend para obtener los productos favoritos debe estar indexada por id_usuario para evitar escaneos completos sobre la tabla de favoritos. | F14: x
B15: 3 | C15: La API de favoritos debe mantener un tiempo de respuesta objetivo P95 menor a 300–400 ms bajo carga normal. | F15: x
B16: 4 | C16: El layout de la lista de favoritos debe ser completamente responsivo, mostrando una columna en móviles y varias columnas en pantallas de mayor tamaño sin solapamientos ni recortes de contenido. | F16: x
B17: 5 | C17: Las imágenes de los productos favoritos deben utilizar lazy loading para aquellos elementos que aún no están en el viewport, reduciendo el peso inicial de la página. | F17: x
B18: 6 | C18: El diseño debe reservar espacio para las tarjetas antes de cargar las imágenes, evitando saltos de layout perceptibles (CLS). | F18: x
B19: 7 | C19: La acción de quitar de favoritos debe ejecutarse sin recargar la página completa, actualizando la interfaz de manera reactiva (por ejemplo, mediante actualización del estado en cliente). | F19: x
B20: 8 | C20: Los botones o iconos de quitar/agregar a favoritos deben tener tamaño y contraste suficientes para ser usados cómodamente en dispositivos táctiles y cumplir criterios de accesibilidad. | F20: x
B21: 9 | C21: Los errores al intentar quitar un producto de favoritos (por ejemplo, fallo de red) deben mostrarse al usuario con mensajes claros sin dejar la interfaz en un estado inconsistente. | F21: x
B22: 10 | C22: El texto que indica el número de productos guardados en favoritos debe actualizarse en tiempo real cuando se agregan o eliminan favoritos, sin requerir recarga manual. | F22: x
B23: 11 | C23: El formato de dicho texto debe ser internacionalizable (singular/plural, otros idiomas) para adaptarse a distintas configuraciones regionales. | F23: x
B24: 12 | C24: El cálculo del contador de favoritos no debe implicar una consulta pesada adicional; idealmente debe derivarse de la misma respuesta que trae la lista de productos. | F24: x
... B36: 24 | C36: La sección de favoritos debe respetar las políticas de cookies y privacidad: si el usuario ha rechazado cookies de analítica/marketing, la carga de la sección no debe disparar scripts adicionales de tracking | F36: x

Sheet Funcionales Dashboard Admin
B2: LISTADO DE REQUERIMIENTOS DE COMPRALO | K2: ESTADISTICAS
K3: Requirimientos | L3: =COUNT(B12:D97) -> 22
B4: SI | C4: Marque con una equis (X) si el sistema cumple con la función descrita | K4: Cumplidos | L4: =COUNTIF(F12:F97,"X") -> 22
B5: NO | C5: Marque con una equis (X) si el sistema no cumple con la función descrita | K5: Porcentaje | L5: =PERCENTOF(L4,L3) -> #NAME?
B6: ADI | C6: Marque con una equis (X) si el sistema debe adicionar la función descrita
B7: Observaciones: | D7: Espacio para complementar respuestas
B9: REQUERIMIENTOS FUNCIONALES DE LA SECRETARIA GESTORA (FUNCIONARIO)
F10: Nivel de cumplimiento | I10: Observaciones
B11: REQUERIMIENTOS FUNCIONALES DASHBOARD ADMIN | F11: SI | G11: NO | H11: ADI
B13: 1 | C13: El sistema debe mostrar una página principal de Dashboard accesible desde el menú lateral con la opción "Dashboard" seleccionada. | F13: X | I13: Cumple.
B14: 2 | C14: El sistema debe mostrar en el sidebar el nombre y el correo del administrador logueado. | F14: X | I14: Cumple.
B15: 3 | C15: El sistema debe ofrecer menú lateral con secciones: Principal (Dashboard, Órdenes), Catálogo (Categorías, Atributos, Marcas, Proveedores, Productos), Gestión (Usuarios, Descuentos, Puntos, Barra Informativa) y Otros (Analíticas). | F15: X | I15: Cumple.
B16: 4 | C16: El sistema debe mostrar breadcrumbs que indiquen la ruta actual (por ejemplo "Inicio -> Dashboard"). | F16: X | I16: No cumple. Solo aparece en productos.
B17: 5 | C17: El sistema debe mostrar la hora de la última actualización de los datos del dashboard. | F17: X | I17: Cumple.
B18: 6 | C18: El sistema debe permitir filtrar los datos del dashboard por período (por ejemplo "Mensual"). | F18: X | I18: No cumple. Los datos en las tarjetas no concuerdan con el periodo filtrado, no se puede seleccionar un rango de periodo como un mes en concreto o ciertas semanas de un mes.
B19: 7 | C19: El sistema debe permitir configurar un intervalo de actualización automática (por ejemplo "Cada 30 s"). | F19: X | I19: Cumple.
B20: 8 | C20: El sistema debe ofrecer un botón "Actualizar" para refrescar manualmente los datos del dashboard. | F20: X | I20: Cumple.
B21: 9 | C21: El sistema debe mostrar un resumen en texto del mes con: total de pedidos, pedidos enviados, productos más vendidos con cantidades, facturación total y tasa de conversión. | F21: X | I21: Cumple.
B22: 10 | C22: El sistema debe mostrar tarjetas de KPIs con: Total de Órdenes, Órdenes Activas, Órdenes Enviadas e Ingresos Totales, cada una con valor actual y variación respecto al mes anterior. | F22: X | I22: Cumple.
B23: 11 | C23: El sistema debe representar la variación mensual con indicadores visuales (por ejemplo flecha y color: verde subida, neutro sin cambio). | F23: X | I23: Cumple.
B24: 12 | C24: El sistema debe mostrar un gráfico de resumen de ventas (por ejemplo barras por mes) con subtítulo "Rendimiento de ventas mensual". | F24: X | I24: Cumple.
... B34: 23 | C34: El sistema debe ofrecer en el header un control para iniciar un tour o guía (icono de reproducción), un chatbot interactivo y controles para alternar tema claro/oscuro (icono sol, icono luna). | F34: X | I34: No cumple. El icono de la guia no concuerda con el descrito en el requerimiento.

Sheet No-funcionales Dashboard Admin
B2: LISTADO DE REQUERIMIENTOS DE COMPRALO | K2: ESTADISTICAS
K3: Requirimientos | L3: =COUNT(B12:D99) -> 19
B4: SI | C4: Marque con una equis (X) si el sistema cumple con la función descrita | K4: Cumplidos | L4: =COUNTIF(F12:F99,"X") -> 19
B5: NO | C5: Marque con una equis (X) si el sistema no cumple con la función descrita | K5: Porcentaje | L5: =PERCENTOF(L4,L3) -> #NAME?
B6: ADI | C6: Marque con una equis (X) si el sistema debe adicionar la función descrita
B7: Observaciones: | D7: Espacio para complementar respuestas
B9: REQUERIMIENTOS FUNCIONALES DE LA SECRETARIA GESTORA (FUNCIONARIO)
F10: Nivel de cumplimiento | I10: Observaciones
B11: REQUERIMIENTOS FUNCIONALES DASHBOARD ADMIN | F11: SI | G11: NO | H11: ADI
B13: 1 | C13: El dashboard debe cargar en un tiempo aceptable (por ejemplo menos de 3 segundos) para no bloquear al administrador. | F13: X
B14: 2 | C14: Solo usuarios autenticados con rol de administrador (o equivalente) deben poder acceder al dashboard. | F14: X
B15: 3 | C15: Los valores mostrados (órdenes, ingresos, conversión, productos destacados, actividad reciente) deben coincidir con los datos almacenados y el período seleccionado. | F15: X
B16: 4 | C16: El menú lateral debe dejar claramente resaltada la opción "Dashboard" cuando el usuario está en esa página. | F16: X
B17: 5 | C17: Las tarjetas de KPIs y el gráfico deben usar una paleta y tipografía coherentes con el resto del panel (por ejemplo tema oscuro). | F17: X
B18: 6 | C18: El dashboard debe adaptarse a distintos anchos de pantalla sin ocultar contenido esencial ni romper el layout. | F18: X
B19: 7 | C19: La actualización automática no debe provocar parpadeos molestos ni pérdida de scroll; los datos deben actualizarse de forma controlada. | F19: X
B20: 8 | C20: Los textos del dashboard (títulos, etiquetas, resumen del mes) deben estar en español y ser editables/configurables para la instancia. | F20: X
B21: 9 | C21: El gráfico de ventas y las tablas deben ser legibles (buen contraste, tamaños de fuente adecuados). | F21: X
B22: 10 | C22: Los iconos del header (notificaciones, configuración, perfil, tour, tema) deben ser identificables. | F22: X
B23: 11 | C23: La lógica que calcula totales, variaciones porcentuales y top productos debe estar centralizada y ser mantenible (evitar duplicación y fórmulas dispersas). | F23: X
B24: 12 | C24: Si el backend no responde o falla, el dashboard debe mostrar un mensaje de error claro y no pantallas en blanco. | F24: X
... B31: 19 | C31: La tabla de actividad reciente debe ordenar por fecha (más recientes primero) de forma coherente con el título "Últimas actualizaciones de órdenes" | F31: X

Sheet Funcionales Ordenes admin
B2: LISTADO DE REQUERIMIENTOS DE COMPRALO | K2: ESTADISTICAS
K3: Requirimientos | L3: =COUNT(B12:D82) -> 7
B4: SI | C4: Marque con una equis (X) si el sistema cumple con la función descrita | K4: Cumplidos | L4: =COUNTIF(F12:F82,"X") -> 7
B5: NO | C5: Marque con una equis (X) si el sistema no cumple con la función descrita | K5: Porcentaje | L5: =PERCENTOF(L4,L3) -> #NAME?
B6: ADI | C6: Marque con una equis (X) si el sistema debe adicionar la función descrita
B7: Observaciones: | D7: Espacio para complementar respuestas
F9: Nivel de cumplimiento | I9: Observaciones
B10: REQUIRIMIENTOS FUNCIONALES ORDENES ADMIN | F10: SI | G10: NO | H10: ADI
B12: 1 | C12: La sección de Órdenes debe mostrar tarjetas de resumen con el total de órdenes, órdenes pendientes, completadas, canceladas y el monto total de ventas completadas. | F12: X | I12: Cumple.
B13: 2 | C13: La sección debe mostrar un listado paginado de órdenes con al menos estas columnas: ID de orden, cliente (nombre y email), fecha, estado, monto total, número de ítems, método de pago y acciones. | F13: X | I13: Cumple.
B14: 3 | C14: El administrador debe poder buscar órdenes por ID de orden, nombre de cliente o correo electrónico desde un campo de búsqueda en la parte superior del listado. | F14: X | I14: Cumple.
B15: 4 | C15: El administrador debe poder filtrar las órdenes por un rango de fechas utilizando controles “Desde” y “Hasta”. | F15: X | I15: Cumple.
B16: 5 | C16: El administrador debe poder filtrar las órdenes por estado (por ejemplo: todas, pendientes, completadas, canceladas) usando un selector de estados y un botón para limpiar los filtros. | F16: X | I16: Cumple.
B17: 6 | C17: El listado de órdenes debe permitir abrir el detalle de una orden específica mediante la acción “Ver Detalle”. | F17: X | I17: Cumple.
B18: 7 | C18: La vista de detalle de orden debe mostrar en secciones separadas la información del cliente, la información de la orden (ID, fecha, método de pago, estado), la dirección completa de envío, los puntos ganados por la compra, el listado de productos (con cantidad, precio unitario, subtotal, opciones elegidas e imagen) y un resumen de importes (subtotal y total). | F18: X | I18: Cumple.

Sheet No-funcionales Ordenes admin
B2: LISTADO DE REQUERIMIENTOS DE COMPRALO | K2: ESTADISTICAS
K3: Requirimientos | L3: =COUNT(B12:D98) -> 20
B4: SI | C4: Marque con una equis (X) si el sistema cumple con la función descrita | K4: Cumplidos | L4: =COUNTIF(F12:F98,"X") -> 20
B5: NO | C5: Marque con una equis (X) si el sistema no cumple con la función descrita | K5: Porcentaje | L5: =PERCENTOF(L4,L3) -> #NAME?
B6: ADI | C6: Marque con una equis (X) si el sistema debe adicionar la función descrita
B7: Observaciones: | D7: Espacio para complementar respuestas
F9: Nivel de cumplimiento | I9: Observaciones
B10: REQUIRIMIENTOS NO FUNCIONALES ORDENES ADMIN | F10: SI | G10: NO | H10: ADI
B12: 1 | C12: El tiempo de carga inicial de la sección de Órdenes (tarjetas de resumen + primera página del listado) debe ser razonable para un entorno administrativo, evitando bloqueos visibles mientras se obtienen los datos. | F12: X
B13: 2 | C13: Las consultas que alimentan las tarjetas de resumen (totales de órdenes y ventas) deben utilizar agregaciones optimizadas sobre las tablas de órdenes para no degradar el rendimiento del resto del sistema. | F13: X
B14: 3 | C14: Las tarjetas de resumen deben actualizarse de forma consistente con la información del listado, utilizando el mismo rango temporal y criterios que se defina para la vista. | F14: X
B15: 4 | C15: El listado de órdenes debe estar paginado para evitar cargar en memoria un número excesivo de registros y mantener tiempos de respuesta aceptables. | F15: X
B16: 5 | C16: La paginación debe indicar de forma clara al administrador en qué página se encuentra y cuántos registros se muestran por página, manteniendo la navegación fluida entre páginas. | F16: X
B17: 6 | C17: El campo de búsqueda debe responder sin bloqueos perceptibles, ejecutando las consultas de filtrado de manera asincrónica o con recarga controlada. | F17: X
B18: 7 | C18: Las búsquedas por cliente o email deben estar apoyadas en índices adecuados en la base de datos para evitar escaneos completos de la tabla de órdenes. | F18: X
B19: 8 | C19: La aplicación de filtros por rango de fechas debe validar que las fechas sean válidas (formato correcto, fecha “Desde” no posterior a “Hasta”) antes de ejecutar la consulta. | F19: X
B20: 9 | C20: Las consultas filtradas por rango de fechas deben usar índices sobre la columna de fecha de la orden para que el rendimiento se mantenga aceptable incluso con muchos registros históricos. | F20: X
B21: 10 | C21: El selector de estado debe actualizar el listado sin inconsistencias visuales, mostrando únicamente las órdenes que pertenecen al estado elegido y reflejándolo en las tarjetas de resumen cuando corresponda. | F21: X
B22: 11 | C22: El botón de “Limpiar” filtros debe restaurar el listado a su estado por defecto sin dejar filtros “fantasma” aplicados en la capa de datos. | F22: X
B23: 12 | C23: La tabla de órdenes debe mantener un formato legible y consistente, con alineación adecuada de montos, fechas y textos, tanto en pantallas grandes como en resoluciones más pequeñas usadas en administración. | F23: X
... B31: 20 | C31: Los mensajes de error en caso de fallo al cargar órdenes o detalles (por ejemplo, error de red o ID inexistente) deben ser claros, sin exponer información técnica sensible y permitiendo reintentar o volver al listado | F31: X

Sheet Funcionales Productos Admin
B2: LISTADO DE REQUERIMIENTOS DE COMPRALO | K2: ESTADISTICAS
K3: Requirimientos | L3: =COUNT(B12:D97) -> 14
B4: SI | C4: Marque con una equis (X) si el sistema cumple con la función descrita | K4: Cumplidos | L4: =COUNTIF(F12:F97,"X") -> 14
B5: NO | C5: Marque con una equis (X) si el sistema no cumple con la función descrita | K5: Porcentaje | L5: =PERCENTOF(L4,L3) -> #NAME?
B6: ADI | C6: Marque con una equis (X) si el sistema debe adicionar la función descrita
B7: Observaciones: | D7: Espacio para complementar respuestas
F9: Nivel de cumplimiento | I9: Observaciones
B10: REQUIRIMIENTOS FUNCIONALES PRODUCTOS ADMIN | F10: SI | G10: NO | H10: ADI
B12: 1 | C12: El sistema debe mostrar un listado de todos los productos en la sección “Todos los Productos” del admin. | F12: X
B13: 2 | C13: La tabla debe mostrar por cada producto: Imagen (miniatura), Producto (nombre e ID), Categoría, Línea, Sublínea, Marca, Precio (único o rango), Stock, Estado (Activo/Inactivo) y Acciones. | F13: X
B14: 3 | C14: El sistema debe mostrar un resumen de stock con tres contadores: “En Stock”, “Stock Bajo” y “Sin Stock”, con valores numéricos actualizados. | F14: X
B15: 4 | C15: El sistema debe permitir buscar productos por nombre mediante un campo de búsqueda (placeholder “Nombre del producto…”). | F15: X
B16: 5 | C16: El sistema debe permitir filtrar productos por Categoría, Línea, Sublínea, Marca y Proveedor mediante desplegables con opción “Todas las…”. | F16: X
B17: 7 | C17: El sistema debe permitir agregar un nuevo producto mediante el botón “+ Agregar Producto”. | F17: X
B18: 8 | C18: El sistema debe permitir ver el detalle de un producto mediante el ícono de ojo en la columna Acciones. | F18: X
B19: 9 | C19: El sistema debe permitir editar un producto existente mediante el ícono de lápiz en la columna Acciones. | F19: X
B20: 10 | C20: El sistema debe permitir activar o desactivar un producto (cambiar estado) mediante el ícono de encendido en la columna Acciones. | F20: X
B21: 11 | C21: El sistema debe mostrar el estado de cada producto de forma clara (Activo / Inactivo), por ejemplo con badges diferenciados por color. | F21: X
B22: 12 | C22: El sistema debe soportar productos con precio único o rango de precios (ej. “$20.000” o “$300.000 - $500.000”). | F22: X
B23: 13 | C23: El sistema debe ofrecer paginación del listado (Anterior, Siguiente) y permitir elegir el número de filas por página (ej. 10). | F23: X
... B25: 16 | C25: El sistema debe resaltar en el menú lateral la sección activa (“Productos”) cuando el usuario está en la sección de productos. | F25: X

Sheet No-funcionales Productos Admin 
B2: LISTADO DE REQUERIMIENTOS DE COMPRALO | K2: ESTADISTICAS
K3: Requirimientos | L3: =COUNT(B12:D97) -> 16
B4: SI | C4: Marque con una equis (X) si el sistema cumple con la función descrita | K4: Cumplidos | L4: =COUNTIF(F12:F97,"X") -> 16
B5: NO | C5: Marque con una equis (X) si el sistema no cumple con la función descrita | K5: Porcentaje | L5: =PERCENTOF(L4,L3) -> #NAME?
B6: ADI | C6: Marque con una equis (X) si el sistema debe adicionar la función descrita
B7: Observaciones: | D7: Espacio para complementar respuestas
F9: Nivel de cumplimiento | I9: Observaciones
B10: REQUIRIMIENTOS NO FUNCIONALES PRODUCTOS ADMIN | F10: SI | G10: NO | H10: ADI
B12: 1 | C12: La carga del listado de productos (incluidas miniaturas) debe realizarse en un tiempo aceptable sin bloquear la interfaz. | F12: X
B13: 2 | C13: La búsqueda y los filtros (categoría, línea, sublínea, marca, proveedor) deben responder con baja latencia para no degradar la experiencia del administrador. | F13: X
B14: 3 | C14: El diseño de la sección Productos debe ser coherente con el resto del dashboard (tema oscuro, tipografía, espaciados y componentes reutilizados). | F14: X
B15: 4 | C15: Los colores del resumen de stock (verde En Stock, naranja Stock Bajo, rojo Sin Stock) y de estado (Activo/Inactivo) deben ser consistentes y accesibles (contraste y texto legible). | F15: X
B16: 5 | C16: Los íconos de Acciones (ver, editar, activar/desactivar) deben ser reconocibles y usables en distintos tamaños de pantalla. | F16: X
B17: 6 | C17: El acceso a la sección Productos del admin debe estar restringido a usuarios autenticados con rol de administrador (o el equivalente en el proyecto). | F17: X
B18: 7 | C18: Los datos mostrados (ID, nombre, categoría, línea, sublínea, marca, precio, stock, estado) deben coincidir con los almacenados en la base de datos. | F18: X
B19: 8 | C19: La paginación y el cambio de “filas por página” deben mantener el contexto (filtros y búsqueda aplicados) sin recargas bruscas. | F19: X
B20: 9 | C20: Las imágenes de producto en la tabla deben cargarse de forma eficiente (tamaño adecuado, lazy loading si aplica) para no ralentizar la página. | F20: X
B21: 10 | C21: Los textos de la interfaz (títulos, columnas, botones, filtros) deben estar en español y ser consistentes con el resto del sistema. | F21: X
B22: 11 | C22: La tabla debe seguir siendo usable con muchos productos gracias a paginación, búsqueda y filtros. | F22: X
B23: 12 | C23: Los contadores del resumen de stock deben actualizarse de forma coherente con los filtros aplicados o con una política de actualización definida. | F23: X
... B27: 16 | C27: En caso de error al cargar productos o al aplicar filtros, debe mostrarse un mensaje claro y la opción de reintentar, evitando pantallas vacías o confusas. | F27: X

Sheet Funcionales Categorías Admin
B2: LISTADO DE REQUERIMIENTOS DE COMPRALO | K2: ESTADISTICAS
K3: Requirimientos | L3: =COUNT(B12:D98) -> 13
B4: SI | C4: Marque con una equis (X) si el sistema cumple con la función descrita | K4: Cumplidos | L4: =COUNTIF(F12:F98,"X") -> 13
B5: NO | C5: Marque con una equis (X) si el sistema no cumple con la función descrita | K5: Porcentaje | L5: =PERCENTOF(L4,L3) -> #NAME?
B6: ADI | C6: Marque con una equis (X) si el sistema debe adicionar la función descrita
B7: Observaciones: | D7: Espacio para complementar respuestas
F9: Nivel de cumplimiento | I9: Observaciones
B10: REQUIRIMIENTOS FUNCIONALES CATEGORIAS ADMIN | F10: SI | G10: NO | H10: ADI
B12: 1 | C12: El sistema debe permitir crear categorías principales | F12: X
B13: 1 | C13: La sección de categorías debe mostrar tres pestañas: Categoría, Línea y Sublínea, con el conteo de registros en cada una. | F13: X
B14: 2 | C14: El sistema debe listar categorías/líneas/sublíneas en tabla con columnas: ID, Nombre, Fecha de Creación, Estado y Acciones. | F14: X
B15: 3 | C15: En las pestañas Línea y Sublínea, la tabla debe incluir la columna Padre que muestre la entidad superior en la jerarquía (categoría para Línea, línea para Sublínea). | F15: X
B16: 4 | C16: El sistema debe mostrar el estado de cada registro (por ejemplo, "Activo") mediante etiquetas/badges. | F16: X
B17: 5 | C17: El sistema debe incluir el botón "+ Agregar Categoría" para crear nuevas categorías, líneas o sublíneas según la pestaña activa. | F17: X
B18: 6 | C18: El sistema debe proporcionar un campo de búsqueda para filtrar por nombre ("Buscar categoría...", "Buscar línea...", "Buscar sublínea..." según la pestaña). | F18: X
B19: 7 | C19: En pestaña Línea, el sistema debe permitir filtrar por categoría padre mediante un desplegable (por ejemplo, "Todas las categorías"). | F19: X
B20: 8 | C20: En pestaña Sublínea, el sistema debe permitir filtrar por línea padre mediante un desplegable (por ejemplo, "Todas las lineas"). | F20: X
B21: 10 | C21: Para cada fila, el sistema debe ofrecer el botón de ver detalle (ícono de ojo). | F21: X
B22: 11 | C22: Para cada fila, el sistema debe ofrecer el botón de editar (ícono de lápiz). | F22: X
B23: 12 | C23: Para cada fila, el sistema debe ofrecer el botón de activar/desactivar (ícono de interruptor). | F23: X
B24: 13 | C24: La sección de categorías debe aparecer en el menú lateral del panel admin y resaltarse cuando esté activa. | F24: X

Sheet No-funcionales Categorias Admin
B2: LISTADO DE REQUERIMIENTOS DE COMPRALO | K2: ESTADISTICAS
K3: Requirimientos | L3: =COUNT(B12:D85) -> 13
B4: SI | C4: Marque con una equis (X) si el sistema cumple con la función descrita | K4: Cumplidos | L4: =COUNTIF(F12:F85,"X") -> 13
B5: NO | C5: Marque con una equis (X) si el sistema no cumple con la función descrita | K5: Porcentaje | L5: =PERCENTOF(L4,L3) -> #NAME?
B6: ADI | C6: Marque con una equis (X) si el sistema debe adicionar la función descrita
B7: Observaciones: | D7: Espacio para complementar respuestas
F9: Nivel de cumplimiento | I9: Observaciones
B10: REQUIRIMIENTOS NO FUNCIONALES CATEGORIAS ADMIN | F10: SI | G10: NO | H10: ADI
B12: 1 | C12: La estructura jerárquica debe cargarse en menos de 1 segundo | F12: X
B13: 2 | C13: La tabla de categorías/líneas/sublíneas debe cargar y actualizarse con filtros y búsqueda en un tiempo razonable (< 2–3 segundos en condiciones normales). | F13: X
B14: 3 | C14: Las consultas que alimentan la tabla deben soportar paginación, búsqueda por texto y filtro por padre sin tiempos de respuesta excesivos. | F14: X
B15: 4 | C15: Las acciones de crear, editar y cambiar estado deben aplicarse sin recarga completa de la página o con feedback inmediato (toast, actualización de fila). | F15: X
B16: 5 | C16: La sección debe usar el mismo tema oscuro y estilos que el resto del panel admin para mantener coherencia. | F16: X
B17: 6 | C17: Los badges de estado deben tener contraste suficiente para distinguir "Activo" de "Inactivo". | F17: X
B18: 7 | C18: Botones e iconos de acción deben tener tamaño y espaciado adecuados para uso con mouse y teclado. | F18: X
B19: 8 | C19: Los controles (búsqueda, filtros, acciones) deben ser accesibles por teclado con focos visibles. | F19: X
B20: 9 | C20: Solo los usuarios autenticados con rol de administrador deben poder acceder a la sección de categorías. | F20: X
B21: 10 | C21: Los datos mostrados (ID, nombre, padre, fecha, estado) deben ser consistentes con la base de datos. | F21: X
B22: 11 | C22: La jerarquía categoría → línea → sublínea debe respetarse en filtros y en la columna Padre. | F22: X
B23: 12 | C23: Los textos de la interfaz (etiquetas, placeholders, botones) deben ser completamente traducibles. | F23: X
B24: 13 | C24: La estructura de la sección debe facilitar añadir nuevas columnas o filtros sin refactorizaciones amplias | F24: X

Sheet Funcionales Usuario Admin
B2: LISTADO DE REQUERIMIENTOS DE COMPRALO | K2: ESTADISTICAS
K3: Requirimientos | L3: =COUNT(B12:D95) -> 10
B4: SI | C4: Marque con una equis (X) si el sistema cumple con la función descrita | K4: Cumplidos | L4: =COUNTIF(F12:F95,"X") -> 10
B5: NO | C5: Marque con una equis (X) si el sistema no cumple con la función descrita | K5: Porcentaje | L5: =PERCENTOF(L4,L3) -> #NAME?
B6: ADI | C6: Marque con una equis (X) si el sistema debe adicionar la función descrita
B7: Observaciones: | D7: Espacio para complementar respuestas
F9: Nivel de cumplimiento | I9: Observaciones
B10: REQUIRIMIENTOS FUNCIONALES USUARIOS ADMIN | F10: SI | G10: NO | H10: ADI
B12: 1 | C12: El sistema debe mostrar un listado de todos los usuarios registrados en una tabla dentro de la sección “Usuarios”. | F12: X
B13: 2 | C13: La tabla debe mostrar por cada usuario: Usuario (inicial/avatar, nombre completo, email), Teléfono, Género, Rol, Estado y Acciones. | F13: X
B14: 3 | C14: El sistema debe mostrar tarjetas de resumen con: Total de usuarios, Clientes, Admins, Usuarios activos y Usuarios inactivos, con valores numéricos actualizados. | F14: X
B15: 4 | C15: El sistema debe permitir editar los datos de un usuario mediante el ícono de lápiz en la columna Acciones. | F15: X
B16: 5 | C16: El sistema debe permitir activar o desactivar un usuario (cambiar estado entre Activo/Inactivo) mediante el ícono de encendido en la columna Acciones. | F16: X
B17: 6 | C17: El sistema debe mostrar el rol de cada usuario (por ejemplo Admin, Cliente) de forma clara y diferenciada visualmente. | F17: X
B18: 7 | C18: El sistema debe mostrar el estado de cada usuario (Activo / Inactivo) de forma clara, por ejemplo con badges diferenciados por color. | F18: X
B19: 8 | C19: El sistema debe ofrecer paginación del listado (Anterior, Siguiente) y permitir elegir el número de filas por página (por ejemplo 10). | F19: X
B20: 9 | C20: El sistema debe permitir navegar a otras secciones del admin (Dashboard, Órdenes, Categorías, Atributos, Marcas, Proveedores, Productos, Descuentos, Puntos, Barra informativa, Analíticas) desde el menú lateral. | F20: X
B21: 10 | C21: El sistema debe resaltar en el menú lateral la sección “Usuarios” cuando el usuario está en esta sección. | F21: X

Sheet No-funcionales Usuarios Admin
B2: LISTADO DE REQUERIMIENTOS DE COMPRALO | K2: ESTADISTICAS
K3: Requirimientos | L3: =COUNT(B12:D99) -> 16
B4: SI | C4: Marque con una equis (X) si el sistema cumple con la función descrita | K4: Cumplidos | L4: =COUNTIF(F12:F99,"X") -> 16
B5: NO | C5: Marque con una equis (X) si el sistema no cumple con la función descrita | K5: Porcentaje | L5: =PERCENTOF(L4,L3) -> #NAME?
B6: ADI | C6: Marque con una equis (X) si el sistema debe adicionar la función descrita
B7: Observaciones: | D7: Espacio para complementar respuestas
F9: Nivel de cumplimiento | I9: Observaciones
B10: REQUIRIMIENTOS FUNCIONALES USUARIOS ADMIN | F10: SI | G10: NO | H10: ADI
B12: 1 | C12: La carga del listado de usuarios y de los contadores de resumen debe realizarse en un tiempo aceptable sin bloquear la interfaz. | F12: X
B13: 2 | C13: La paginación debe cargar solo la página solicitada para no degradar el rendimiento con muchos usuarios. | F13: X
B14: 3 | C14: El diseño de la sección Usuarios debe ser coherente con el resto del dashboard (tema oscuro, tipografía, espaciados). | F14: X
B15: 4 | C15: Los roles (Admin, Cliente) y los estados (Activo, Inactivo) deben distinguirse de forma clara por color y texto, de forma accesible. | F15: X
B16: 5 | C16: Los íconos de Acciones (editar, activar/desactivar) deben ser reconocibles y usables en distintos tamaños de pantalla. | F16: X
B17: 6 | C17: El acceso a la sección Usuarios debe estar restringido a usuarios autenticados con rol de administrador (o el equivalente definido en el proyecto). | F17: X
B18: 7 | C18: Los datos mostrados (nombre, email, teléfono, género, rol, estado) deben coincidir con los almacenados en la base de datos. | F18: X
B19: 8 | C19: Todas las entradas relacionadas con usuarios (creación, edición, búsqueda) deben validarse y sanearse en backend para evitar inyección de código o manipulación indebida de datos. | F19: X
B20: 9 | C20: La paginación y el cambio de “filas por página” deben mantener el contexto sin recargas bruscas de la página. | F20: X
B21: 10 | C21: Los textos de la interfaz (títulos, columnas, tarjetas, botones) deben estar en español y ser consistentes con el resto del sistema. | F21: X
B22: 11 | C22: Los contadores del resumen (Total, Clientes, Admins, Activos, Inactivos) deben ser coherentes entre sí y con el listado paginado. | F22: X
B23: 12 | C23: La sección debe cumplir criterios básicos de accesibilidad: contraste, foco visible y navegación por teclado en elementos interactivos. | F23: X
... B27: 16 | C27: El manejo de datos personales (nombre, email, teléfono) debe alinearse con la política de privacidad del sistema y con buenas prácticas de protección de datos. | F27: X

Sheet Funcionales Atributos
B2: LISTADO DE REQUERIMIENTOS DE COMPRALO | K2: ESTADISTICAS
K3: Requirimientos | L3: =COUNT(B12:D99) -> 10
B4: SI | C4: Marque con una equis (X) si el sistema cumple con la función descrita | K4: Cumplidos | L4: =COUNTIF(F12:F99,"X") -> 9
B5: NO | C5: Marque con una equis (X) si el sistema no cumple con la función descrita | K5: Porcentaje | L5: =PERCENTOF(L4,L3) -> #NAME?
B6: ADI | C6: Marque con una equis (X) si el sistema debe adicionar la función descrita
B7: Observaciones: | D7: Espacio para complementar respuestas
F9: Nivel de cumplimiento | I9: Observaciones
B10: REQUIRIMIENTOS FUNCIONALES ATRIBUTOS | F10: SI | G10: NO | H10: ADI
B12: 1 | C12: La sección de Atributos debe mostrar un listado tabular de todos los atributos configurados en el catálogo, incluyendo al menos columnas de ID, nombre, tipo de dato y si tiene valores predefinidos. | F12: X
B13: 2 | C13: La sección debe permitir buscar atributos por nombre mediante un campo de búsqueda en la parte superior del listado. | F13: X
B14: 3 | C14: La sección debe permitir agregar un nuevo atributo haciendo clic en el botón “Agregar Atributo”, abriendo un formulario con nombre, tipo de dato y opción de definir si tendrá valores predefinidos. | F14: X
B15: 4 | C15: La sección debe permitir editar un atributo existente mediante una acción de edición en la columna de Acciones. | F15: X
B16: 5 | C16: La sección debe permitir eliminar un atributo existente mediante una acción de eliminación en la columna de Acciones.
B17: 6 | C17: La sección debe permitir al administrador ver y gestionar los valores predefinidos de un atributo (por ejemplo, para “Almacenamiento” ver 128GB, 256GB, etc.) accediendo a una vista de “Valores” asociada al atributo. | F17: X
B18: 7 | C18: En la vista de valores de un atributo, el sistema debe listar los valores predefinidos con columnas de ID, valor, color (cuando aplique), orden de visualización y estado activo/inactivo, además de acciones de edición y eliminación. | F18: X
B19: 8 | C19: En la vista de valores de un atributo, el sistema debe permitir agregar nuevos valores predefinidos mediante un botón “Agregar valor”. | F19: X
B20: 9 | C20: Ambas vistas (listado de atributos y listado de valores) deben soportar paginación, mostrando un número configurable de filas por página y controles para navegar entre páginas. | F20: X
B21: 10 | C21: La sección de Atributos debe integrarse con el resto del dashboard reutilizando el mismo menú lateral, encabezado y esquema de navegación (por ejemplo, resaltando “Atributos” en el menú cuando la vista está activa). | F21: X

Sheet No-funcionales Atributos
B2: LISTADO DE REQUERIMIENTOS DE COMPRALO | K2: ESTADISTICAS
K3: Requirimientos | L3: =COUNT(B12:D99) -> 24
B4: SI | C4: Marque con una equis (X) si el sistema cumple con la función descrita | K4: Cumplidos | L4: =COUNTIF(F12:F99,"X") -> 24
B5: NO | C5: Marque con una equis (X) si el sistema no cumple con la función descrita | K5: Porcentaje | L5: =PERCENTOF(L4,L3) -> #NAME?
B6: ADI | C6: Marque con una equis (X) si el sistema debe adicionar la función descrita
B7: Observaciones: | D7: Espacio para complementar respuestas
F9: Nivel de cumplimiento | I9: Observaciones
B10: REQUIRIMIENTOS NO FUNCIONALES ATRIBUTOS | F10: SI | G10: NO | H10: ADI
B12: 1 | C12: El listado inicial de atributos debe cargarse en un tiempo razonable (por ejemplo, menos de ~2–3 segundos en condiciones normales) para no afectar la experiencia del administrador. | F12: X
B13: 2 | C13: Las consultas a la base de datos para obtener atributos deben estar paginadas y utilizar índices sobre campos como nombre y tipo para evitar lecturas completas de tablas. | F13: X
B14: 3 | C14: Al aplicar un término de búsqueda de atributo, el filtrado debe ejecutarse sin bloquear la interfaz, mostrando un indicador de carga si el tiempo de respuesta es apreciable. | F14: X
B15: 4 | C15: La interfaz de atributos debe ser responsiva, adaptándose correctamente a distintos anchos de pantalla (al menos escritorio y laptops), sin cortar columnas críticas ni acciones. | F15: X
B16: 5 | C16: Los nombres de atributos mostrados en la tabla deben truncarse de forma elegante cuando excedan el ancho de la columna para evitar desbordes visuales. | F16: X
B17: 6 | C17: La paginación en el listado de atributos debe mantener el estado del filtro de búsqueda aplicado, evitando que se pierda al cambiar de página. | F17: X
B18: 7 | C18: El formulario para crear o editar un atributo debe validar que el nombre no vaya vacío y que el tipo de dato sea uno de los tipos permitidos (por ejemplo, texto, número, booleano), mostrando mensajes de error claros. | F18: X
B19: 8 | C19: El formulario de atributos debe impedir envíos duplicados (por ejemplo, deshabilitando el botón de guardar mientras se procesa la solicitud) para evitar crear o editar dos veces el mismo registro. | F19: X
B20: 9 | C20: La eliminación de un atributo debe requerir confirmación explícita (diálogo o equivalente) para reducir el riesgo de borrados accidentales. | F20: X
B21: 10 | C21: Si un atributo está en uso en productos o variantes, la lógica de backend debe manejar la eliminación de forma segura (por ejemplo, bloqueando o condicionando la acción) y devolver mensajes claros al administrador. | F21: X
B22: 11 | C22: Los iconos de acciones (ver valores, editar, eliminar) deben contar con etiquetas accesibles (title o similares) para que su función sea comprensible incluso sin texto. | F22: X
B23: 12 | C23: El color y el diseño de los botones/etiquetas de estado (por ejemplo, “Activo”) deben seguir el sistema visual del dashboard para mantener consistencia y evitar confusión. | F23: X
... B35: 24 | C35: La implementación de la sección de atributos debe seguir las convenciones de código del proyecto (separación de capas, reutilización de componentes de tabla y formularios) para facilitar su mantenimiento y evolución futura | F35: X

Sheet Funcionales Marcas
B2: LISTADO DE REQUERIMIENTOS DE COMPRALO | K2: ESTADISTICAS
K3: Requirimientos | L3: =COUNT(B12:D85) -> 12
B4: SI | C4: Marque con una equis (X) si el sistema cumple con la función descrita | K4: Cumplidos | L4: =COUNTIF(F12:F85,"X") -> 12
B5: NO | C5: Marque con una equis (X) si el sistema no cumple con la función descrita | K5: Porcentaje | L5: =PERCENTOF(L4,L3) -> #NAME?
B6: ADI | C6: Marque con una equis (X) si el sistema debe adicionar la función descrita
B7: Observaciones: | D7: Espacio para complementar respuestas
F9: Nivel de cumplimiento | I9: Observaciones
B10: REQUIRIMIENTOS FUNCIONALES MARCAS | F10: SI | G10: NO | H10: ADI
B12: 1 | C12: El sistema debe mostrar un listado de todas las marcas registradas en una tabla. | F12: X
B13: 2 | C13: La tabla debe mostrar por cada marca: ID, Nombre, Fecha de creación, Fecha de actualización, Estado (Activo/Inactivo) y Acciones. | F13: X
B14: 3 | C14: El sistema debe permitir agregar una nueva marca mediante un botón “+ Agregar Marca”. | F14: X
B15: 4 | C15: El sistema debe permitir buscar o filtrar marcas por nombre mediante un campo de búsqueda (placeholder tipo “Buscar marca…”). | F15: X
B16: 6 | C16: El sistema debe permitir ver el detalle de una marca mediante un ícono de ojo en la columna Acciones. | F16: X
B17: 7 | C17: El sistema debe permitir editar una marca existente mediante un ícono de lápiz en la columna Acciones. | F17: X
B18: 8 | C18: El sistema debe permitir activar o desactivar una marca (cambiar estado) mediante un ícono de encendido/apagado en la columna Acciones. | F18: X
B19: 9 | C19: El sistema debe mostrar el estado de cada marca de forma clara (Activo / Inactivo), por ejemplo con etiquetas o badges diferenciados. | F19: X
B20: 10 | C20: El sistema debe ofrecer paginación del listado de marcas (Anterior, Siguiente, indicador de página actual y total). | F20: X
B21: 11 | C21: El sistema debe permitir elegir cuántas filas se muestran por página (ej. “Filas por página: 10”). | F21: X
B22: 12 | C22: El sistema debe permitir navegar a otras secciones del admin (Dashboard, Órdenes, Categorías, Atributos, Proveedores, Productos, Usuarios, Descuentos, Puntos, Barra informativa, Analíticas) desde el menú lateral. | F22: X
B23: 13 | C23: El sistema debe mostrar en el menú lateral la sección activa (Marcas resaltada cuando el usuario está en Marcas). | F23: X

Sheet No-funcionales Marcas 
B2: LISTADO DE REQUERIMIENTOS DE COMPRALO | K2: ESTADISTICAS
K3: Requirimientos | L3: =COUNT(B12:D99) -> 22
B4: SI | C4: Marque con una equis (X) si el sistema cumple con la función descrita | K4: Cumplidos | L4: =COUNTIF(F12:F99,"X") -> 22
B5: NO | C5: Marque con una equis (X) si el sistema no cumple con la función descrita | K5: Porcentaje | L5: =PERCENTOF(L4,L3) -> #NAME?
B6: ADI | C6: Marque con una equis (X) si el sistema debe adicionar la función descrita
B7: Observaciones: | D7: Espacio para complementar respuestas
F9: Nivel de cumplimiento | I9: Observaciones
B10: REQUIRIMIENTOS FUNCIONALES MARCAS | F10: SI | G10: NO | H10: ADI
B12: 1 | C12: La carga del listado de marcas debe ser rápida y no bloquear la interfaz, incluso con decenas de registros. | F12: X
B13: 2 | C13: La búsqueda o filtrado por nombre debe responder en un tiempo aceptable (sin demoras perceptibles). | F13: X
B14: 3 | C14: La interfaz debe ser clara y usable para un administrador: etiquetas, botón de agregar y acciones por fila fácilmente identificables. | F14: X
B15: 4 | C15: El diseño debe ser coherente con el resto del dashboard (tema oscuro, tipografía y espaciado uniformes). | F15: X
B16: 5 | C16: Los estados Activo e Inactivo deben distinguirse de forma visual (por ejemplo color o estilo de badge) y con texto, para accesibilidad. | F16: X
B17: 6 | C17: Los íconos de acciones (ver, editar, activar/desactivar) deben ser reconocibles y usables en distintos tamaños de pantalla. | F17: X
B18: 7 | C18: El acceso a la sección Marcas debe estar restringido a usuarios autenticados y con rol de administrador (o el rol que corresponda en el proyecto). | F18: X
B19: 8 | C19: Los datos mostrados (ID, nombre, fechas, estado) deben coincidir con los almacenados en la base de datos; no debe haber incoherencias entre listado y detalle/edición. | F19: X
B20: 9 | C20: La paginación y el cambio de “filas por página” deben funcionar sin recargar toda la página de forma brusca, manteniendo el contexto (filtros, búsqueda). | F20: X
B21: 10 | C21: La interfaz de la sección Marcas debe estar en español (títulos, botones, columnas, estados). | F21: X
B22: 11 | C22: La estructura de la página (encabezado, tabla, filtros, paginación) debe permitir añadir o quitar columnas y acciones sin romper el layout. | F22: X
B23: 12 | C23: Con muchas marcas, el uso de paginación y búsqueda debe permitir encontrar y gestionar marcas sin degradación notable del rendimiento.La búsqueda o filtrado por nombre debe responder en un tiempo aceptable (sin demoras perceptibles). | F23: X
... B33: 22 | C33: Con muchas marcas, el uso de paginación y búsqueda debe permitir encontrar y gestionar marcas sin degradación notable del rendimiento. | F33: X

Sheet Funcionales Proveedores Admin
B2: LISTADO DE REQUERIMIENTOS DE COMPRALO | K2: ESTADISTICAS
K3: Requirimientos | L3: =COUNT(B12:D86) -> 9
B4: SI | C4: Marque con una equis (X) si el sistema cumple con la función descrita | K4: Cumplidos | L4: =COUNTIF(F12:F86,"X") -> 9
B5: NO | C5: Marque con una equis (X) si el sistema no cumple con la función descrita | K5: Porcentaje | L5: =PERCENTOF(L4,L3) -> #NAME?
B6: ADI | C6: Marque con una equis (X) si el sistema debe adicionar la función descrita
B7: Observaciones: | D7: Espacio para complementar respuestas
F9: Nivel de cumplimiento | I9: Observaciones
B10: REQUIRIMIENTOS FUNCIONALES PROVEEDORES | F10: SI | G10: NO | H10: ADI
B12: 1 | C12: El sistema debe mostrar un listado de todos los proveedores registrados en una tabla dentro de la sección “Proveedores”. | F12: X
B13: 2 | C13: La tabla de proveedores debe mostrar, como mínimo, las columnas: ID, Nombre, Fecha de creación, Fecha de actualización, Estado y Acciones. | F13: X
B14: 3 | C14: El sistema debe permitir buscar proveedores por nombre a través de un campo de búsqueda (por ejemplo “Buscar proveedor…”). | F14: X
B15: 5 | C15: El sistema debe permitir agregar un nuevo proveedor mediante el botón “+ Agregar Proveedor”. | F15: X
B16: 6 | C16: El sistema debe permitir visualizar el detalle de un proveedor mediante el ícono de “ver” en la columna Acciones. | F16: X
B17: 7 | C17: El sistema debe permitir editar los datos de un proveedor mediante el ícono de edición en la columna Acciones. | F17: X
B18: 8 | C18: El sistema debe permitir activar o desactivar un proveedor (cambiar su estado entre Activo/Inactivo) mediante el botón/ícono de encendido en la columna Acciones. | F18: X
B19: 9 | C19: El sistema debe mostrar claramente el estado actual de cada proveedor (por ejemplo, badge “Activo” en amarillo). | F19: X
B20: 10 | C20: El sistema debe paginar el listado de proveedores, permitiendo navegar entre páginas con controles de “Anterior”, “Siguiente” y “Filas por página”. | F20: X

Sheet No-funcionales Proveedores Admi
B2: LISTADO DE REQUERIMIENTOS DE COMPRALO | K2: ESTADISTICAS
K3: Requirimientos | L3: =COUNT(B12:D94) -> 17
B4: SI | C4: Marque con una equis (X) si el sistema cumple con la función descrita | K4: Cumplidos | L4: =COUNTIF(F12:F94,"X") -> 17
B5: NO | C5: Marque con una equis (X) si el sistema no cumple con la función descrita | K5: Porcentaje | L5: =PERCENTOF(L4,L3) -> #NAME?
B6: ADI | C6: Marque con una equis (X) si el sistema debe adicionar la función descrita
B7: Observaciones: | D7: Espacio para complementar respuestas
F9: Nivel de cumplimiento | I9: Observaciones
B10: REQUIRIMIENTOS NO FUNCIONALES PROVEEDORES | F10: SI | G10: NO | H10: ADI
B12: 1 | C12: La carga inicial del listado de proveedores debe realizarse en un tiempo aceptable para el administrador, sin bloqueos visibles de la interfaz. | F12: X
B13: 2 | C13: La búsqueda por nombre de proveedor debe responder sin retrasos perceptibles (latencia baja al aplicar el filtro). | F13: X
B14: 3 | C14: El diseño de la sección Proveedores debe ser coherente con el resto del dashboard (tema oscuro, tipografía, espaciados y componentes reutilizados). | F14: X
B15: 4 | C15: Los estados “Activo” e “Inactivo” de un proveedor deben distinguirse de forma clara y consistente, usando colores y texto, de forma accesible. | F15: X
B16: 5 | C16: Los íconos de la columna Acciones (ver, editar, activar/desactivar) deben ser reconocibles y usables tanto en pantallas grandes como en portátiles con menor resolución. | F16: X
B17: 6 | C17: La sección Proveedores debe ser accesible solo para usuarios autenticados con permisos de administrador o rol equivalente de gestión. | F17: X
B18: 7 | C18: Los datos mostrados en la tabla (ID, nombre, fechas, estado) deben estar sincronizados con la base de datos; tras una edición o cambio de estado, la vista debe reflejar el cambio sin inconsistencias. | F18: X
B19: 8 | C19: La paginación y el control de “Filas por página” deben mantener el contexto visual (no hacer saltos bruscos ni perder la posición del usuario). | F19: X
B20: 9 | C20: El campo de búsqueda debe tolerar mayúsculas y minúsculas sin afectar los resultados (búsqueda case-insensitive). | F20: X
B21: 10 | C21: Los textos de la interfaz de la sección Proveedores (títulos, columnas, botones) deben estar en español y ser consistentes con el lenguaje del resto del sistema. | F21: X
B22: 11 | C22: La tabla debe ser legible y usable con diferentes cantidades de proveedores (desde pocos registros hasta decenas), sin romper el layout. | F22: X
B23: 12 | C23: Los cambios realizados sobre un proveedor (edición, activación/desactivación) deben registrarse siguiendo las políticas de auditoría definidas para el backend (fechas de actualización, usuario que realizó el cambio). | F23: X
... B28: 17 | C28: En caso de error al cargar la lista de proveedores, la sección debe mostrar un mensaje claro para el administrador y ofrecer la opción de reintentar, evitando pantallas vacías. | F28: X

Sheet Funcionales Descuentos Admin
B2: LISTADO DE REQUERIMIENTOS DE COMPRALO | K2: ESTADISTICAS
K3: Requirimientos | L3: =COUNT(B12:D91) -> 14
B4: SI | C4: Marque con una equis (X) si el sistema cumple con la función descrita | K4: Cumplidos | L4: =COUNTIF(F12:F91,"X") -> 14
B5: NO | C5: Marque con una equis (X) si el sistema no cumple con la función descrita | K5: Porcentaje | L5: =PERCENTOF(L4,L3) -> #NAME?
B6: ADI | C6: Marque con una equis (X) si el sistema debe adicionar la función descrita
B7: Observaciones: | D7: Espacio para complementar respuestas
F9: Nivel de cumplimiento | I9: Observaciones
B10: REQUIRIMIENTOS FUNCIONALES DESCUENTOS ADMIN | F10: SI | G10: NO | H10: ADI
B12: 1 | C12: El sistema debe mostrar un listado de todos los descuentos y cupones en una tabla dentro de la sección “Descuentos”. | F12: X
B13: 2 | C13: La tabla debe mostrar por cada descuento: ID, Nombre, Tipo, Valor, Código, Puntos, Usos (actual/total o ilimitado), Estado y Acciones. | F13: X
B14: 3 | C14: El sistema debe mostrar tarjetas de resumen con: Total activos (descuentos disponibles), Total inactivos (descuentos pausados), Total canjes realizados y Puntos canjeados (puntos utilizados), con valores numéricos actualizados. | F14: X
B15: 4 | C15: El sistema debe permitir crear un nuevo descuento o cupón mediante el botón “+ Crear Descuento”. | F15: X
B16: 5 | C16: El sistema debe permitir buscar descuentos por nombre, descripción o código mediante un campo de búsqueda. | F16: X
B17: 6 | C17: El sistema debe permitir filtrar descuentos por tipo mediante un desplegable (por ejemplo “Todos los tipos”). | F17: X
B18: 7 | C18: El sistema debe permitir ordenar el listado (por ejemplo “Ordenar por nombre”) en orden ascendente o descendente. | F18: X
B19: 8 | C19: El sistema debe permitir ver el detalle de un descuento mediante el ícono de ojo en la columna Acciones. | F19: X
B20: 9 | C20: El sistema debe permitir editar un descuento existente mediante el ícono de lápiz en la columna Acciones. | F20: X
B21: 10 | C21: El sistema debe permitir activar o desactivar un descuento (cambiar estado) mediante el ícono de encendido en la columna Acciones. | F21: X
B22: 11 | C22: El sistema debe mostrar el estado de cada descuento (Activo / Inactivo) de forma clara, por ejemplo con badges. | F22: X
B23: 12 | C23: El sistema debe mostrar para cada descuento el número de usos actual y el límite (o indicación de usos ilimitados, p. ej. “∞”). | F23: X
... B25: 14 | C25: El sistema debe permitir navegar a otras secciones del admin desde el menú lateral y resaltar la sección “Descuentos” cuando el usuario está en ella. | F25: X

Sheet No-funcionales Descuentos Admin
B2: LISTADO DE REQUERIMIENTOS DE COMPRALO | K2: ESTADISTICAS
K3: Requirimientos | L3: =COUNT(B12:D93) -> 16
B4: SI | C4: Marque con una equis (X) si el sistema cumple con la función descrita | K4: Cumplidos | L4: =COUNTIF(F12:F93,"X") -> 16
B5: NO | C5: Marque con una equis (X) si el sistema no cumple con la función descrita | K5: Porcentaje | L5: =PERCENTOF(L4,L3) -> #NAME?
B6: ADI | C6: Marque con una equis (X) si el sistema debe adicionar la función descrita
B7: Observaciones: | D7: Espacio para complementar respuestas
F9: Nivel de cumplimiento | I9: Observaciones
B10: REQUIRIMIENTOS NO FUNCIONALES DESCUENTOS ADMIN | F10: SI | G10: NO | H10: ADI
B12: 1 | C12: La carga del listado de descuentos y de los contadores de resumen debe realizarse en un tiempo aceptable sin bloquear la interfaz. | F12: X
B13: 2 | C13: La búsqueda, el filtro por tipo y el ordenamiento deben responder con baja latencia para no degradar la experiencia del administrador. | F13: X
B14: 3 | C14: El diseño de la sección Descuentos debe ser coherente con el resto del dashboard (tema oscuro, tipografía, espaciados y componentes reutilizados). | F14: X
B15: 4 | C15: Los estados Activo e Inactivo deben distinguirse de forma clara por color y texto, de forma accesible. | F15: X
B16: 5 | C16: Los íconos de Acciones (ver, editar, activar/desactivar) deben ser reconocibles y usables en distintos tamaños de pantalla. | F16: X
B17: 6 | C17: El acceso a la sección Descuentos debe estar restringido a usuarios autenticados con rol de administrador (o el equivalente en el proyecto). | F17: X
B18: 7 | C18: Los datos mostrados (ID, nombre, tipo, valor, código, usos, estado) deben coincidir con los almacenados en la base de datos. | F18: X
B19: 8 | C19: La paginación y el cambio de “filas por página” deben mantener el contexto (búsqueda, filtro y orden aplicados) sin recargas bruscas. | F19: X
B20: 9 | C20: Los textos de la interfaz (títulos, columnas, tarjetas, botones, placeholders) deben estar en español y ser consistentes con el resto del sistema. | F20: X
B21: 10 | C21: Los contadores del resumen (activos, inactivos, canjes, puntos canjeados) deben ser coherentes con el listado y con la lógica de negocio. | F21: X
B22: 11 | C22: La sección debe cumplir criterios básicos de accesibilidad: contraste, foco visible y navegación por teclado en elementos interactivos. | F22: X
B23: 12 | C23: Las operaciones de crear, editar o cambiar estado no deben bloquear el resto del dashboard ni provocar pérdida de contexto sin aviso. | F23: X
... B27: 16 | C27: Con un número creciente de descuentos, el uso de paginación, búsqueda y filtros debe permitir gestionar el listado sin degradación notable del rendimiento. | F27: X

Sheet Funcionales Puntos Admin
B2: LISTADO DE REQUERIMIENTOS DE COMPRALO | K2: ESTADISTICAS
K3: Requirimientos | L3: =COUNT(B12:D80) -> 13
B4: SI | C4: Marque con una equis (X) si el sistema cumple con la función descrita | K4: Cumplidos | L4: =COUNTIF(F12:F80,"X") -> 13
B5: NO | C5: Marque con una equis (X) si el sistema no cumple con la función descrita | K5: Porcentaje | L5: =PERCENTOF(L4,L3) -> #NAME?
B6: ADI | C6: Marque con una equis (X) si el sistema debe adicionar la función descrita
B7: Observaciones: | D7: Espacio para complementar respuestas
F9: Nivel de cumplimiento | I9: Observaciones
B10: REQUIRIMIENTOS FUNCIONALES PUNTOS ADMIN | F10: SI | G10: NO | H10: ADI
B12: 1 | C12: El sistema debe mostrar la tasa actual del sistema de puntos (por ejemplo “$1500 = 1 punto”) en una tarjeta visible para el administrador. | F12: X
B13: 2 | C13: El sistema debe mostrar la fecha de inicio de la configuración de puntos y, si aplica, que no tiene fecha de fin (“Sin fecha”). | F13: X
B14: 3 | C14: El sistema debe mostrar el estado actual de la configuración de puntos (por ejemplo “Activo”) junto con la fecha en que fue creada. | F14: X
B15: 4 | C15: El sistema debe mostrar el total de usuarios que participan en el sistema de puntos en una tarjeta de resumen. | F15: X
